Workbook
Name _ftn1: 'Gráfico 13'!#REF!
Name _ftn1: 'Gráfico 15'!#REF!
Name _ftn1: 'Gráfico 16'!#REF!
Name _ftn1: 'Gráfico 17'!#REF!
Name _ftn1: 'Gráfico 18'!#REF!
Name _ftn1: 'Gráfico 19'!#REF!
Name _ftn1: 'Gráfico 20'!#REF!
Name _ftn1: 'Gráfico 21'!#REF!
Name _ftn1: 'Gráfico 3'!#REF!
Name _ftn1: 'Gráfico 4'!#REF!
Name _ftn1: 'Gráfico 5'!#REF!
Name _ftn1: 'Gráfico 6'!#REF!
Name _ftn1: 'Gráfico 8'!#REF!
Name _ftn1: 'Gráfico 9'!#REF!
Name _ftn1: 'Ilustración 20'!#REF!
Name _ftn1: 'Ilustración 21'!#REF!
Name _ftn1: 'Ilustración 22'!#REF!
Name _ftn1: 'Tabla 100'!#REF!
Name _ftn1: 'Tabla 101'!#REF!
Name _ftn1: 'Tabla 105'!#REF!
Name _ftn1: 'Tabla 108'!#REF!
Name _ftn1: 'Tabla 110'!#REF!
Name _ftn1: 'Tabla 111'!#REF!
Name _ftn1: 'Tabla 112'!#REF!
Name _ftn1: 'Tabla 113'!#REF!
Name _ftn1: 'Tabla 114'!#REF!
Name _ftn1: 'Tabla 115'!#REF!
Name _ftn1: 'Tabla 116'!#REF!
Name _ftn1: 'Tabla 121'!#REF!
Name _ftn1: 'Tabla 122'!#REF!
Name _ftn1: 'Tabla 123'!#REF!
Name _ftn1: 'Tabla 126'!#REF!
Name _ftn1: 'Tabla 127'!#REF!
Name _ftn1: 'Tabla 131'!#REF!
Name _ftn1: 'Tabla 132'!#REF!
Name _ftn1: 'Tabla 133'!#REF!
Name _ftn1: 'Tabla 134'!#REF!
Name _ftn1: 'Tabla 135'!#REF!
Name _ftn1: 'Tabla 136'!#REF!
Name _ftn1: 'Tabla 137'!#REF!
Name _ftn1: 'Tabla 138'!#REF!
Name _ftn1: 'Tabla 139'!#REF!
Name _ftn1: 'Tabla 144'!#REF!
Name _ftn1: 'Tabla 145'!#REF!
Name _ftn1: 'Tabla 147'!#REF!
Name _ftn1: 'Tabla 148'!#REF!
Name _ftn1: 'Tabla 149'!#REF!
Name _ftn1: 'Tabla 150'!#REF!
Name _ftn1: 'Tabla 151'!#REF!
Name _ftn1: 'Tabla 152'!#REF!
Name _ftn1: 'Tabla 153'!#REF!
Name _ftn1: 'Tabla 154'!#REF!
Name _ftn1: 'Tabla 156'!#REF!
Name _ftn1: 'Tabla 157'!#REF!
Name _ftn1: 'Tabla 159'!#REF!
Name _ftn1: 'Tabla 161'!#REF!
Name _ftn1: 'Tabla 164'!#REF!
Name _ftn1: 'Tabla 165'!#REF!
Name _ftn1: 'Tabla 166'!#REF!
Name _ftn1: 'Tabla 167'!#REF!

Sheet Respaldo
A1: No | B1: Factor | C1: SUBCAPÍTULO/CARACTERÍSTICA | D1: Tabla No | E1: Gráfico | F1: Nombre | G1: Fuente | H1: Responsable Información | I1: Enlace
A2: 1 | B2: CONTEXTO INSTITUCIONAL | C2: Cifras institucionales | D2: 1 | F2: Evolución de la oferta académica de la Sede Bogotá en el quinquenio | G2: DAC | H2: Hector pérez | I2: Sebastián Diaz
A3: 2 | B3: CONTEXTO INSTITUCIONAL | C3: Cifras institucionales | D3: 2 | F3: Distribución de la oferta académica por facultades | G3: DAC | H3: Hector pérez | I3: Sebastián Diaz
A4: 3 | B4: CONTEXTO INSTITUCIONAL | C4: Cifras institucionales | D4: 3 | F4: Programas acreditados en alta calidad en la Sede Bogotá | G4: DAC | H4: Hector pérez | I4: Sebastián Diaz
A5: 4 | B5: CONTEXTO INSTITUCIONAL | C5: Cifras institucionales | D5: 4 | F5: Programas con informe de autoevaluación radicado en CNA | G5: DAC | H5: Hector pérez | I5: Sebastián Diaz
A6: 5 | B6: CONTEXTO INSTITUCIONAL | C6: Cifras institucionales | D6: 5 | F6: Programas con condiciones iniciales aprobadas | G6: DAC | H6: Hector pérez | I6: Sebastián Diaz
A7: 6 | B7: CONTEXTO INSTITUCIONAL | C7: Cifras institucionales | D7: 6 | F7: Matrícula de estudiantes 2019-2 a 2024-1 | G7: Datos y Analítica | H7: Javier Mendieta | I7: Maylor Sabio
A8: 7 | B8: CONTEXTO INSTITUCIONAL | C8: Cifras institucionales | E8: 1 | F8: Profesores por dedicación 2019-2 a 2024-1 | G8: Dirección de Docencia | H8: Lina Giraldo | I8: Ángela Ramírez
A9: 8 | B9: CONTEXTO INSTITUCIONAL | C9: Cifras institucionales | E9: 2 | F9: Profesores por nivel de formación | G9: Dirección de Docencia | H9: Lina Giraldo | I9: Ángela Ramírez
A10: 9 | B10: CONTEXTO INSTITUCIONAL | C10: Cifras institucionales | D10: 7 | F10: Graduados por nivel de formación y modalidad 2019-2 a 2024-1 | G10: Datos y Analítica | H10: Javier Mendieta | I10: Maylor Sabio
A11: 10 | B11: CONTEXTO INSTITUCIONAL | C11: Cifras institucionales | D11: 8 | F11: Grupos de investigación categorizados en Ministerio de Ciencias, Tecnología e Innovación Minciencias | G11: Dir Investigación | H11: Jenny Hernández | I11: David Ricciulli
A12: 11 | B12: CONTEXTO INSTITUCIONAL | C12: Cifras institucionales | D12: 9 | F12: Investigadores categorizados Minciencias | G12: Dir Investigación | H12: Jenny Hernández | I12: David Ricciulli
A13: 12 | B13: CONTEXTO INSTITUCIONAL | C13: Cifras institucionales | D13: 10 | F13: Semilleros por facultad 2019-2- a 2024-1 | G13: Dir Investigación | H13: Jenny Hernández | I13: David Ricciulli
A14: 13 | B14: FACTOR 1. Identidad institucional | C14: Característica 3. Formación integral y construcción de identidad | D14: 23 | F14: Resultados de las acciones de formación integral | G14: DAC | H14: Hector pérez | I14: Carlos Rincón
A15: 14 | B15: FACTOR 1. Identidad institucional | C15: Característica 6. Rendición de cuentas | D15: 29 | F15: Visualizaciones del informe de sostenibilidad anual | G15: Gerencia de Planeación y Gestión | H15: Liliana Bernal | I15: Camilo Chacón
A16: 15 | B16: FACTOR 3. Desarrollo, gestión y sostenibilidad institucional | C16: Característica 7. Administración y Gestión | D16: 32 | F16: Personal administrativo beneficiado con políticas de estímulos 2019-2 a 2024-1 | G16: Gerencia Talento HUmano | H16: Andrea Carmona | I16: Francy Lineth Castrillón
A17: 16 | B17: FACTOR 3. Desarrollo, gestión y sostenibilidad institucional | C17: Característica 7. Administración y Gestión | D17: 33 | F17: Participación de administrativos en formación | G17: Gerencia Talento HUmano | H17: Andrea Carmona | I17: Francy Lineth Castrillón
A18: 17 | B18: FACTOR 3. Desarrollo, gestión y sostenibilidad institucional | C18: Característica 7. Administración y Gestión | D18: 34 | F18: Ascensos en la planta administrativa | G18: Gerencia Talento HUmano | H18: Mónica Avendaño | I18: Mónica Avendaño
A19: 18 | B19: FACTOR 3. Desarrollo, gestión y sostenibilidad institucional | C19: Característica 8. Procesos de COmunicación | E19: Ilustración 20 | F19: Frecuencia de uso de medios de comunicación para informarse | G19: Gerencia de Mercadeo / Estudio Brand equity Kanta | H19: Nestor Ivan Moreno | I19: Laura Barrera
A20: 19 | B20: FACTOR 3. Desarrollo, gestión y sostenibilidad institucional | C20: Característica 8. Procesos de COmunicación | E20: Ilustración 21 | F20: Medios destacados para el Poli | G20: Gerencia de Mercadeo / Estudio Brand equity Kanta | H20: Nestor Ivan Moreno | I20: Laura Barrera
A21: 20 | B21: FACTOR 3. Desarrollo, gestión y sostenibilidad institucional | C21: Característica 8. Procesos de COmunicación | E21: Ilustración 22 | F21: Alcance de personas en Redes sociales cuentas del Poli | G21: Dirección de marca | H21: Nestor Ivan Moreno | I21: Laura Barrera
A22: 21 | B22: FACTOR 3. Desarrollo, gestión y sostenibilidad institucional | C22: Característica 8. Procesos de COmunicación | D22: 36 | F22: Leads obtenidos año a año por canal en el Poli | G22: Dirección de marca | H22: Nestor Ivan Moreno | I22: Laura Barrera
A23: 22 | B23: FACTOR 3. Desarrollo, gestión y sostenibilidad institucional | C23: Característica 10. Recursos de apoyo académico | D23: 39 | F23: Tipología de recursos documentales en la Biblioteca | G23: Dirección de Bibliotecas | H23: Carmen Romero | I23: Elizabeth Rodríguez Mora
A24: 23 | B24: FACTOR 3. Desarrollo, gestión y sostenibilidad institucional | C24: Característica 10. Recursos de apoyo académico | D24: 40 | F24: Libros por área de conocimiento | G24: Dirección de Bibliotecas | H24: Carmen Romero | I24: Elizabeth Rodríguez Mora
A25: 24 | B25: FACTOR 3. Desarrollo, gestión y sostenibilidad institucional | C25: Característica 10. Recursos de apoyo académico | D25: 41 | F25: Revistas por área de conocimiento | G25: Dirección de Bibliotecas | H25: Carmen Romero | I25: Elizabeth Rodríguez Mora
A26: 25 | B26: FACTOR 3. Desarrollo, gestión y sostenibilidad institucional | C26: Característica 10. Recursos de apoyo académico | D26: 42 | F26: Recursos bibliográficos 2019-2 a 2024-1 | G26: Dirección de Bibliotecas | H26: Carmen Romero | I26: Elizabeth Rodríguez Mora
A27: 26 | B27: FACTOR 3. Desarrollo, gestión y sostenibilidad institucional | C27: Característica 10. Recursos de apoyo académico | D27: 43 | F27: Uso de los Recursos Bibliográficos 2019-2 a 2024-1 | G27: Dirección de Bibliotecas | H27: Carmen Romero | I27: Elizabeth Rodríguez Mora
A28: 27 | B28: FACTOR 3. Desarrollo, gestión y sostenibilidad institucional | C28: Característica 10. Recursos de apoyo académico | D28: 44 | F28: Divulgación periódica revistas | G28: Editorial | H28: Eduardo Norman Acevedo | I28: Guillermo Alberto González
A29: 28 | B29: FACTOR 3. Desarrollo, gestión y sostenibilidad institucional | C29: Característica 10. Recursos de apoyo académico | E29: 3 | F29: Estado de los ambientes inmersivos | G29: Secretaría Académica y de Extensión | H29: Luis Martín Trujillo | I29: Luis Martín Trujillo
A30: 29 | B30: FACTOR 3. Desarrollo, gestión y sostenibilidad institucional | C30: Característica 10. Recursos de apoyo académico | D30: 45 | F30: Ambientes inmersivos registrados a nombre del Politécnico Grancolombiano | G30: Secretaría Académica y de Extensión | H30: Luis Martín Trujillo | I30: Luis Martín Trujillo
A31: 30 | B31: FACTOR 3. Desarrollo, gestión y sostenibilidad institucional | C31: Característica 10. Recursos de apoyo académico | D31: 46 | F31: Histórico de la salida a los estudiantes de los diferentes ambientes | G31: Secretaría Académica y de Extensión | H31: Luis Martín Trujillo | I31: Luis Martín Trujillo
A32: 31 | B32: FACTOR 3. Desarrollo, gestión y sostenibilidad institucional | C32: Característica 10. Recursos de apoyo académico | D32: 47 | F32: Uso de los ambientes inmersivos por los estudiantes Poli | G32: Secretaría Académica y de Extensión | H32: Luis Martín Trujillo | I32: Luis Martín Trujillo
A33: 32 | B33: FACTOR 3. Desarrollo, gestión y sostenibilidad institucional | C33: Característica 10. Recursos de apoyo académico | D33: 48 | F33: Distribución de los MI-Books por facultades | G33: Secretaría Académica y de Extensión | H33: Luis Martín Trujillo | I33: Luis Martín Trujillo
A34: 33 | B34: FACTOR 3. Desarrollo, gestión y sostenibilidad institucional | C34: Característica 10. Recursos de apoyo académico | E34: 4 | F34: Medición uso recorridos | G34: Secretaría Académica y de Extensión | H34: Luis Martín Trujillo | I34: Luis Martín Trujillo
A35: 34 | B35: FACTOR 3. Desarrollo, gestión y sostenibilidad institucional | C35: Característica 10. Recursos de apoyo académico | D35: 49 | F35: Visitas MI-Books por país | G35: Secretaría Académica y de Extensión | H35: Luis Martín Trujillo | I35: Luis Martín Trujillo
A36: 35 | B36: FACTOR 3. Desarrollo, gestión y sostenibilidad institucional | C36: Característica 10. Recursos de apoyo académico | D36: 53 | F36: Talleres y laboratorios de la Institución | G36: Dirección de Infraestructura | H36: Raul Ricardo Cortes Rincón | I36: Edith marthza Nino
A37: 36 | B37: FACTOR 3. Desarrollo, gestión y sostenibilidad institucional | C37: Característica 10. Recursos de apoyo académico | E37: 5 | F37: Sitios de práctica | G37: Dir Graduados y Proyección Empresarial | H37: Luis Miguel Corredor | I37: Luis Miguel Corredor
A38: 37 | B38: FACTOR 3. Desarrollo, gestión y sostenibilidad institucional | C38: Característica 11. Infraestructura Física y Tecnológica | D38: 55 | F38: Infraestructura física del Poli | G38: Dirección de Infraestructura | H38: Raul Ricardo Cortes Rincón | I38: Edith marthza Nino
A39: 38 | B39: FACTOR 3. Desarrollo, gestión y sostenibilidad institucional | C39: Característica 11. Infraestructura Física y Tecnológica | D39: 57 | F39: Infraestructura física 2019-2 a 2024-1 | G39: Dirección de Infraestructura | H39: Raul Ricardo Cortes Rincón | I39: Edith marthza Nino
A40: 39 | B40: FACTOR 3. Desarrollo, gestión y sostenibilidad institucional | C40: Característica 11. Infraestructura Física y Tecnológica | D40: 58 | F40: Infraestructura Tecnológica 2019-2 a 2024-1 | G40: Dirección de Infraestructura | H40: Uriel Mejia Terán | I40: Iván Diaz / Diana García
A41: 40 | B41: FACTOR 3. Desarrollo, gestión y sostenibilidad institucional | C41: Característica 12. recursos y gestión Financiera | D41: 61 | F41: Ingresos operacionales de la Institución | G41: Planeación Financiera | H41: Diana Baquero | I41: Diana Baquero
A42: 41 | B42: FACTOR 3. Desarrollo, gestión y sostenibilidad institucional | C42: Característica 12. recursos y gestión Financiera | D42: 62 | F42: Fuentes de financiamiento internas y externas de la Institución | G42: Planeación Financiera | H42: Diana Baquero | I42: Diana Baquero
A43: 42 | B43: FACTOR 3. Desarrollo, gestión y sostenibilidad institucional | C43: Característica 12. recursos y gestión Financiera | D43: 63 | F43: Comportamiento de excedentes operacional y neto | G43: Planeación Financiera | H43: Diana Baquero | I43: Diana Baquero
A44: 43 | B44: FACTOR 3. Desarrollo, gestión y sostenibilidad institucional | C44: Característica 12. recursos y gestión Financiera | D44: 64 | F44: Evolución y composición del patrimonio | G44: Planeación Financiera | H44: Diana Baquero | I44: Diana Baquero
A45: 44 | B45: FACTOR 3. Desarrollo, gestión y sostenibilidad institucional | C45: Característica 12. recursos y gestión Financiera | D45: 65 | F45: Evolución y composición del activo | G45: Planeación Financiera | H45: Diana Baquero | I45: Diana Baquero
A46: 45 | B46: FACTOR 3. Desarrollo, gestión y sostenibilidad institucional | C46: Característica 12. recursos y gestión Financiera | D46: 66 | F46: Evolución del estado de la situación financiera | G46: Planeación Financiera | H46: Diana Baquero | I46: Diana Baquero
A47: 46 | B47: FACTOR 3. Desarrollo, gestión y sostenibilidad institucional | C47: Característica 12. recursos y gestión Financiera | D47: 67 | F47: inversiones realizadas en torno al plan de mejoramiento | G47: Planeación Financiera | H47: Diana Baquero | I47: Diana Baquero
A48: 47 | B48: FACTOR 3. Desarrollo, gestión y sostenibilidad institucional | C48: Característica 12. recursos y gestión Financiera | E48: 6 | F48: Liquidez y Capital de Trabajo | G48: Planeación Financiera | H48: Diana Baquero | I48: Diana Baquero
A49: 48 | B49: FACTOR 3. Desarrollo, gestión y sostenibilidad institucional | C49: Característica 12. recursos y gestión Financiera | D49: 68 | F49: Inversiones misionales de la Institución | G49: Planeación Financiera | H49: Diana Baquero | I49: Diana Baquero
A50: 49 | B50: FACTOR 3. Desarrollo, gestión y sostenibilidad institucional | C50: Característica 12. recursos y gestión Financiera | D50: 69 | F50: Inversiones en bienestar | G50: Planeación Financiera | H50: Diana Baquero | I50: Diana Baquero
A51: 50 | B51: FACTOR 3. Desarrollo, gestión y sostenibilidad institucional | C51: Característica 12. recursos y gestión Financiera | D51: 70 | F51: Inversiones en proyección social | G51: Planeación Financiera | H51: Diana Baquero | I51: Diana Baquero
A52: 51 | B52: FACTOR 3. Desarrollo, gestión y sostenibilidad institucional | C52: Característica 12. recursos y gestión Financiera | D52: 71 | F52: Inversión en investigación | G52: Planeación Financiera | H52: Diana Baquero | I52: Diana Baquero
A53: 52 | B53: FACTOR 3. Desarrollo, gestión y sostenibilidad institucional | C53: Característica 12. recursos y gestión Financiera | D53: 72 | F53: Inversión en internacionalización | G53: Planeación Financiera | H53: Diana Baquero | I53: Diana Baquero
A54: 53 | B54: FACTOR 3. Desarrollo, gestión y sostenibilidad institucional | C54: Característica 12. recursos y gestión Financiera | D54: 73 | F54: Inversión en Docencia | G54: Planeación Financiera | H54: Diana Baquero | I54: Diana Baquero
A55: 54 | B55: FACTOR 3. Desarrollo, gestión y sostenibilidad institucional | C55: Característica 12. recursos y gestión Financiera | E55: 8 | F55: Ingresos Por extensión | G55: Planeación Financiera | H55: Diana Baquero | I55: Diana Baquero
A56: 55 | B56: FACTOR 3. Desarrollo, gestión y sostenibilidad institucional | C56: Característica 12. recursos y gestión Financiera | D56: 74 | F56: Inversión en Infraestructura | G56: Planeación Financiera | H56: Diana Baquero | I56: Diana Baquero
A57: 56 | B57: FACTOR 3. Desarrollo, gestión y sostenibilidad institucional | C57: Característica 12. recursos y gestión Financiera | D57: 75 | F57: Inversión en Infraestructura tecnológica | G57: Planeación Financiera | H57: Diana Baquero | I57: Diana Baquero
A58: 57 | B58: FACTOR 3. Desarrollo, gestión y sostenibilidad institucional | C58: Característica 12. recursos y gestión Financiera | D58: 76 | F58: Inversión en contenidos virtuales | G58: Planeación Financiera | H58: Diana Baquero | I58: Diana Baquero
A59: 58 | B59: FACTOR 3. Desarrollo, gestión y sostenibilidad institucional | C59: Característica 12. recursos y gestión Financiera | D59: 77 | F59: Inversión en Medios Audiovisuales y Biblioteca | G59: Planeación Financiera | H59: Diana Baquero | I59: Diana Baquero
A60: 59 | B60: FACTOR 4. Mejoramiento continuo y Autoregulación | C60: Característica 14. procesos de Autorregulación | D60: 82 | F60: Proyectos finalizados | G60: Gerencia de Planeación y Gestión | H60: Liliana Bernal | I60: Rubén Dario Gelvez
A61: 60 | B61: FACTOR 4. Mejoramiento continuo y Autoregulación | C61: Característica 14. procesos de Autorregulación | D61: 83 | F61: Proyectos en ejecución | G61: Gerencia de Planeación y Gestión | H61: Liliana Bernal | I61: Rubén Dario Gelvez
A62: 61 | B62: FACTOR 4. Mejoramiento continuo y Autoregulación | C62: Característica 16. Evaluación de directivas, profesores y personal administrativo | D62: 85 | F62: Procesos formación permanente desarrollados desde el SIAC | G62: DAC | H62: Hector pérez | I62: Sebastián Diaz
A63: 62 | B63: FACTOR 4. Mejoramiento continuo y Autoregulación | C63: Característica 16. Evaluación de directivas, profesores y personal administrativo | D63: 87 | F63: Resultados de la evaluación de administrativos | G63: Dirección de Formación | H63: Andrea Carmona | I63: Francy Lineth Castrillón
A64: 63 | B64: FACTOR 4. Mejoramiento continuo y Autoregulación | C64: Característica 16. Evaluación de directivas, profesores y personal administrativo | E64: 9 | F64: Resultados de la evaluación de profesores | G64: Dirección de Formación | H64: Lina Giraldo | I64: Ángela Ramírez
A65: 64 | B65: FACTOR 5. Estructura y procesos académicos | C65: Característica 18. Componentes pedagógicos y de evaluación | D65: 98 | F65: Formación a equipos curriculares encargados de la declaración y formulación de resultados de aprendizaje | G65: Dirección de currículo | H65: Maria Isabel Cortes | I65: Diana Shirley Velasquez
A66: 65 | B66: FACTOR 5. Estructura y procesos académicos | C66: Característica 18. Componentes pedagógicos y de evaluación | D66: 99 | F66: Formación para declarar indicadores de logro | G66: Dirección de currículo | H66: Maria Isabel Cortes | I66: Diana Shirley Velasquez
A67: 66 | B67: FACTOR 5. Estructura y procesos académicos | C67: Característica 18. Componentes pedagógicos y de evaluación | D67: 100 | F67: Participación de profesores formación del Modelo Institucional de Resultados de Aprendizaje | G67: Dirección de currículo | H67: Maria Isabel Cortes | I67: Diana Shirley Velasquez
A68: 67 | B68: FACTOR 5. Estructura y procesos académicos | C68: Característica 18. Componentes pedagógicos y de evaluación | D68: 101 | F68: Participación de profesores en el plan de cualificación institucional | G68: Dirección de currículo | H68: Andrea Carmona | I68: Francy Lineth Castrillón
A69: 68 | B69: FACTOR 5. Estructura y procesos académicos | C69: Característica 20. Procesos de creación, modificación y ampliación de programas académicos | D69: 105 | F69: Evolución de la nueva oferta 2019-2024 | G69: DAC | H69: Hector pérez | I69: Sebastián Diaz
A70: 69 | B70: FACTOR 6. Aportes de la investigación, la innovación, el desarrollo tecnológico y la creación al entorno | C70: Característica 21. Formación para la investigación, creación e innovación | D70: 108 | F70: Estudiantes en actividades de investigación 2019 a 2024-1 | G70: Dir Investigación | H70: Jenny Hernández | I70: David Ricciulli
A71: 70 | B71: FACTOR 6. Aportes de la investigación, la innovación, el desarrollo tecnológico y la creación al entorno | C71: Característica 22. Investigación, desarrollo tecnológico, innovación y creación | D71: 110 | F71: Resultado de los grupos institucionales en la Convocatoria de Medición de Grupos e Investigadores 894 | G71: Dir Investigación | H71: Jenny Hernández | I71: David Ricciulli
A72: 71 | B72: FACTOR 6. Aportes de la investigación, la innovación, el desarrollo tecnológico y la creación al entorno | C72: Característica 22. Investigación, desarrollo tecnológico, innovación y creación | D72: 111 | F72: Investigadores categorizados por área en la Convocatoria de Medición de Grupos e Investigadores 894 | G72: Dir Investigación | H72: Jenny Hernández | I72: David Ricciulli
A73: 72 | B73: FACTOR 6. Aportes de la investigación, la innovación, el desarrollo tecnológico y la creación al entorno | C73: Característica 22. Investigación, desarrollo tecnológico, innovación y creación | D73: 112 | F73: Profesores en capacitaciones de investigación durante el quinquenio | G73: Dir Investigación | H73: Jenny Hernández | I73: David Ricciulli
A74: 73 | B74: FACTOR 6. Aportes de la investigación, la innovación, el desarrollo tecnológico y la creación al entorno | C74: Característica 22. Investigación, desarrollo tecnológico, innovación y creación | D74: 113 | F74: Estímulos por productividad de alto impacto entregados a profesores | G74: Dir Investigación | H74: Jenny Hernández | I74: David Ricciulli
A75: 74 | B75: FACTOR 6. Aportes de la investigación, la innovación, el desarrollo tecnológico y la creación al entorno | C75: Característica 22. Investigación, desarrollo tecnológico, innovación y creación | D75: 114 | F75: Número de Proyectos de investigación 2019-2024 | G75: Dir Investigación | H75: Jenny Hernández | I75: David Ricciulli
A76: 75 | B76: FACTOR 6. Aportes de la investigación, la innovación, el desarrollo tecnológico y la creación al entorno | C76: Característica 22. Investigación, desarrollo tecnológico, innovación y creación | D76: 115 | F76: Número de Proyectos con obtención de recursos externos | G76: Dir Investigación | H76: Jenny Hernández | I76: David Ricciulli
... A82: 81 | B82: FACTOR 7. Impacto Social | C82: Característica 23. Institución y entorno | D82: 127 | F82: Estudiantes que realizan práctica profesional de acuerdo con los tipos de vinculación 2019-2 a 2024-1 | G82: Dir Graduados y Proyección Empresarial | H82: Luis Miguel Corredor | I82: Luis Miguel Corredor
A83: 82 | B83: FACTOR 7. Impacto Social | C83: Característica 23. Institución y entorno | E83: 13 | F83: Estudiantes modalidad virtual que han realizado practicas pedagógicas entre 2019-2024 | G83: Dir Graduados y Proyección Empresarial | H83: Luis Miguel Corredor | I83: Luis Miguel Corredor
A84: 83 | B84: FACTOR 7. Impacto Social | C84: Característica 23. Institución y entorno | D84: 131 | F84: Estudiantes modalidad presencial y virtual que han realizado prácticas educativas del programa de Psicología entre 2019-2024 | G84: Dir Graduados y Proyección Empresarial | H84: Luis Miguel Corredor | I84: Luis Miguel Corredor
A85: 84 | B85: FACTOR 7. Impacto Social | C85: Característica 23. Institución y entorno | D85: 132 | F85: Estudiantes modalidad presencial y virtual que han realizado prácticas en el consultorio tributario y empresarial entre 2019-2024 | G85: Consultorio Tributario y Empresarial | H85: Luis Miguel Corredor | I85: Luis Miguel Corredor
A86: 85 | B86: FACTOR 7. Impacto Social | C86: Característica 23. Institución y entorno | D86: 133 | F86: Estudiantes en modalidad presencial que han realizado prácticas entre 2019-2024 | G86: Dir Graduados y Proyección Empresarial | H86: Luis Miguel Corredor | I86: Luis Miguel Corredor
A87: 86 | B87: FACTOR 7. Impacto Social | C87: Característica 23. Institución y entorno | D87: 134 | F87: Estudiantes de modalidad presencial que han realizado prácticas en la Agencia Trompo entre 2019-2024 | G87: Dir Graduados y Proyección Empresarial | H87: Luis Miguel Corredor | I87: Luis Miguel Corredor
A88: 87 | B88: FACTOR 7. Impacto Social | C88: Característica 23. Institución y entorno | D88: 135 | F88: Histórico de Becas otorgadas por el Poli entre 2019-2 y 2024-1 | G88: Dirección de Bienestar | H88: Juan Carlos Rivera | I88: Lina Vanessa gonzález
A89: 88 | B89: FACTOR 7. Impacto Social | C89: Característica 23. Institución y entorno | E89: 15 | F89: Usuarios que han tomado el servicio de transporte desde 2019 a 2024-1 | G89: Servicios Administrativos | H89: Gustavo Espinel | I89: Gustavo Espinel
A90: 89 | B90: FACTOR 7. Impacto Social | C90: Característica 23. Institución y entorno | D90: 136 | F90: Investigación asociada a proyección social 2019-1 a 2024-1 | G90: Dir Investigación | H90: Jenny Hernández | I90: David Ricciulli
A91: 90 | B91: FACTOR 7. Impacto Social | C91: Característica 23. Institución y entorno | D91: 137 | F91: Actividad y población impactada entre 2020-2023 | G91: Escuela de Educación e Innovación | H91: Gerardo Machuca | I91: Gerardo Machuca
A92: 91 | B92: FACTOR 7. Impacto Social | C92: Característica 23. Institución y entorno | D92: 138 | F92: Semilleros asociados a proyección social 2019-2024-1 | G92: Dir Investigación | H92: Jenny Hernández | I92: David Ricciulli /Maria alejandra Tequia
A93: 92 | B93: FACTOR 7. Impacto Social | C93: Característica 23. Institución y entorno | D93: 139 | F93: Trabajos de grado que han aportado a la solución de problemas en el entorno | G93: **** | H93: Carlos Augusto García | I93: Mary Natalia Ortegón
A94: 93 | B94: FACTOR 8. Visibilidad nacional e internacional | C94: Característica 25. Inserción de la Institución en contextos académicos nacionales e internacionales | D94: 144 | F94: Convenios por países | G94: Dirección de Relaciones Internacionales e Interinstitucionales | H94: Raquel Breton | I94: Raquel Breton
A95: 94 | B95: FACTOR 8. Visibilidad nacional e internacional | C95: Característica 25. Inserción de la Institución en contextos académicos nacionales e internacionales | D95: 145 | F95: Número de clases espejo y estudiantes que participaron en estos espacios | G95: Dirección de Relaciones Internacionales e Interinstitucionales | H95: Raquel Breton | I95: Raquel Breton
A96: 95 | B96: FACTOR 8. Visibilidad nacional e internacional | C96: Característica 25. Inserción de la Institución en contextos académicos nacionales e internacionales | D96: 147 | F96: Número de estudiantes con reconocimientos académicos por medio de seminarios internacionales virtuales, doble titulación, intercambio virtual | G96: Dirección de Relaciones Internacionales e Interinstitucionales | H96: Raquel Breton | I96: Raquel Breton
A97: 96 | B97: FACTOR 8. Visibilidad nacional e internacional | C97: Característica 25. Inserción de la Institución en contextos académicos nacionales e internacionales | D97: 148 | F97: Número de profesores y expertos invitados | G97: Dirección de Relaciones Internacionales e Interinstitucionales | H97: Raquel Breton | I97: Raquel Breton
A98: 97 | B98: FACTOR 8. Visibilidad nacional e internacional | C98: Característica 25. Inserción de la Institución en contextos académicos nacionales e internacionales | D98: 149 | F98: Número de estudiantes en internacionalización en casa | G98: Dirección de Relaciones Internacionales e Interinstitucionales | H98: Raquel Breton | I98: Raquel Breton
A99: 98 | B99: FACTOR 8. Visibilidad nacional e internacional | C99: Característica 25. Inserción de la Institución en contextos académicos nacionales e internacionales | D99: 150 | F99: Número de estudiantes en cursos de idiomas | G99: Dirección de Relaciones Internacionales e Interinstitucionales | H99: Raquel Breton | I99: Raquel Breton
A100: 99 | B100: FACTOR 8. Visibilidad nacional e internacional | C100: Característica 25. Inserción de la Institución en contextos académicos nacionales e internacionales | D100: 151 | F100: Número de convenios con ICETEX para asistentes extranjeros | G100: Dirección de Relaciones Internacionales e Interinstitucionales | H100: Raquel Breton | I100: Raquel Breton
A101: 100 | B101: FACTOR 8. Visibilidad nacional e internacional | C101: Característica 25. Inserción de la Institución en contextos académicos nacionales e internacionales | E101: 16 | F101: Evolución bilingüismo profesores | G101: Dirección de Formación | H101: Raquel Breton | I101: Raquel Breton
A102: 101 | B102: FACTOR 8. Visibilidad nacional e internacional | C102: Característica 25. Inserción de la Institución en contextos académicos nacionales e internacionales | D102: 152 | F102: Número de eventos académicos desde y para la academia | G102: Dirección de Relaciones Internacionales e Interinstitucionales | H102: Raquel Breton | I102: Raquel Breton
A103: 102 | B103: FACTOR 8. Visibilidad nacional e internacional | C103: Característica 25. Inserción de la Institución en contextos académicos nacionales e internacionales | D103: 153 | F103: Contenido del Poli para otros | G103: Dirección de Relaciones Internacionales e Interinstitucionales | H103: Raquel Breton | I103: Raquel Breton
A104: 103 | B104: FACTOR 8. Visibilidad nacional e internacional | C104: Característica 25. Inserción de la Institución en contextos académicos nacionales e internacionales | D104: 154 | F104: Actividades en las regiones | G104: Dirección de Relaciones Internacionales e Interinstitucionales | H104: Raquel Breton | I104: Raquel Breton
A105: 104 | B105: FACTOR 8. Visibilidad nacional e internacional | C105: Característica 26. Relaciones externas de profesores y estudiantes | D105: 156 | F105: Cifras de movilidad saliente y entrante de estudiantes y profesores | G105: Dirección de Relaciones Internacionales e Interinstitucionales | H105: Raquel Breton | I105: Raquel Breton
...

Sheet Índice Tablas
A1: Factor | B1: SUBCAPÍTULO/CARACTERÍSTICA | C1: Orden | D1: Tabla No | E1: Gráfico | F1: Nombre | G1: Fuente | H1: Responsable Información | I1: Enlace | J1: Observaciones | BX1: Orden
A2: CONTEXTO INSTITUCIONAL | B2: Cifras institucionales | C2: 1 | D2: 1 | F2: Evolución de la oferta académica de la Sede Bogotá en el quinquenio | G2: DAC | H2: Hector pérez | I2: Sebastián Diaz | BX2: 1
A3: CONTEXTO INSTITUCIONAL | B3: Cifras institucionales | C3: 2 | D3: 2 | F3: Distribución de la oferta académica por facultades | G3: DAC | H3: Hector pérez | I3: Sebastián Diaz | BX3: 2
A4: CONTEXTO INSTITUCIONAL | B4: Cifras institucionales | C4: 3 | D4: 3 | F4: Programas acreditados en alta calidad en la Sede Bogotá | G4: DAC | H4: Hector pérez | I4: Sebastián Diaz | BX4: 3
A5: CONTEXTO INSTITUCIONAL | B5: Cifras institucionales | C5: 4 | D5: 4 | F5: Programas con informe de autoevaluación radicado en CNA | G5: DAC | H5: Hector pérez | I5: Sebastián Diaz | BX5: 4
A6: CONTEXTO INSTITUCIONAL | B6: Cifras institucionales | C6: 5 | D6: 5 | F6: Programas con condiciones iniciales aprobadas | G6: DAC | H6: Hector pérez | I6: Sebastián Diaz | BX6: 5
A7: CONTEXTO INSTITUCIONAL | B7: Cifras institucionales | C7: 6 | D7: 6 | F7: Matrícula de estudiantes 2019-2 a 2025-1 | G7: Datos y Analítica | H7: Javier Mendieta | I7: Maylor Sabio | BX7: 6
A8: CONTEXTO INSTITUCIONAL | B8: Cifras institucionales | C8: 7 | E8: 1 | F8: Profesores por dedicación 2019-2 a 2025-1 | G8: Dirección de Docencia | H8: Lina Giraldo | I8: Ángela Ramírez | BX8: 7
A9: CONTEXTO INSTITUCIONAL | B9: Cifras institucionales | C9: 8 | E9: 2 | F9: Profesores por nivel de formación | G9: Dirección de Docencia | H9: Lina Giraldo | I9: Ángela Ramírez | BX9: 8
A10: CONTEXTO INSTITUCIONAL | B10: Cifras institucionales | C10: 9 | D10: 7 | F10: Graduados por nivel de formación y modalidad 2019-2 a 2025-1 | G10: Datos y Analítica | H10: Javier Mendieta | I10: Maylor Sabio | BX10: 9
A11: CONTEXTO INSTITUCIONAL | B11: Cifras institucionales | C11: 10 | D11: 8 | F11: Grupos de investigación categorizados en Ministerio de Ciencias, Tecnología e Innovación Minciencias | G11: Dir Investigación | H11: Jenny Hernández | I11: David Ricciulli | J11: Nota: Se actualizan con los últimos resultados Convocatoria 957 | BX11: 10
A12: CONTEXTO INSTITUCIONAL | B12: Cifras institucionales | C12: 11 | D12: 9 | F12: Investigadores categorizados Minciencias | G12: Dir Investigación | H12: Jenny Hernández | I12: David Ricciulli | J12: Nota: Se actualizan con los últimos resultados Convocatoria 957 | BX12: 11
A13: CONTEXTO INSTITUCIONAL | B13: Cifras institucionales | C13: 12 | D13: 10 | F13: Semilleros por facultad 2019-2- a 2025-1 | G13: Dir Investigación | H13: Jenny Hernández | I13: David Ricciulli | BX13: 12
A14: FACTOR 1. Identidad institucional | B14: Característica 3. Formación integral y construcción de identidad | C14: 13 | D14: 23 | F14: Resultados de las acciones de formación integral | G14: DAC | H14: Hector pérez | I14: Carlos Rincón | BX14: 13
A15: FACTOR 1. Identidad institucional | B15: Característica 6. Rendición de cuentas | C15: 14 | D15: 29 | F15: Visualizaciones del informe de sostenibilidad anual | G15: Gerencia de Planeación y Gestión | H15: Liliana Bernal | I15: Camilo Chacón | BX15: 14
A16: FACTOR 3. Desarrollo, gestión y sostenibilidad institucional | B16: Característica 7. Administración y Gestión | C16: 15 | D16: 32 | F16: Personal administrativo beneficiado con políticas de estímulos 2019-2 a 2025-1 | G16: Gerencia Talento HUmano | H16: Andrea Carmona | I16: Francy Lineth Castrillón | BX16: 15
A17: FACTOR 3. Desarrollo, gestión y sostenibilidad institucional | B17: Característica 7. Administración y Gestión | C17: 16 | D17: 33 | F17: Participación de administrativos en formación | G17: Gerencia Talento HUmano | H17: Andrea Carmona | I17: Francy Lineth Castrillón | BX17: 16
A18: FACTOR 3. Desarrollo, gestión y sostenibilidad institucional | B18: Característica 7. Administración y Gestión | C18: 17 | D18: 34 | F18: Ascensos en la planta administrativa | G18: Gerencia Talento HUmano | H18: Mónica Avendaño | I18: Mónica Avendaño | BX18: 17
A19: FACTOR 3. Desarrollo, gestión y sostenibilidad institucional | B19: Característica 8. Procesos de COmunicación | C19: 18 | E19: Ilustración 20 | F19: Frecuencia de uso de medios de comunicación para informarse | G19: Gerencia de Mercadeo / Estudio Brand equity Kanta | H19: Nestor Ivan Moreno | I19: Laura Barrera | BX19: 18
A20: FACTOR 3. Desarrollo, gestión y sostenibilidad institucional | B20: Característica 8. Procesos de COmunicación | C20: 19 | E20: Ilustración 21 | F20: Medios destacados para el Poli | G20: Gerencia de Mercadeo / Estudio Brand equity | H20: Nestor Ivan Moreno | I20: Laura Barrera | BX20: 19
A21: FACTOR 3. Desarrollo, gestión y sostenibilidad institucional | B21: Característica 8. Procesos de COmunicación | C21: 20 | E21: Ilustración 22 | F21: Alcance de personas en Redes sociales cuentas del Poli | G21: Dirección de marca | H21: Nestor Ivan Moreno | I21: Laura Barrera | BX21: 20
A22: FACTOR 3. Desarrollo, gestión y sostenibilidad institucional | B22: Característica 8. Procesos de COmunicación | C22: 21 | D22: 36 | F22: Leads obtenidos año a año por canal en el Poli | G22: Dirección de marca | H22: Nestor Ivan Moreno | I22: Natalia Rincón | BX22: 21
A23: FACTOR 3. Desarrollo, gestión y sostenibilidad institucional | B23: Característica 10. Recursos de apoyo académico | C23: 22 | D23: 39 | F23: Tipología de recursos documentales en la Biblioteca 2025-1 | G23: Dirección de Bibliotecas | H23: Carmen Romero | I23: Elizabeth Rodríguez Mora | BX23: 22
A24: FACTOR 3. Desarrollo, gestión y sostenibilidad institucional | B24: Característica 10. Recursos de apoyo académico | C24: 23 | D24: 40 | F24: Libros por área de conocimiento | G24: Dirección de Bibliotecas | H24: Carmen Romero | I24: Elizabeth Rodríguez Mora | BX24: 23
A25: FACTOR 3. Desarrollo, gestión y sostenibilidad institucional | B25: Característica 10. Recursos de apoyo académico | C25: 24 | D25: 41 | F25: Revistas por área de conocimiento | G25: Dirección de Bibliotecas | H25: Carmen Romero | I25: Elizabeth Rodríguez Mora | BX25: 24
A26: FACTOR 3. Desarrollo, gestión y sostenibilidad institucional | B26: Característica 10. Recursos de apoyo académico | C26: 25 | D26: 42 | F26: Recursos bibliográficos 2019-2 a 2025-1 | G26: Dirección de Bibliotecas | H26: Carmen Romero | I26: Elizabeth Rodríguez Mora | BX26: 25
A27: FACTOR 3. Desarrollo, gestión y sostenibilidad institucional | B27: Característica 10. Recursos de apoyo académico | C27: 26 | D27: 43 | F27: Uso de los Recursos Bibliográficos 2019-2 a 2025-1 | G27: Dirección de Bibliotecas | H27: Carmen Romero | I27: Elizabeth Rodríguez Mora | BX27: 26
A28: FACTOR 3. Desarrollo, gestión y sostenibilidad institucional | B28: Característica 10. Recursos de apoyo académico | C28: 27 | D28: 44 | F28: Divulgación periódica revistas | G28: Editorial | H28: Guillermo Alberto González | I28: Guillermo Alberto González | BX28: 27
A29: FACTOR 3. Desarrollo, gestión y sostenibilidad institucional | B29: Característica 10. Recursos de apoyo académico | C29: 28 | E29: 3 | F29: Estado de los ambientes inmersivos | G29: Secretaría Académica y de Extensión | H29: Luis Martín Trujillo | I29: Luis Martín Trujillo | BX29: 28
A30: FACTOR 3. Desarrollo, gestión y sostenibilidad institucional | B30: Característica 10. Recursos de apoyo académico | C30: 29 | D30: 45 | F30: Ambientes inmersivos registrados a nombre del Politécnico Grancolombiano | G30: Secretaría Académica y de Extensión | H30: Luis Martín Trujillo | I30: Luis Martín Trujillo | BX30: 29
A31: FACTOR 3. Desarrollo, gestión y sostenibilidad institucional | B31: Característica 10. Recursos de apoyo académico | C31: 30 | D31: 46 | F31: Histórico de la salida a los estudiantes de los diferentes ambientes | G31: Secretaría Académica y de Extensión | H31: Luis Martín Trujillo | I31: Luis Martín Trujillo | BX31: 30
A32: FACTOR 3. Desarrollo, gestión y sostenibilidad institucional | B32: Característica 10. Recursos de apoyo académico | C32: 31 | D32: 47 | F32: Uso de los ambientes inmersivos por los estudiantes Poli | G32: Secretaría Académica y de Extensión | H32: Luis Martín Trujillo | I32: Luis Martín Trujillo | BX32: 31
A33: FACTOR 3. Desarrollo, gestión y sostenibilidad institucional | B33: Característica 10. Recursos de apoyo académico | C33: 32 | D33: 48 | F33: Distribución de los MI-Books por facultades | G33: Secretaría Académica y de Extensión | H33: Luis Martín Trujillo | I33: Luis Martín Trujillo | BX33: 32
A34: FACTOR 3. Desarrollo, gestión y sostenibilidad institucional | B34: Característica 10. Recursos de apoyo académico | C34: 33 | E34: 4 | F34: Medición uso recorridos | G34: Secretaría Académica y de Extensión | H34: Luis Martín Trujillo | I34: Luis Martín Trujillo | BX34: 33
A35: FACTOR 3. Desarrollo, gestión y sostenibilidad institucional | B35: Característica 10. Recursos de apoyo académico | C35: 34 | D35: 49 | F35: Visitas MI-Books por país | G35: Secretaría Académica y de Extensión | H35: Luis Martín Trujillo | I35: Luis Martín Trujillo | BX35: 34
A36: FACTOR 3. Desarrollo, gestión y sostenibilidad institucional | B36: Característica 10. Recursos de apoyo académico | C36: 35 | D36: 53 | F36: Talleres y laboratorios de la Institución | G36: Dirección de Infraestructura | H36: Raul Ricardo Cortes Rincón | I36: Edith marthza Nino | BX36: 35
A37: FACTOR 3. Desarrollo, gestión y sostenibilidad institucional | B37: Característica 10. Recursos de apoyo académico | C37: 36 | E37: 5 | F37: Sitios de práctica | G37: Dir Graduados y Proyección Empresarial | H37: Luis Miguel Corredor | I37: Luis Miguel Corredor | BX37: 36
A38: FACTOR 3. Desarrollo, gestión y sostenibilidad institucional | B38: Característica 11. Infraestructura Física y Tecnológica | C38: 37 | D38: 55 | F38: Infraestructura física del Poli | G38: Dirección de Infraestructura | H38: Raul Ricardo Cortes Rincón | I38: Edith marthza Nino | BX38: 37
A39: FACTOR 3. Desarrollo, gestión y sostenibilidad institucional | B39: Característica 11. Infraestructura Física y Tecnológica | C39: 38 | D39: 57 | F39: Infraestructura física 2019-2 a 2025-1 | G39: Dirección de Infraestructura | H39: Raul Ricardo Cortes Rincón | I39: Edith marthza Nino | BX39: 38
A40: FACTOR 3. Desarrollo, gestión y sostenibilidad institucional | B40: Característica 11. Infraestructura Física y Tecnológica | C40: 39 | D40: 58 | F40: Infraestructura Tecnológica 2019-2 a 2025-1 | G40: Dirección de Infraestructura | H40: Uriel Mejia Terán | I40: Iván Diaz / Diana García | BX40: 39
A41: FACTOR 3. Desarrollo, gestión y sostenibilidad institucional | B41: Característica 12. recursos y gestión Financiera | C41: 40 | D41: 61 | F41: Ingresos operacionales de la Institución | G41: Planeación Financiera | H41: Diana Baquero | I41: Diana Baquero | J41: Son datos anuales, se actualiza con información cierre 2024 | BX41: 40
A42: FACTOR 3. Desarrollo, gestión y sostenibilidad institucional | B42: Característica 12. recursos y gestión Financiera | C42: 41 | D42: 62 | F42: Fuentes de financiamiento internas y externas de la Institución | G42: Planeación Financiera | H42: Diana Baquero | I42: Diana Baquero | J42: Son datos anuales, se actualiza con información cierre 2024 | BX42: 41
A43: FACTOR 3. Desarrollo, gestión y sostenibilidad institucional | B43: Característica 12. recursos y gestión Financiera | C43: 42 | D43: 63 | F43: Comportamiento de excedentes operacional y neto | G43: Planeación Financiera | H43: Diana Baquero | I43: Diana Baquero | J43: Son datos anuales, se actualiza con información cierre 2024 | BX43: 42
A44: FACTOR 3. Desarrollo, gestión y sostenibilidad institucional | B44: Característica 12. recursos y gestión Financiera | C44: 43 | D44: 64 | F44: Evolución y composición del patrimonio | G44: Planeación Financiera | H44: Diana Baquero | I44: Diana Baquero | J44: Son datos anuales, se actualiza con información cierre 2024 | BX44: 43
A45: FACTOR 3. Desarrollo, gestión y sostenibilidad institucional | B45: Característica 12. recursos y gestión Financiera | C45: 44 | D45: 65 | F45: Evolución y composición del activo | G45: Planeación Financiera | H45: Diana Baquero | I45: Diana Baquero | J45: Son datos anuales, se actualiza con información cierre 2024 | BX45: 44
A46: FACTOR 3. Desarrollo, gestión y sostenibilidad institucional | B46: Característica 12. recursos y gestión Financiera | C46: 45 | D46: 66 | F46: Evolución del estado de la situación financiera | G46: Planeación Financiera | H46: Diana Baquero | I46: Diana Baquero | J46: Son datos anuales, se actualiza con información cierre 2024 | BX46: 45
A47: FACTOR 3. Desarrollo, gestión y sostenibilidad institucional | B47: Característica 12. recursos y gestión Financiera | C47: 46 | D47: 67 | F47: inversiones realizadas en torno al plan de mejoramiento | G47: Planeación Financiera | H47: Diana Baquero | I47: Diana Baquero | J47: Son datos anuales, se actualiza con información cierre 2024 | BX47: 46
A48: FACTOR 3. Desarrollo, gestión y sostenibilidad institucional | B48: Característica 12. recursos y gestión Financiera | C48: 47 | E48: 6 | F48: Liquidez y Capital de Trabajo | G48: Planeación Financiera | H48: Diana Baquero | I48: Diana Baquero | J48: Son datos anuales, se actualiza con información cierre 2024 | BX48: 47
A49: FACTOR 3. Desarrollo, gestión y sostenibilidad institucional | B49: Característica 12. recursos y gestión Financiera | C49: 48 | D49: 68 | F49: Inversiones misionales de la Institución | G49: Planeación Financiera | H49: Diana Baquero | I49: Diana Baquero | J49: Son datos anuales, se actualiza con información cierre 2024 | BX49: 48
A50: FACTOR 3. Desarrollo, gestión y sostenibilidad institucional | B50: Característica 12. recursos y gestión Financiera | C50: 49 | D50: 69 | F50: Inversiones en bienestar | G50: Planeación Financiera | H50: Diana Baquero | I50: Diana Baquero | J50: Son datos anuales, se actualiza con información cierre 2024 | BX50: 49
A51: FACTOR 3. Desarrollo, gestión y sostenibilidad institucional | B51: Característica 12. recursos y gestión Financiera | C51: 50 | D51: 70 | F51: Inversiones en proyección social | G51: Planeación Financiera | H51: Diana Baquero | I51: Diana Baquero | J51: Son datos anuales, se actualiza con información cierre 2024 | BX51: 50
A52: FACTOR 3. Desarrollo, gestión y sostenibilidad institucional | B52: Característica 12. recursos y gestión Financiera | C52: 51 | D52: 71 | F52: Inversión en investigación | G52: Planeación Financiera | H52: Diana Baquero | I52: Diana Baquero | J52: Son datos anuales, se actualiza con información cierre 2024 | BX52: 51
A53: FACTOR 3. Desarrollo, gestión y sostenibilidad institucional | B53: Característica 12. recursos y gestión Financiera | C53: 52 | D53: 72 | F53: Inversión en internacionalización | G53: Planeación Financiera | H53: Diana Baquero | I53: Diana Baquero | J53: Son datos anuales, se actualiza con información cierre 2024 | BX53: 52
A54: FACTOR 3. Desarrollo, gestión y sostenibilidad institucional | B54: Característica 12. recursos y gestión Financiera | C54: 53 | D54: 73 | F54: Inversión en Docencia | G54: Planeación Financiera | H54: Diana Baquero | I54: Diana Baquero | J54: Son datos anuales, se actualiza con información cierre 2024 | BX54: 53
A55: FACTOR 3. Desarrollo, gestión y sostenibilidad institucional | B55: Característica 12. recursos y gestión Financiera | C55: 54 | E55: 8 | F55: Ingresos Por extensión | G55: Planeación Financiera | H55: Diana Baquero | I55: Diana Baquero | J55: Son datos anuales, se actualiza con información cierre 2024 | BX55: 54
A56: FACTOR 3. Desarrollo, gestión y sostenibilidad institucional | B56: Característica 12. recursos y gestión Financiera | C56: 55 | D56: 74 | F56: Inversión en Infraestructura | G56: Planeación Financiera | H56: Diana Baquero | I56: Diana Baquero | J56: Son datos anuales, se actualiza con información cierre 2024 | BX56: 55
A57: FACTOR 3. Desarrollo, gestión y sostenibilidad institucional | B57: Característica 12. recursos y gestión Financiera | C57: 56 | D57: 75 | F57: Inversión en Infraestructura tecnológica | G57: Planeación Financiera | H57: Diana Baquero | I57: Diana Baquero | J57: Son datos anuales, se actualiza con información cierre 2024 | BX57: 56
A58: FACTOR 3. Desarrollo, gestión y sostenibilidad institucional | B58: Característica 12. recursos y gestión Financiera | C58: 57 | D58: 76 | F58: Inversión en contenidos virtuales | G58: Planeación Financiera | H58: Diana Baquero | I58: Diana Baquero | J58: Son datos anuales, se actualiza con información cierre 2024 | BX58: 57
A59: FACTOR 3. Desarrollo, gestión y sostenibilidad institucional | B59: Característica 12. recursos y gestión Financiera | C59: 58 | D59: 77 | F59: Inversión en Medios Audiovisuales y Biblioteca | G59: Planeación Financiera | H59: Diana Baquero | I59: Diana Baquero | J59: Son datos anuales, se actualiza con información cierre 2024 | BX59: 58
A60: FACTOR 4. Mejoramiento continuo y Autoregulación | B60: Característica 14. procesos de Autorregulación | C60: 59 | D60: 82 | F60: Proyectos finalizados | G60: Gerencia de Planeación y Gestión | H60: Liliana Bernal | I60: Rubén Dario Gelvez | BX60: 59
A61: FACTOR 4. Mejoramiento continuo y Autoregulación | B61: Característica 14. procesos de Autorregulación | C61: 60 | D61: 83 | F61: Proyectos en ejecución | G61: Gerencia de Planeación y Gestión | H61: Liliana Bernal | I61: Rubén Dario Gelvez | BX61: 60
A62: FACTOR 4. Mejoramiento continuo y Autoregulación | B62: Característica 16. Evaluación de directivas, profesores y personal administrativo | C62: 61 | D62: 85 | F62: Procesos formación permanente desarrollados desde el SIAC | G62: DAC | H62: Hector pérez | I62: Sebastián Diaz | BX62: 61
A63: FACTOR 4. Mejoramiento continuo y Autoregulación | B63: Característica 16. Evaluación de directivas, profesores y personal administrativo | C63: 62 | D63: 87 | F63: Resultados de la evaluación de administrativos | G63: Dirección de Formación | H63: Andrea Carmona | I63: Francy Lineth Castrillón | BX63: 62
A64: FACTOR 4. Mejoramiento continuo y Autoregulación | B64: Característica 16. Evaluación de directivas, profesores y personal administrativo | C64: 63 | E64: 9 | F64: Resultados de la evaluación de profesores | G64: Dirección de Formación | H64: Lina Giraldo | I64: Ángela Ramírez | BX64: 63
A65: FACTOR 5. Estructura y procesos académicos | B65: Característica 18. Componentes pedagógicos y de evaluación | C65: 64 | D65: 98 | F65: Formación a equipos curriculares encargados de la declaración y formulación de resultados de aprendizaje | G65: Dirección de currículo | H65: Maria Isabel Cortes | I65: Diana Shirley Velasquez | BX65: 64
A66: FACTOR 5. Estructura y procesos académicos | B66: Característica 18. Componentes pedagógicos y de evaluación | C66: 65 | D66: 99 | F66: Formación para declarar indicadores de logro | G66: Dirección de currículo | H66: Maria Isabel Cortes | I66: Diana Shirley Velasquez | BX66: 65
A67: FACTOR 5. Estructura y procesos académicos | B67: Característica 18. Componentes pedagógicos y de evaluación | C67: 66 | D67: 100 | F67: Participación de profesores formación del Modelo Institucional de Resultados de Aprendizaje | G67: Dirección de currículo | H67: Maria Isabel Cortes | I67: Diana Shirley Velasquez | BX67: 66
A68: FACTOR 5. Estructura y procesos académicos | B68: Característica 18. Componentes pedagógicos y de evaluación | C68: 67 | D68: 101 | F68: Participación de profesores en el plan de cualificación institucional | G68: Dirección de currículo | H68: Andrea Carmona | I68: Francy Lineth Castrillón | BX68: 67
A69: FACTOR 5. Estructura y procesos académicos | B69: Característica 20. Procesos de creación, modificación y ampliación de programas académicos | C69: 68 | D69: 105 | F69: Evolución de la nueva oferta 2019-2025-1 | G69: DAC | H69: Hector pérez | I69: Sebastián Diaz | BX69: 68
A70: FACTOR 6. Aportes de la investigación, la innovación, el desarrollo tecnológico y la creación al entorno | B70: Característica 21. Formación para la investigación, creación e innovación | C70: 69 | D70: 108 | F70: Estudiantes en actividades de investigación 2019 a 2025-1 | G70: Dir Investigación | H70: Jenny Hernández | I70: David Ricciulli | BX70: 69
A71: FACTOR 6. Aportes de la investigación, la innovación, el desarrollo tecnológico y la creación al entorno | B71: Característica 22. Investigación, desarrollo tecnológico, innovación y creación | C71: 70 | D71: 110 | F71: Resultado de los grupos institucionales en la Convocatoria de Medición de Grupos e Investigadores 957 | G71: Dir Investigación | H71: Jenny Hernández | I71: David Ricciulli | J71: Nota: Se actualizan con los últimos resultados Convocatoria 957 | BX71: 70
A72: FACTOR 6. Aportes de la investigación, la innovación, el desarrollo tecnológico y la creación al entorno | B72: Característica 22. Investigación, desarrollo tecnológico, innovación y creación | C72: 71 | D72: 111 | F72: Investigadores categorizados por área en la Convocatoria de Medición de Grupos e Investigadores 957 | G72: Dir Investigación | H72: Jenny Hernández | I72: David Ricciulli | J72: Nota: Se actualizan con los últimos resultados Convocatoria 957 | BX72: 71
A73: FACTOR 6. Aportes de la investigación, la innovación, el desarrollo tecnológico y la creación al entorno | B73: Característica 22. Investigación, desarrollo tecnológico, innovación y creación | C73: 72 | D73: 112 | F73: Profesores en capacitaciones de investigación durante el quinquenio | G73: Dir Investigación | H73: Jenny Hernández | I73: David Ricciulli | BX73: 72
A74: FACTOR 6. Aportes de la investigación, la innovación, el desarrollo tecnológico y la creación al entorno | B74: Característica 22. Investigación, desarrollo tecnológico, innovación y creación | C74: 73 | D74: 113 | F74: Estímulos por productividad de alto impacto entregados a profesores | G74: Dir Investigación | H74: Jenny Hernández | I74: David Ricciulli | BX74: 73
A75: FACTOR 6. Aportes de la investigación, la innovación, el desarrollo tecnológico y la creación al entorno | B75: Característica 22. Investigación, desarrollo tecnológico, innovación y creación | C75: 74 | D75: 114 | F75: Número de Proyectos de investigación 2019-2025-1 | G75: Dir Investigación | H75: Jenny Hernández | I75: David Ricciulli | BX75: 74
A76: FACTOR 6. Aportes de la investigación, la innovación, el desarrollo tecnológico y la creación al entorno | B76: Característica 22. Investigación, desarrollo tecnológico, innovación y creación | C76: 75 | D76: 115 | F76: Número de Proyectos con obtención de recursos externos | G76: Dir Investigación | H76: Jenny Hernández | I76: David Ricciulli | BX76: 75
A77: FACTOR 6. Aportes de la investigación, la innovación, el desarrollo tecnológico y la creación al entorno | B77: Característica 22. Investigación, desarrollo tecnológico, innovación y creación | C77: 76 | D77: 116 | F77: Productividad académica por tipología entre 2019-2025-1 | G77: Dir Investigación | H77: Jenny Hernández | I77: David Ricciulli | BX77: 76
A78: FACTOR 6. Aportes de la investigación, la innovación, el desarrollo tecnológico y la creación al entorno | B78: Característica 22. Investigación, desarrollo tecnológico, innovación y creación | C78: 77 | D78: 121 | F78: Histórico de producción del Laboratorio de Experiencias de Aprendizaje Inmersivo (LEAI y MI-Book) 2019-2025-1 | G78: Director del CREA | H78: Luis Martín Trujillo | I78: Luis Martín Trujillo | BX78: 77
A79: FACTOR 6. Aportes de la investigación, la innovación, el desarrollo tecnológico y la creación al entorno | B79: Característica 22. Investigación, desarrollo tecnológico, innovación y creación | C79: 78 | D79: 122 | F79: Histórico de uso de los ambientes inmersivos por parte de los estudiantes 2019-2025-1 | G79: Director del CREA | H79: Luis Martín Trujillo | I79: Luis Martín Trujillo | BX79: 78
A80: FACTOR 6. Aportes de la investigación, la innovación, el desarrollo tecnológico y la creación al entorno | B80: Característica 22. Investigación, desarrollo tecnológico, innovación y creación | C80: 79 | D80: 123 | F80: Proyectos con aliados regionales | G80: Dir Investigación | H80: Jenny Hernández | I80: David Ricciulli | BX80: 79
A81: FACTOR 7. Impacto Social | B81: Característica 23. Institución y entorno | C81: 80 | D81: 126 | F81: Capacitación y actualización profesional entre 2019-2 a 2025-1 | G81: Servicios corporativos | H81: John Jaime Marín | I81: John Jaime Marín | BX81: 80
A82: FACTOR 7. Impacto Social | B82: Característica 23. Institución y entorno | C82: 81 | D82: 130 | F82: Estudiantes que realizan práctica profesional de acuerdo con los tipos de vinculación 2019-2 a 2025-1 | G82: Dir Graduados y Proyección Empresarial | H82: Luis Miguel Corredor | I82: Luis Miguel Corredor | J82: Se actualiza metodología de cálculo, y se recalculan los datos del periodo de análisis | BX82: 81
A83: FACTOR 7. Impacto Social | B83: Característica 23. Institución y entorno | C83: 82 | E83: 13 | F83: Estudiantes modalidad virtual que han realizado practicas pedagógicas entre 2019-2025-1 | G83: Dir Graduados y Proyección Empresarial | H83: Luis Miguel Corredor | I83: Luis Miguel Corredor | BX83: 82
A84: FACTOR 7. Impacto Social | B84: Característica 23. Institución y entorno | C84: 83 | D84: 131 | F84: Estudiantes modalidad presencial y virtual que han realizado prácticas educativas del programa de Psicología entre 2019-2025-1 | G84: Dir Graduados y Proyección Empresarial | H84: Luis Miguel Corredor | I84: Luis Miguel Corredor | BX84: 83
A85: FACTOR 7. Impacto Social | B85: Característica 23. Institución y entorno | C85: 84 | D85: 132 | F85: Estudiantes modalidad presencial y virtual que han realizado prácticas en el consultorio tributario y empresarial entre 2019-2025-1 | G85: Consultorio Tributario y Empresarial | H85: Luis Miguel Corredor | I85: Luis Miguel Corredor | BX85: 84
A86: FACTOR 7. Impacto Social | B86: Característica 23. Institución y entorno | C86: 85 | D86: 133 | F86: Estudiantes en modalidad presencial que han realizado prácticas entre 2019-2025-1 | G86: Dir Graduados y Proyección Empresarial | H86: Luis Miguel Corredor | I86: Luis Miguel Corredor | J86: < | BX86: 85
A87: FACTOR 7. Impacto Social | B87: Característica 23. Institución y entorno | C87: 86 | D87: 134 | F87: Estudiantes de modalidad presencial que han realizado prácticas en la Agencia Trompo entre 2019-2025-1 | G87: Dir Graduados y Proyección Empresarial | H87: Luis Miguel Corredor | I87: Luis Miguel Corredor | BX87: 86
A88: FACTOR 7. Impacto Social | B88: Característica 23. Institución y entorno | C88: 87 | D88: 135 | F88: Histórico de Becas otorgadas por el Poli entre 2019-2 y 2025-1 | G88: Dirección de Bienestar | H88: Juan Carlos Rivera | I88: Lina Vanessa gonzález | BX88: 87
A89: FACTOR 7. Impacto Social | B89: Característica 23. Institución y entorno | C89: 88 | E89: 15 | F89: Usuarios que han tomado el servicio de transporte desde 2019 a 2025-1 | G89: Servicios Administrativos | H89: Gustavo Espinel | I89: Gustavo Espinel | J89: < | BX89: 88
A90: FACTOR 7. Impacto Social | B90: Característica 23. Institución y entorno | C90: 89 | D90: 136 | F90: Investigación asociada a proyección social 2019-1 a 2025-1 | G90: Dir Investigación | H90: Jenny Hernández | I90: David Ricciulli | BX90: 89
A91: FACTOR 7. Impacto Social | B91: Característica 23. Institución y entorno | C91: 90 | D91: 137 | F91: Actividad y población impactada entre 2020-2025-1 | G91: Escuela de Educación e Innovación | H91: Gerardo Machuca | I91: Gerardo Machuca | BX91: 90
A92: FACTOR 7. Impacto Social | B92: Característica 23. Institución y entorno | C92: 91 | D92: 138 | F92: Semilleros asociados a proyección social 2019-2025-1 | G92: Dir Investigación | H92: Jenny Hernández | I92: David Ricciulli /Maria alejandra Tequia | BX92: 91
A93: FACTOR 7. Impacto Social | B93: Característica 23. Institución y entorno | C93: 92 | D93: 139 | F93: Trabajos de grado que han aportado a la solución de problemas en el entorno | G93: **** | H93: Carlos Augusto García | I93: Mary Natalia Ortegón | BX93: 92
A94: FACTOR 8. Visibilidad nacional e internacional | B94: Característica 25. Inserción de la Institución en contextos académicos nacionales e internacionales | C94: 93 | D94: 144 | F94: Convenios por países | G94: Dirección de Relaciones Internacionales e Interinstitucionales | H94: Raquel Breton | I94: Raquel Breton | BX94: 93
A95: FACTOR 8. Visibilidad nacional e internacional | B95: Característica 25. Inserción de la Institución en contextos académicos nacionales e internacionales | C95: 94 | D95: 145 | F95: Número de clases espejo y estudiantes que participaron en estos espacios | G95: Dirección de Relaciones Internacionales e Interinstitucionales | H95: Raquel Breton | I95: Raquel Breton | BX95: 94
A96: FACTOR 8. Visibilidad nacional e internacional | B96: Característica 25. Inserción de la Institución en contextos académicos nacionales e internacionales | C96: 95 | D96: 147 | F96: Número de estudiantes con reconocimientos académicos por medio de seminarios internacionales virtuales, doble titulación, intercambio virtual | G96: Dirección de Relaciones Internacionales e Interinstitucionales | H96: Raquel Breton | I96: Raquel Breton | BX96: 95
A97: FACTOR 8. Visibilidad nacional e internacional | B97: Característica 25. Inserción de la Institución en contextos académicos nacionales e internacionales | C97: 96 | D97: 148 | F97: Número de profesores y expertos invitados | G97: Dirección de Relaciones Internacionales e Interinstitucionales | H97: Raquel Breton | I97: Raquel Breton | BX97: 96
A98: FACTOR 8. Visibilidad nacional e internacional | B98: Característica 25. Inserción de la Institución en contextos académicos nacionales e internacionales | C98: 97 | D98: 149 | F98: Número de estudiantes en internacionalización en casa | G98: Dirección de Relaciones Internacionales e Interinstitucionales | H98: Raquel Breton | I98: Raquel Breton | BX98: 97
A99: FACTOR 8. Visibilidad nacional e internacional | B99: Característica 25. Inserción de la Institución en contextos académicos nacionales e internacionales | C99: 98 | D99: 150 | F99: Número de estudiantes en cursos de idiomas | G99: Dirección de Relaciones Internacionales e Interinstitucionales | H99: Raquel Breton | I99: Raquel Breton | BX99: 98
A100: FACTOR 8. Visibilidad nacional e internacional | B100: Característica 25. Inserción de la Institución en contextos académicos nacionales e internacionales | C100: 99 | D100: 151 | F100: Número de convenios con ICETEX para asistentes extranjeros | G100: Dirección de Relaciones Internacionales e Interinstitucionales | H100: Raquel Breton | I100: Raquel Breton | BX100: 99
...

Sheet Tabla 1
A1: Tabla NO | B1: 1
A2: Nombre | B2: Evolución de la oferta académica de la Sede Bogotá en el quinquenio
A3: MODALIDAD | B3: NIVEL DE FORMACIÓN | C3: 2019 | D3: 2020 | E3: 2021 | F3: 2022 | G3: 2023 | H3: 2024-1 | I3: 2024-2 | J3: 2025-1 | K3: 2025-2 | L3: 2026-1
A4: PRESENCIAL | B4: TECNOLÓGICOS | C4: 4 | D4: 4 | E4: 3 | F4: 3 | G4: 2 | H4: 2 | I4: 2 | J4: 2 | K4: 2 | L4: 2
B5: PROFESIONALES UNIVERSITARIOS | C5: 20 | D5: 20 | E5: 19 | F5: 21 | G5: 20 | H5: 20 | I5: 20 | J5: 20 | K5: 19 | L5: 19
B6: ESPECIALIZACIONES UNIVERSITARIAS | C6: 10 | D6: 11 | E6: 12 | F6: 12 | G6: 11 | H6: 11 | I6: 11 | J6: 11 | K6: 11 | L6: 10
B7: MAESTRÍAS | C7: 5 | D7: 5 | E7: 5 | F7: 5 | G7: 5 | H7: 5 | I7: 3 | J7: 3 | K7: 2 | L7: 2
A8: VIRTUAL | B8: TÉCNICOS PROFESIONALES | C8: 2 | D8: 2 | E8: 2 | F8: 2 | G8: 2 | H8: 2 | I8: 2 | J8: 2 | K8: 2 | L8: 3
B9: TECNOLÓGICOS | C9: 7 | D9: 8 | E9: 8 | F9: 8 | G9: 7 | H9: 7 | I9: 7 | J9: 7 | K9: 7 | L9: 7
B10: PROFESIONALES UNIVERSITARIOS | C10: 10 | D10: 11 | E10: 15 | F10: 17 | G10: 17 | H10: 19 | I10: 19 | J10: 22 | K10: 22 | L10: 25
B11: ESPECIALIZACIONES TECNOLÓGICAS | C11: 1 | D11: 0 | E11: 0 | F11: 0 | G11: 0 | H11: 0 | I11: 0 | J11: 0 | K11: 0 | L11: 0
B12: ESPECIALIZACIONES UNIVERSITARIAS | C12: 10 | D12: 10 | E12: 11 | F12: 10 | G12: 9 | H12: 9 | I12: 9 | J12: 10 | K12: 10 | L12: 11
B13: MAESTRÍAS | C13: 0 | D13: 0 | E13: 3 | F13: 4 | G13: 4 | H13: 7 | I13: 7 | J13: 14 | K13: 14 | L13: 17
A14: TOTAL | C14: 69 | D14: 71 | E14: 78 | F14: 82 | G14: 77 | H14: 82 | I14: =SUM(I4:I13) -> 80 | J14: =SUM(J4:J13) -> 91 | K14: =SUM(K4:K13) -> 89 | L14: 96

Sheet Tabla 2
A1: Tabla NO | B1: 2
A2: Nombre | B2: Distribución de la oferta académica por facultades
A4: FACULTAD | B4: PREGRADO | D4: POSGRADO | F4: TOTAL
B5: PRESENCIAL | C5: VIRTUAL | D5: PRESENCIAL | E5: VIRTUAL
A6: FACULTAD DE INGENIERÍA, DISEÑO E INNOVACIÓN | B6: 11 | C6: 5 | D6: 3 | E6: 7 | F6: =SUM(B6:E6) -> 26
A7: FACULTAD DE NEGOCIOS, GESTIÓN Y SOSTENIBILIDAD | B7: 6 | C7: 12 | D7: 4 | E7: 9 | F7: =SUM(B7:E7) -> 31
A8: FACULTAD DE SOCIEDAD, CULTURA Y CREATIVIDAD | B8: 5 | C8: 14 | D8: 7 | E8: 8 | F8: =SUM(B8:E8) -> 34
A9: TOTAL | B9: =SUM(B6:B8) -> 22 | C9: =SUM(C6:C8) -> 31 | D9: =SUM(D6:D8) -> 14 | E9: =SUM(E6:E8) -> 24 | F9: =SUM(F6:F8) -> 91
A12: 2026-1
A13: FACULTAD | B13: PREGRADO | D13: POSGRADO | F13: TOTAL
B14: PRESENCIAL | C14: VIRTUAL | D14: PRESENCIAL | E14: VIRTUAL
A15: FACULTAD DE INGENIERÍA, DISEÑO E INNOVACIÓN | B15: 10 | C15: 6 | D15: 1 | E15: 9 | F15: =SUM(B15:E15) -> 26
A16: FACULTAD DE NEGOCIOS, GESTIÓN Y SOSTENIBILIDAD | B16: 6 | C16: 13 | D16: 4 | E16: 9 | F16: =SUM(B16:E16) -> 32
A17: FACULTAD DE SOCIEDAD, CULTURA Y CREATIVIDAD | B17: 5 | C17: 16 | D17: 7 | E17: 10 | F17: =SUM(B17:E17) -> 38
A18: TOTAL | B18: =SUM(B15:B17) -> 21 | C18: =SUM(C15:C17) -> 35 | D18: =SUM(D15:D17) -> 12 | E18: =SUM(E15:E17) -> 28 | F18: =SUM(F15:F17) -> 96

Sheet Tabla 3
A1: Tabla NO | B1: 3
A2: Nombre | B2: Programas acreditados en alta calidad en la Sede Bogotá
A5: Nombre | B5: Programas acreditados en alta calidad en la Sede Bogotá 2025-1
A7: SNIES | B7: MODALIDAD | C7: SEDE | D7: FACULTAD | E7: ESCUELA | F7: PROGRAMA | G7: VIGENCIA
A8: 54534 | B8: PRESENCIAL | C8: BOGOTÁ | D8: FIDI | E8: ESCUELA DE DISEÑO | F8: DISEÑO GRÁFICO | G8: 6
A9: 53835 | B9: PRESENCIAL | C9: BOGOTÁ | D9: FIDI | E9: ESCUELA DE TECNOLOGÍA, INFORMACIÓN Y COMUNICACIÓN | F9: INGENIERÍA EN TELECOMUNICACIONES | G9: 6
A10: 10561 | B10: PRESENCIAL | C10: BOGOTÁ | D10: FIDI | E10: ESCUELA DE OPTIMIZACIÓN, INFRAESTRUCTURA Y AUTOMATIZACIÓN | F10: INGENIERÍA INDUSTRIAL | G10: 4
A11: 1895 | B11: PRESENCIAL | C11: BOGOTÁ | D11: FIDI | E11: ESCUELA DE TECNOLOGÍA, INFORMACIÓN Y COMUNICACIÓN | F11: INGENIERÍA DE SISTEMAS | G11: 4
A12: 53237 | B12: PRESENCIAL | C12: BOGOTÁ | D12: FNGS | E12: ESCUELA DE NEGOCIOS Y DESARROLLO INTERNACIONAL | F12: TECNOLOGÍA EN GESTIÓN DE SERVICIOS PARA AEROLÍNEAS | G12: 6
A13: 53178 | B13: VIRTUAL | C13: NACIONAL | D13: FNGS | E13: ESCUELA DE ADMINISTRACIÓN Y COMPETITIVIDAD | F13: TECNOLOGÍA EN GESTIÓN FINANCIERA | G13: 4
A14: 7470 | B14: PRESENCIAL | C14: BOGOTÁ | D14: FNGS | E14: ESCUELA DE NEGOCIOS Y DESARROLLO INTERNACIONAL | F14: NEGOCIOS INTERNACIONALES | G14: 4
A15: 101382 | B15: PRESENCIAL | C15: BOGOTÁ | D15: FNGS | E15: ESCUELA DE ADMINISTRACIÓN Y COMPETITIVIDAD | F15: ADMINISTRACIÓN DE EMPRESAS | G15: 6
A16: 1892 | B16: PRESENCIAL | C16: BOGOTÁ | D16: FSCC | E16: ESCUELA DE MARKETING Y BRANDING | F16: MERCADEO Y PUBLICIDAD | G16: 6
A17: 6699 | B17: PRESENCIAL | C17: BOGOTÁ | D17: FSCC | E17: ESCUELA DE COMUNICACIÓN, ARTES VISUALES Y DIGITALES | F17: PROFESIONAL EN MEDIOS AUDIOVISUALES | G17: 6
A18: 101647 | B18: VIRTUAL | C18: NACIONAL | D18: FSCC | E18: ESCUELA DE DERECHO Y GOBIERNO | F18: TECNICA PROFESIONAL JUDICIAL | G18: 6
A20: Nombre | B20: Programas acreditados en alta calidad en la Sede Bogotá - Nacional 2026-1
A21: SNIES | B21: MODALIDAD | C21: SEDE | D21: FACULTAD | E21: ESCUELA | F21: PROGRAMA | G21: VIGENCIA
A22: 54534 | B22: PRESENCIAL | C22: BOGOTÁ | D22: FIDI | E22: ESCUELA DE DISEÑO | F22: DISEÑO GRÁFICO | G22: 6
A23: 101525 | B23: PRESENCIAL | C23: BOGOTÁ | D23: FIDI | E23: ESCUELA DE DISEÑO | F23: DISEÑO INDUSTRIAL | G23: 6
A24: 53835 | B24: PRESENCIAL | C24: BOGOTÁ | D24: FIDI | E24: ESCUELA DE TECNOLOGÍA, INFORMACIÓN Y COMUNICACIÓN | F24: INGENIERÍA EN TELECOMUNICACIONES | G24: 6
A25: 10561 | B25: PRESENCIAL | C25: BOGOTÁ | D25: FIDI | E25: ESCUELA DE OPTIMIZACIÓN, INFRAESTRUCTURA Y AUTOMATIZACIÓN | F25: INGENIERÍA INDUSTRIAL | G25: 4*
A26: 1895 | B26: PRESENCIAL | C26: BOGOTÁ | D26: FIDI | E26: ESCUELA DE TECNOLOGÍA, INFORMACIÓN Y COMUNICACIÓN | F26: INGENIERÍA DE SISTEMAS | G26: 4
A27: 53237 | B27: PRESENCIAL | C27: BOGOTÁ | D27: FNGS | E27: ESCUELA DE NEGOCIOS Y DESARROLLO INTERNACIONAL | F27: TECNOLOGÍA EN GESTIÓN DE SERVICIOS PARA AEROLÍNEAS | G27: 6
A28: 53178 | B28: VIRTUAL | C28: NACIONAL | D28: FNGS | E28: ESCUELA DE ADMINISTRACIÓN Y COMPETITIVIDAD | F28: TECNOLOGÍA EN GESTIÓN FINANCIERA | G28: 4
A29: 7470 | B29: PRESENCIAL | C29: BOGOTÁ | D29: FNGS | E29: ESCUELA DE NEGOCIOS Y DESARROLLO INTERNACIONAL | F29: NEGOCIOS INTERNACIONALES | G29: 4
A30: 101382 | B30: PRESENCIAL | C30: BOGOTÁ | D30: FNGS | E30: ESCUELA DE ADMINISTRACIÓN Y COMPETITIVIDAD | F30: ADMINISTRACIÓN DE EMPRESAS | G30: 6
A31: 1892 | B31: PRESENCIAL | C31: BOGOTÁ | D31: FSCC | E31: ESCUELA DE MARKETING Y BRANDING | F31: MERCADEO Y PUBLICIDAD | G31: 6
A32: 6699 | B32: PRESENCIAL | C32: BOGOTÁ | D32: FSCC | E32: ESCUELA DE COMUNICACIÓN, ARTES VISUALES Y DIGITALES | F32: MEDIOS AUDIOVISUALES | G32: 6
A33: 3638 | B33: PRESENCIAL | C33: BOGOTÁ | D33: FSCC | E33: ESCUELA DE COMUNICACIÓN, ARTES VISUALES Y DIGITALES | F33: COMUNICACIÓN SOCIAL - PERIODISMO | G33: 6
A34: 91360 | B34: PRESENCIAL | C34: BOGOTÁ | D34: FSCC | E34: ESCUELA DE MARKETING Y BRANDING | F34: MAESTRÍA EN GERENCIA ESTRATÉGICA DE MERCADEO | G34: 6
A35: 103799 | B35: VIRTUAL | C35: NACIONAL | D35: FSCC | E35: ESCUELA DE PSICOLOGÍA, TALENTO HUMANO Y SOCIEDAD | F35: PROFESIONAL EN GESTIÓN DE LA SEGURIDAD Y LA SALUD LABORAL | G35: 6
A36: 101647 | B36: VIRTUAL | C36: NACIONAL | D36: FSCC | E36: ESCUELA DE DERECHO Y GOBIERNO | F36: TÉCNICA PROFESIONAL JUDICIAL | G36: 6

Sheet Tabla 4
A1: Tabla NO | B1: 4
A2: Nombre | B2: Programas con informe de autoevaluación radicado en CNA
A4: SNIES | B4: MODALIDAD | C4: SEDE | D4: FACULTAD | E4: ESCUELA | F4: PROGRAMA
A5: 101525 | B5: PRESENCIAL | C5: BOGOTÁ | D5: FIDI | E5: ESCUELA DE DISEÑO | F5: DISEÑO INDUSTRIAL
A6: 91360 | B6: PRESENCIAL | C6: BOGOTÁ | D6: FSCC | E6: ESCUELA DE MARKETING Y BRANDING | F6: MAESTRÍA EN GERENCIA ESTRATÉGICA DE MERCADEO
A7: 3638 | B7: PRESENCIAL | C7: BOGOTÁ | D7: FSCC | E7: ESCUELA DE COMUNICACIÓN, ARTES VISUALES Y DIGITALES | F7: COMUNICACIÓN SOCIAL – PERIODISMO
A8: 103799 | B8: VIRTUAL | C8: NACIONAL | D8: FSCC | E8: ESCUELA DE PSICOLOGÍA, TALENTO HUMANO Y SOCIEDAD | F8: PROFESIONAL EN GESTIÓN DE LA SEGURIDAD Y LA SALUD LABORAL
A9: 101647 | B9: VIRTUAL | C9: NACIONAL | D9: FSCC | E9: ESCUELA DE DERECHO Y GOBIERNO | F9: TÉCNICA PROFESIONAL JUDICIAL
A12: Nombre | B12: Programas con informe de autoevaluación radicado en CNA 2026-1
A14: SNIES | B14: MODALIDAD | C14: SEDE | D14: FACULTAD | E14: ESCUELA | F14: PROGRAMA
A15: 102473 | B15: PRESENCIAL | C15: MEDELLÍN | D15: FIDI | E15: ESCUELA DE OPTIMIZACIÓN, INFRAESTRUCTURA Y AUTOMATIZACIÓN | F15: INGENIERÍA INDUSTRIAL
A16: 53178 | B16: VIRTUAL | C16: NACIONAL | D16: FNGS | E16: ESCUELA DE ADMINISTRACIÓN Y COMPETITIVIDAD | F16: TECNOLOGÍA EN GESTIÓN FINANCIERA
A17: 7470 | B17: PRESENCIAL | C17: BOGOTÁ | D17: FNGS | E17: ESCUELA DE NEGOCIOS Y DESARROLLO INTERNACIONAL | F17: NEGOCIOS INTERNACIONALES
A18: 103752 | B18: PRESENCIAL | C18: MEDELLÍN | D18: FSCC | E18: ESCUELA DE PSICOLOGÍA, TALENTO HUMANO Y SOCIEDAD | F18: PSICOLOGÍA

Sheet Hoja1
A1: SNIES | B1: MODALIDAD | C1: SEDE | D1: FACULTAD | E1: ESCUELA | F1: PROGRAMA
A2: 103752 | B2: PRESENCIAL | C2: MEDELLÍN | D2: FSCC | E2: ESCUELA DE PSICOLOGÍA, TALENTO HUMANO Y SOCIEDAD | F2: PSICOLOGÍA

Sheet Gráfico 1
A1: Gráfico No | B1: 1
A2: Nombre | B2: Profesores por dedicación 2019-2 a 2024-1
B4: 2019-2 | C4: 2020-1 | D4: 2020-2 | E4: 2021-1 | F4: 2021-2 | G4: 2022-1 | H4: 2022-2 | I4: 2023-1 | J4: 2023-2 | K4: 2024-1 | L4: 2024-2 | M4: 2025-1 | N4: 2025-2 | O4: 2026-1
A5: Tiempo Completo | B5: 216 | C5: 236 | D5: 231 | E5: 371 | F5: 355 | G5: 436 | H5: 503 | I5: 499 | J5: 536 | K5: 594 | L5: 591 | M5: 649 | N5: 666 | O5: 690
A6: Medio Tiempo | B6: 47 | C6: 50 | D6: 68 | E6: 118 | F6: 100 | G6: 133 | H6: 136 | I6: 183 | J6: 165 | K6: 195 | L6: 180 | M6: 273 | N6: 276 | O6: 329
A7: Hora Cátedra | B7: 1016 | C7: 948 | D7: 704 | E7: 342 | F7: 397 | G7: 303 | H7: 222 | I7: 190 | J7: 179 | K7: 199 | L7: 153 | M7: 136 | N7: 96 | O7: 63
B8: =+SUM(B5:B7) -> 1279 | C8: =+SUM(C5:C7) -> 1234 | D8: =+SUM(D5:D7) -> 1003 | E8: =+SUM(E5:E7) -> 831 | F8: =+SUM(F5:F7) -> 852 | G8: =+SUM(G5:G7) -> 872 | H8: =+SUM(H5:H7) -> 861 | I8: =+SUM(I5:I7) -> 872 | ... M8: =+SUM(M5:M7) -> 1058 | N8: =SUM(N5:N7) -> 1038 | O8: =SUM(O5:O7) -> 1082

Sheet Tabla 5
A1: Tabla NO | B1: 5
A2: Nombre | B2: Programas con condiciones iniciales aprobadas
A4: SNIES | B4: MODALIDAD | C4: SEDE | D4: FACULTAD | E4: ESCUELA | F4: PROGRAMA
A5: 54726 | B5: PRESENCIAL | C5: BOGOTÁ | D5: FIDI | E5: ESCUELA DE DISEÑO | F5: DISEÑO DE MODAS
A6: 1894 | B6: PRESENCIAL | C6: BOGOTÁ | D6: FNGS | E6: ESCUELA DE CONTADURÍA Y FINANZAS GLOBALES | F6: CONTADURÍA PÚBLICA
A7: 111178 | B7: VIRTUAL | C7: NACIONAL | D7: FSCC | E7: ESCUELA DE EDUCACIÓN E INNOVACIÓN | F7: LICENCIATURA EN EDUCACIÓN INFANTIL
A10: Nombre | B10: Programas con condiciones iniciales aprobadas 2026-1
A12: SNIES | B12: MODALIDAD | C12: SEDE | D12: FACULTAD | E12: ESCUELA | F12: PROGRAMA
A13: 101660 | B13: Virtual | C13: Nacional | D13: FSCC | E13: Escuela de Educación e Innovación | F13: Licenciatura en Ciencias Sociales
A14: 53632 | B14: Virtual | C14: Nacional | D14: FNGS | E14: Escuela de Contabilidad y Finanzas Globales | F14: Contaduría Pública
A15: 90399 | B15: Virtual | C15: Nacional | D15: FNGS | E15: Escuela de Administración y Competitividad | F15: Administracion de Empresas
A16: 102847 | B16: Presencial | C16: Medellín | D16: FNGS | E16: Escuela de Administración y Competitividad | F16: Administracion de Empresas

Sheet Tabla 6
A1: * | B1: 6
A2: Nombre | B2: Matrícula de estudiantes 2019-2 a 2024-1
B4: Nivel formación | C4: 2019-2 | D4: 2020-1 | E4: 2020-2 | F4: 2021-1 | G4: 2021-2 | H4: 2022-1 | I4: 2022-2 | J4: 2023-1 | K4: 2023-2 | L4: 2024-1 | M4: 2024-2 | N4: 2025-1 | O4: 2025-2 | P4: 2026-1
A5: Total Presencial | C5: 7501 | D5: 7426 | E5: 6292 | F5: 6113 | G5: 5601 | H5: 5505 | I5: 5239 | J5: 5614 | K5: 5627 | L5: 5800 | M5: 5585 | N5: 5979 | O5: =SUM(O6:O10) -> 6000 | P5: =SUM(P6:P10) -> 6289
A6: Presencial | B6: T profesional | C6: 31 | D6: 27 | E6: 13 | F6: 13 | G6: 6 | H6: 5 | I6: 3 | J6: 2 | K6: 2 | L6: 1 | M6: 0 | N6: 0 | O6: 0 | P6: 0
B7: Tecnológico | C7: 392 | D7: 369 | E7: 291 | F7: 275 | G7: 263 | H7: 249 | I7: 320 | J7: 385 | K7: 423 | L7: 458 | M7: 442 | N7: 435 | O7: 390 | P7: 344
B8: Universitario | C8: 6391 | D8: 6327 | E8: 5430 | F8: 5294 | G8: 4822 | H8: 4768 | I8: 4429 | J8: 4720 | K8: 4665 | L8: 4755 | M8: 4535 | N8: 4880 | O8: 5006 | P8: 5351
B9: Especialización | C9: 569 | D9: 577 | E9: 446 | F9: 438 | G9: 435 | H9: 420 | I9: 437 | J9: 470 | K9: 467 | L9: 483 | M9: 499 | N9: 538 | O9: 525 | P9: 508
B10: Maestría | C10: 118 | D10: 126 | E10: 112 | F10: 93 | G10: 75 | H10: 63 | I10: 50 | J10: 37 | K10: 70 | L10: 103 | M10: 109 | N10: 126 | O10: 79 | P10: 86
A11: Total Virtual | C11: 43613 | D11: 44262 | E11: 44718 | F11: 43590 | G11: 42676 | H11: 43415 | I11: 43449 | J11: 43568 | K11: 44083 | L11: 44161 | M11: 43840 | N11: 47762 | O11: =SUM(O12:O16) -> 48072 | P11: =SUM(P12:P16) -> 52109
A12: Virtual | B12: T profesional | C12: 312 | D12: 355 | E12: 434 | F12: 370 | G12: 383 | H12: 427 | I12: 401 | J12: 344 | K12: 353 | L12: 328 | M12: 291 | N12: 355 | O12: 346 | P12: 382
B13: Tecnológico | C13: 5405 | D13: 5544 | E13: 5448 | F13: 5371 | G13: 5106 | H13: 5025 | I13: 4869 | J13: 4702 | K13: 4550 | L13: 4401 | M13: 4079 | N13: 4311 | O13: 4233 | P13: 4475
B14: Universitario | C14: 36710 | D14: 37056 | E14: 37269 | F14: 36150 | G14: 35640 | H14: 36070 | I14: 36076 | J14: 36074 | K14: 36409 | L14: 36534 | M14: 36412 | N14: 39351 | O14: 39465 | P14: 42158
B15: Especialización | C15: 1186 | D15: 1307 | E15: 1567 | F15: 1699 | G15: 1546 | H15: 1760 | I15: 1854 | J15: 1915 | K15: 1981 | L15: 1985 | M15: 1927 | N15: 2060 | O15: 1916 | P15: 1917
B16: Maestría | G16: 1 | H16: 133 | I16: 249 | J16: 533 | K16: 790 | L16: 913 | M16: 1131 | N16: 1685 | O16: 2112 | P16: 3177
A17: Total Sede Bogotá | C17: . | D17: 51688 | E17: 51010 | F17: 49703 | G17: 48277 | H17: 48920 | I17: 48688 | J17: 49182 | K17: 49710 | L17: 49961 | M17: 49425 | N17: 53741 | O17: =+O11+O5 -> 54072 | P17: =+P11+P5 -> 58398

Sheet Gráfico 2
A1: Gráfico No | B1: 2
A2: Nombre | B2: Profesores por nivel de formación
B4: 2019-2 | C4: 2020-1 | D4: 2020-2 | E4: 2021-1 | F4: 2021-2 | G4: 2022-1 | H4: 2022-2 | I4: 2023-1 | J4: 2023-2 | K4: 2024-1 | L4: 2024-2 | M4: 2025-1 | N4: 2025-2 | O4: 2026-1
A5: Doctorado | B5: 35 | C5: 41 | D5: 37 | E5: 47 | F5: 37 | G5: 51 | H5: 47 | I5: 46 | J5: 53 | K5: 71 | L5: 77 | M5: 94 | N5: 89 | O5: 85
A6: Maestría | B6: 784 | C6: 830 | D6: 691 | E6: 604 | F6: 666 | G6: 593 | H6: 597 | I6: 686 | J6: 699 | K6: 766 | L6: 708 | M6: 819 | N6: 794 | O6: 829
A7: Especialización | B7: 286 | C7: 233 | D7: 190 | E7: 122 | F7: 104 | G7: 188 | H7: 170 | I7: 95 | J7: 81 | K7: 91 | L7: 85 | M7: 83 | N7: 97 | O7: 98
A8: Pregrado | B8: 174 | C8: 130 | D8: 85 | E8: 58 | F8: 45 | G8: 40 | H8: 47 | I8: 45 | J8: 47 | K8: 60 | L8: 54 | M8: 62 | N8: 58 | O8: 70
B9: =+SUM(B5:B8) -> 1279 | C9: =+SUM(C5:C8) -> 1234 | D9: =+SUM(D5:D8) -> 1003 | E9: =+SUM(E5:E8) -> 831 | F9: =+SUM(F5:F8) -> 852 | G9: =+SUM(G5:G8) -> 872 | H9: =+SUM(H5:H8) -> 861 | I9: =+SUM(I5:I8) -> 872 | ... O9: =+SUM(O5:O8) -> 1082

Sheet Tabla 7
A1: Tabla NO | B1: 7
A2: Nombre | B2: Graduados por nivel de formación y modalidad 2019-2 a 2024-1
A4: Modalidad | B4: Nivel de formación | C4: 2019-2 | D4: 2020-1 | E4: 2020-2 | F4: 2021-1 | G4: 2021-2 | H4: 2022-1 | I4: 2022-2 | J4: 2023-1 | K4: 2023-2 | L4: 2024-1 | M4: 2024-2 | N4: 2025-1 | O4: 2025-2 | P4: 2026-1
A5: Virtual | B5: Técnico Profesional | C5: 28 | D5: 31 | E5: 32 | F5: 50 | G5: 48 | H5: 33 | I5: 57 | J5: 57 | K5: 45 | L5: 22 | M5: 74 | N5: 26
B6: Tecnológico | C6: 423 | D6: 493 | E6: 398 | F6: 507 | G6: 564 | H6: 531 | I6: 554 | J6: 418 | K6: 523 | L6: 361 | M6: 649 | N6: 378
B7: Universitario | C7: 2626 | D7: 3704 | E7: 4102 | F7: 5449 | G7: 5127 | H7: 5646 | I7: 4973 | J7: 4845 | K7: 4923 | L7: 3858 | M7: 4783 | N7: 3564
B8: Especialización | C8: 556 | D8: 348 | E8: 725 | F8: 527 | G8: 1088 | H8: 250 | I8: 1033 | J8: 501 | K8: 1122 | L8: 682 | M8: 1262 | N8: 1209
B9: Maestría | K9: 1 | L9: 10 | M9: 35 | N9: 56
B10: Virtual | C10: 3633 | D10: 4576 | E10: 5257 | F10: 6533 | G10: 6827 | H10: 6460 | I10: 6617 | J10: 5821 | K10: 6614 | L10: 4933 | M10: 6803 | N10: 5233
A11: Presencial | B11: Técnico Profesional | C11: 5 | D11: 1 | E11: 9 | F11: 6 | G11: 5 | H11: 3 | I11: 1 | J11: 2 | K11: 2 | M11: 2
B12: Tecnológico | C12: 96 | D12: 68 | E12: 92 | F12: 113 | G12: 75 | H12: 66 | I12: 78 | J12: 74 | K12: 81 | L12: 43 | M12: 67 | N12: 68
B13: Universitario | C13: 749 | D13: 853 | E13: 1136 | F13: 1101 | G13: 1062 | H13: 1041 | I13: 881 | J13: 849 | K13: 795 | L13: 735 | M13: 799 | N13: 746
B14: Especialización | C14: 257 | D14: 282 | E14: 341 | F14: 265 | G14: 298 | H14: 190 | I14: 146 | J14: 192 | K14: 295 | L14: 214 | M14: 297 | N14: 219
B15: Maestría | C15: 14 | D15: 10 | E15: 16 | F15: 18 | G15: 31 | H15: 18 | I15: 24 | J15: 7 | K15: 14 | L15: 117 | M15: 163 | N15: 266
B16: Presencial | C16: 1121 | D16: 1214 | E16: 1594 | F16: 1503 | G16: 1471 | H16: 1318 | I16: 1130 | J16: 1124 | K16: 1187 | L16: 1109 | M16: 1328 | N16: 1299
A17: Total | C17: 4754 | D17: 5790 | E17: 6851 | F17: 8036 | G17: 8298 | H17: 7778 | I17: 7747 | J17: 6945 | K17: 7801 | L17: 6042 | M17: 8131 | N17: 6532

Sheet Tabla 8
A1: Tabla NO | B1: 8
A2: Nombre | B2: Grupos de investigación categorizados en Ministerio de Ciencias, Tecnología e Innovación Minciencias
A4: Facultad | B4: Grupo | C4: Categoría
A5: Facultad de Ingeniería, Diseño e Innovación | B5: CITIC | C5: A
B6: Diseño, Artefacto y Sociedad – DAS | C6: C
B7: Optimización, Infraestructura y Automatización – OPINA | C7: B
B8: E-TIC | C8: REC
A9: Facultad de Sociedad, Cultura y Creatividad | B9: Derecho, Sociedad y Empresa – DSE | C9: A
B10: MERCADEO I+2 - MI2 | C10: A
B11: Psicología Educación y Cultura – PEC | C11: A1
B12: Educación, Innovación y Sociedad – EIS | C12: B
B13: Narrativas, Creación y Estéticas – NCE | C13: C
B14: Ciudadanías, Acción social y Desarrollo – CIADE | C14: C
B15: Comunicación Estratégica y Creativa – CEC | C15: C
B16: Grupo de Investigación en Gestión de las Organizaciones Laborales y Seguridad Laboral | C16: C
A17: Facultad Negocios, Gestión y Sostenibilidad | B17: Economía, Negocios y Desarrollo Internacional – ENDI | C17: A
B18: Administración, Competitividad y Sostenibilidad – GACS | C18: B
B19: Equipo de Investigación en Contabilidad, Organizaciones y Sociedad – EICOS | C19: B
B20: GIAP | C20: B
B21: Nota: Cnvocatoria 957 Minciencias

Sheet Tabla 9
A1: Tabla NO | B1: 9
A2: Nombre | B2: Investigadores categorizados Minciencias. Convocatoria 957
B4: Investigadores
A5: Junior | B5: 80
A6: Asociado | B6: 32
A7: Senior | B7: 10
A8: Total | B8: =SUM(B5:B7) -> 122
A9: Resultados concocatoria 957 Minciencas

Sheet Tabla 10
A1: Tabla NO | B1: 10
A2: Nombre | B2: Semilleros por facultad 2019-2- a 2026-1
B4: Facultad | C4: 2019 | D4: 2020 | E4: 2021 | F4: 2022 | G4: 2023 | H4: 2024 | I4: 2025 | J4: 2026-1
B5: Facultad Ingeniería Diseño e Innovación | C5: 23 | D5: 26 | E5: 24 | F5: 36 | G5: 33 | H5: 31 | I5: 30 | J5: 31
B6: Facultad Negocios, Gestión y Sostenibilidad | C6: 32 | D6: 36 | E6: 44 | F6: 34 | G6: 32 | H6: 30 | I6: 27 | J6: 28
B7: Facultad Sociedad, Cultura y Creatividad | C7: 54 | D7: 63 | E7: 65 | F7: 54 | G7: 68 | H7: 71 | I7: 58 | J7: 63
B8: Total | C8: 109 | D8: 125 | E8: 133 | F8: 124 | G8: 133 | H8: 132 | I8: 115 | J8: =SUM(J5:J7) -> 122

Sheet Tabla 23
A1: * | B1: 23
A2: Nombre | B2: Resultados de las acciones de formación integral
A4: Dimensión | B4: Acciones | C4: 2019 | D4: 2020 | E4: 2021 | F4: 2022 | G4: 2023 | H4: 2024 | I4: 2025 | J4: 2026-1
A5: Académica | B5: Semilleros de investigación | C5: 109 | D5: 125 | E5: 133 | F5: 124 | G5: 133 | H5: 132 | I5: 115 | K5: tabla 10
B6: Clases espejo | C6: 13 | D6: 86 | E6: 108 | F6: 106 | G6: 68 | H6: 97 | I6: 101 | K6: tabla 145
B7: Estudiantes | C7: 103 | D7: 2059 | E7: 4269 | F7: 2893 | G7: 1401 | H7: 3747 | I7: 2493 | K7: tabla 145
B8: Uso de los ambientes inmersivos por los estudiantes | C8: - | D8: - | E8: 85 | F8: 4389 | G8: 4284 | H8: 3593 | I8: 14410 | K8: Tabla 47
B9: Promedio global Pruebas Saber Pro | C9: 145 | D9: 147 | E9: 142 | F9: 143 | G9: 141 | H9: 141 | I9: 141 | K9: revisar tabla 131
A10: Socioemocional | B10: Estudiantes en centro de Psicología | C10: 558 | D10: 180 | E10: 183 | F10: 216 | G10: 114 | H10: 299 | I10: 198 | K10: revisar tabla 131
B11: Participación de estudiantes en actividades de Cultura inclusiva y Prácticas pedagógicas | C11: 65 | D11: 2578 | E11: 4121 | F11: 245 | G11: 1628 | H11: 151 | I11: 301 | K11: tabla 209 y tabla 131 a 134
A12: Cultural y artística | B12: Estudiantes en actividades deportivas | C12: 2246 | D12: 1177 | E12: 1526 | F12: 1975 | G12: 2561 | H12: 2947 | I12: 2501 | J12: 1939 | K12: Tabla 166
B13: Estudiantes en actividades culturales y artísticas | C13: 957 | D13: 633 | E13: 414 | F13: 755 | G13: 1103 | H13: 1149 | I13: 1010 | J13: 12686 | K13: Tabla 165
A14: Ambiental y sostenible | B14: Artículos Divulgación periódica revistas: Especializada en los Objetivos de Desarrollo Sostenible - ODS | C14: - | D14: - | E14: 11 | F14: 10 | G14: - | H14: - | I14: - | K14: Tabla 44

Sheet Tabla 29
A1: Tabla NO | B1: 29
A2: Nombre | B2: Visualizaciones del informe de sostenibilidad anual
A4: AÑO DEL INFORME | B4: 2025-1 | C4: 2025-2 | D4: 2026-1
A5: 2019 | B5: 3292 | C5: 3664 | D5: 4274
A6: 2020 | B6: 2320 | C6: 2512 | D6: 3958
A7: 2021 | B7: 3637 | C7: 3908 | D7: 6344
A8: 2022 | B8: 162767 | C8: 175069 | D8: 233123
A9: 2023 | B9: 8709 | C9: 8854 | D9: 9786
A10: 2024 | B10: 18195 | C10: 33111 | D10: 89295
A11: 2025 | D11: 41816

Sheet Tabla 32
A1: Tabla NO | B1: 32
A2: Nombre | B2: Personal administrativo beneficiado con políticas de estímulos
B4: 2019-2 | C4: 2020-1 | D4: 2020-2 | E4: 2021-1 | F4: 2021-2 | G4: 2022-1 | H4: 2022-2 | I4: 2023-1 | J4: 2023-2 | K4: 2024-1 | L4: 2024-2 | M4: 2025-1 | N4: 2025-2 | O4: 2026-1
A5: Auxilios otorgados para formaciones como bilingüismo, capacitaciones | B5: 13 | C5: 8 | D5: 8 | E5: 5 | F5: 7 | G5: 40 | H5: 34 | I5: 36 | J5: 24 | K5: 27 | L5: 21 | M5: 15
A6: Número de becas para colaboradores y familiares (administrativos) | B6: 96 | C6: 92 | D6: 82 | E6: 111 | F6: 120 | G6: 78 | H6: 92 | I6: 93 | J6: 109 | K6: 85 | L6: =38+26 -> 64 | M6: =82+38 -> 120

Sheet Tabla 33
A1: Tabla NO | B1: 33
A2: Nombre | B2: Participación de administrativos en formación
A4: Año | B4: 2019-2 | C4: 2020-1 | D4: 2020-2 | E4: 2021-1 | F4: 2021-2 | G4: 2022-1 | H4: 2022-2 | I4: 2023-1 | J4: 2023-2 | K4: 2024-1 | L4: 2024-2 | M4: 2025-1 | N4: 2025-2 | O4: 2026-1 | P4: Total general
A5: Bilingüe | D5: 19 | E5: 6 | F5: 2 | G5: 26 | H5: 20 | I5: 32 | J5: 21 | K5: 22 | L5: 16 | M5: 13 | P5: =+SUM(B5:O5) -> 177
A6: Complementaria | B6: 185 | C6: 238 | D6: 1038 | E6: 80 | F6: 721 | G6: 630 | H6: 1519 | I6: 129 | J6: 1994 | K6: 1329 | L6: 1804 | M6: 226 | P6: =+SUM(B6:O6) -> 9893
A7: Digital | B7: 2 | C7: 102 | D7: 427 | E7: 409 | F7: 677 | G7: 15 | H7: 384 | I7: 267 | J7: 406 | K7: 475 | L7: 240 | M7: 100 | P7: =+SUM(B7:O7) -> 3504
A8: Disciplinar | B8: 13 | C8: 61 | D8: 175 | E8: 2752 | F8: 842 | G8: 1025 | H8: 593 | I8: 471 | J8: 375 | K8: 1177 | L8: 2633 | M8: 673 | P8: =+SUM(B8:O8) -> 10790
A9: Investigación, Innovación, Internacionalización | B9: 21 | C9: 86 | D9: 62 | E9: 25 | F9: 92 | G9: 56 | H9: 25 | I9: 44 | J9: 43 | K9: 12 | L9: 19 | M9: 56 | P9: =+SUM(B9:O9) -> 541
A10: Pedagógica | B10: 20 | C10: 98 | D10: 74 | E10: 220 | F10: 142 | G10: 47 | H10: 39 | I10: 18 | J10: 37 | K10: 102 | L10: 48 | M10: 737 | P10: =+SUM(B10:O10) -> 1582
A11: POLISIGS | B11: 37 | C11: 856 | D11: 1938 | E11: 1138 | F11: 2158 | G11: 489 | H11: 555 | I11: 708 | J11: 220 | K11: 928 | L11: 2201 | M11: 322 | P11: =+SUM(B11:O11) -> 11550
A12: Total general | B12: 278 | C12: 1441 | D12: 3733 | E12: 4630 | F12: 4634 | G12: 2288 | H12: 3135 | I12: 1669 | J12: 3096 | K12: =SUM(K5:K11) -> 4045 | L12: =SUM(L5:L11) -> 6961 | M12: =SUM(M5:M11) -> 2127 | P12: =+SUM(B12:O12) -> 38037

Sheet Tabla 34
A1: Tabla NO | B1: 34
A2: Nombre | B2: Ascensos en la planta administrativa
A4: Año | B4: Número
A5: 2019 | B5: 27
A6: 2020 | B6: 38
A7: 2021 | B7: 40
A8: 2022 | B8: 50
A9: 2023 | B9: 42
A10: 2024 | B10: 28
A11: 2025 | B11: 23 | C11: Se actualiza al cierre de año
A12: 2026-1 | B12: 9
A13: Total | B13: =SUM(B5:B12) -> 257
A14: Total general | B14: =+B13 -> 257

Sheet Ilustración 20
A1: Tabla NO | B1: Ilustración 20
A2: Nombre | B2: Frecuencia de uso de medios de comunicación para informarse
A4: Medio / Plataforma | B4: Instagram | G4: Buscadores (Google, Bing, Safari, Otros) | L4: Youtube | Q4: Facebook | V4: Servicios Streaming | AA4: Televisión por suscripción/plataformas on demand | AF4: Otras Redes Sociales | AK4: Twitter | AP4: Web de medios informativos | AU4: Spotify | AZ4: Televisión Nacional | BE4: TikTok | BJ4: Prensa, revistas y publicaciones digitales | BO4: Radio | BT4: Prensa, revistas y publicaciones impresas
A5: Año | B5: 2022 | C5: 2023 | D5: 2024 | E5: 2025 | F5: 2026 | G5: 2022 | H5: 2023 | I5: 2024 | J5: 2025 | K5: 2026 | L5: 2022 | M5: 2023 | N5: 2024 | O5: 2025 | P5: 2026 | Q5: 2022 | R5: 2023 | S5: 2024 | T5: 2025 | U5: 2026 | V5: 2022 | W5: 2023 | X5: 2024 | Y5: 2025 | Z5: 2026 | AA5: 2022 | AB5: 2023 | AC5: 2024 | AD5: 2025 | AE5: 2026 | AF5: 2022 | AG5: 2023 | AH5: 2024 | AI5: 2025 | AJ5: 2026 | AK5: 2022 | AL5: 2023 | AM5: 2024 | AN5: 2025 | AO5: 2026 | AP5: 2022 | AQ5: 2023 | AR5: 2024 | AS5: 2025 | AT5: 2026 | AU5: 2022 | AV5: 2023 | AW5: 2024 | AX5: 2025 | AY5: 2026 | AZ5: 2022 | BA5: 2023 | BB5: 2024 | BC5: 2025 | BD5: 2026 | BE5: 2022 | BF5: 2023 | BG5: 2024 | BH5: 2025 | BI5: 2026 | BJ5: 2022 | BK5: 2023 | BL5: 2024 | BM5: 2025 | BN5: 2026 | BO5: 2022 | BP5: 2023 | BQ5: 2024 | BR5: 2025 | BS5: 2026 | BT5: 2022 | BU5: 2023 | BV5: 2024 | BW5: 2025 | BX5: 2026
A6: Lo uso todo el tiempo | B6: 54 | C6: 48 | D6: 43 | E6: 33 | F6: 45 | G6: - | H6: 45 | I6: 55 | J6: 38 | K6: 50 | L6: 46 | M6: 46 | N6: 43 | O6: 33 | P6: 40 | Q6: 49 | R6: 44 | S6: 47 | T6: 36 | U6: 38 | V6: 32 | W6: 30 | X6: 31 | Y6: 30 | Z6: 26 | AA6: 29 | AB6: 25 | AC6: 21 | AD6: 24 | AE6: 16 | AF6: 29 | AG6: 23 | AH6: 38 | AI6: 32 | AJ6: 36 | AK6: 32 | AL6: 28 | AM6: 16 | AN6: 13 | AO6: 9 | AP6: 27 | AQ6: 22 | AR6: 17 | AS6: 16 | AT6: 12 | AU6: - | AV6: 26 | AW6: 22 | AX6: 22 | AY6: 25 | AZ6: 26 | BA6: 23 | BB6: 25 | BC6: 23 | BD6: 14 | BE6: 35 | BF6: 32 | BG6: 36 | BH6: 33 | BI6: 38 | BJ6: 21 | BK6: 15 | BL6: 17 | BM6: 16 | BN6: 12 | BO6: 16 | BP6: 14 | BQ6: 13 | BR6: 14 | BS6: 8 | BT6: 9 | BU6: 9 | BV6: 7 | BW6: 9 | BX6: 6
A7: Lo uso de forma frecuente | B7: 29 | C7: 34 | D7: 26 | E7: 33 | F7: 28 | G7: - | H7: 36 | I7: 30 | J7: 34 | K7: 34 | L7: 36 | M7: 34 | N7: 35 | O7: 39 | P7: 32 | Q7: 34 | R7: 34 | S7: 29 | T7: 41 | U7: 31 | V7: 35 | W7: 39 | X7: 35 | Y7: 35 | Z7: 34 | AA7: 33 | AB7: 33 | AC7: 34 | AD7: 33 | AE7: 27 | AF7: 37 | AG7: 34 | AH7: 33 | AI7: 33 | AJ7: 34 | AK7: 28 | AL7: 29 | AM7: 16 | AN7: 21 | AO7: 13 | AP7: 38 | AQ7: 35 | AR7: 27 | AS7: 27 | AT7: 25 | AU7: - | AV7: 30 | AW7: 24 | AX7: 27 | AY7: 23 | AZ7: 34 | BA7: 32 | BB7: 29 | BC7: 28 | BD7: 29 | BE7: 23 | BF7: 24 | BG7: 27 | BH7: 34 | BI7: 26 | BJ7: 36 | BK7: 35 | BL7: 27 | BM7: 27 | BN7: 25 | BO7: 27 | BP7: 28 | BQ7: 21 | BR7: 25 | BS7: 17 | BT7: 22 | BU7: 21 | BV7: 18 | BW7: 21 | BX7: 13
A8: Lo uso ocasionalmente | B8: 8 | C8: 11 | D8: 21 | E8: 23 | F8: 16 | G8: - | H8: 15 | I8: 11 | J8: 17 | K8: 10 | L8: 13 | M8: 15 | N8: 17 | O8: 20 | P8: 23 | Q8: 10 | R8: 12 | S8: 17 | T8: 15 | U8: 16 | V8: 19 | W8: 20 | X8: 23 | Y8: 23 | Z8: 29 | AA8: 21 | AB8: 24 | AC8: 25 | AD8: 24 | AE8: 28 | AF8: 23 | AG8: 31 | AH8: 19 | AI8: 25 | AJ8: 20 | AK8: 17 | AL8: 19 | AM8: 26 | AN8: 23 | AO8: 21 | AP8: 25 | AQ8: 30 | AR8: 32 | AS8: 30 | AT8: 28 | AU8: - | AV8: 18 | AW8: 20 | AX8: 24 | AY8: 21 | AZ8: 25 | BA8: 30 | BB8: 27 | BC8: 26 | BD8: 26 | BE8: 15 | BF8: 17 | BG8: 15 | BH8: 16 | BI8: 16 | BJ8: 27 | BK8: 31 | BL8: 32 | BM8: 30 | BN8: 28 | BO8: 29 | BP8: 28 | BQ8: 32 | BR8: 25 | BS8: 32 | BT8: 36 | BU8: 31 | BV8: 38 | BW8: 31 | BX8: 32
A9: Casi nunca / nunca lo uso | B9: 9 | C9: 7 | D9: 11 | E9: 11 | F9: 12 | G9: - | H9: 4 | I9: 4 | J9: 11 | K9: 6 | L9: 5 | M9: 5 | N9: 5 | O9: 8 | P9: 5 | Q9: 7 | R9: 10 | S9: 7 | T9: 9 | U9: 15 | V9: 14 | W9: 11 | X9: 11 | Y9: 13 | Z9: 11 | AA9: 17 | AB9: 18 | AC9: 20 | AD9: 20 | AE9: 30 | AF9: 11 | AG9: 12 | AH9: 10 | AI9: 10 | AJ9: 10 | AK9: 23 | AL9: 24 | AM9: 42 | AN9: 43 | AO9: 57 | AP9: 10 | AQ9: 13 | AR9: 23 | AS9: 28 | AT9: 36 | AU9: - | AV9: 26 | AW9: 34 | AX9: 27 | AY9: 31 | AZ9: 15 | BA9: 15 | BB9: 19 | BC9: 24 | BD9: 32 | BE9: 27 | BF9: 27 | BG9: 22 | BH9: 17 | BI9: 20 | BJ9: 16 | BK9: 19 | BL9: 24 | BM9: 28 | BN9: 36 | BO9: 28 | BP9: 30 | BQ9: 34 | BR9: 36 | BS9: 43 | BT9: 33 | BU9: 39 | BV9: 37 | BW9: 39 | BX9: 48

Sheet Ilustración 21
A1: Tabla NO | B1: Ilustración 21
A2: Nombre | B2: Medios destacados para el Poli
A5: Canal | B5: Promedio de categoría 2022 | C5: Promedio de categoría 2023 | D5: Promedio de categoría 2024 | E5: Promedio de categoría 2025 | F5: Promedio de categoría 2026 | G5: Poli 2022 | H5: Poli 2023 | I5: Poli 2024 | J5: Poli 2025 | K5: Poli 2026
A6: TBCA | B6: 0 | C6: 0 | D6: 98 | E6: 98 | F6: 99 | G6: 76 | H6: 71 | I6: 91 | J6: 94 | K6: 93
A7: Internet/Redes sociales | B7: 25 | C7: 25 | D7: 88 | E7: 88 | F7: 90 | G7: 31 | H7: 29 | I7: 46 | J7: 48 | K7: 57
A8: TV | B8: 19 | C8: 19 | D8: 64 | E8: 65 | F8: 58 | G8: 27 | H8: 25 | I8: 25 | J8: 25 | K8: 24
A9: Eventos, actividades y ferias universitarias | B9: 15 | C9: 16 | D9: 57 | E9: 57 | F9: 52 | G9: 16 | H9: 18 | I9: 19 | J9: 15 | K9: 19
A10: Recomendación de un amigo o familiar | B10: 16 | C10: 14 | D10: 74 | E10: 74 | F10: 72 | G10: 14 | H10: 15 | I10: 26 | J10: 23 | K10: 28
A11: Radio | B11: 13 | C11: 14 | D11: 57 | E11: 57 | F11: 48 | G11: 17 | H11: 16 | I11: 20 | J11: 17 | K11: 17
A12: Campus, sedes, centros de servicios, oficinas | B12: 12 | C12: 13 | D12: 57 | E12: 57 | F12: 50 | G12: 13 | H12: 15 | I12: 20 | J12: 11 | K12: 17
A13: Vallas y paraderos | B13: 11 | C13: 11 | D13: 53 | E13: 54 | F13: 53 | G13: 11 | H13: 14 | I13: 17 | J13: 17 | K13: 17
A14: Periódicos / Revistas | B14: 12 | C14: 10 | D14: 51 | E14: 51 | F14: 41 | G14: 12 | H14: 12 | I14: 14 | J14: 13 | K14: 12
A15: En algún otro lugar | B15: 7 | C15: 9 | D15: 34 | E15: 34 | F15: 39 | G15: 8 | H15: 11 | I15: 8 | J15: 9 | K15: 9
A16: Transporte público | B16: 7 | C16: 8 | D16: 45 | E16: 46 | F16: 42 | G16: 9 | H16: 8 | I16: 13 | J16: 14 | K16: 12
A17: Anuncios por internet | B17: 20 | C17: 0 | D17: 0 | E17: 0 | F17: 0 | G17: 22 | H17: 0 | I17: 0 | J17: 0 | K17: 0
A18: No he visto/oído | B18: 0 | C18: 0 | D18: 2 | E18: 2 | F18: 1 | G18: 24 | H18: 29 | I18: 9 | J18: 6 | K18: 7

Sheet Ilustración 22
A1: Tabla NO | B1: Ilustración 22
A2: Nombre | B2: Alcance de personas en Redes sociales cuentas del Poli
A4: Periodo | B4: Valor
A5: 2019-2 | B5: 13200188
A6: 2020-1 | B6: 34020199
A7: 2020-2 | B7: 17009280
A8: 2021-1 | B8: 19029200
A9: 2021-2 | B9: 27009290
A10: 2022-1 | B10: 46554692
A11: 2022-2 | B11: 31564416
A12: 2023-1 | B12: 50097397
A13: 2023-2 | B13: 80857419
A14: 2024-1 | B14: 33220565
A15: 2024-2 | B15: 39978224
A16: 2025-1 | B16: 91672969
... A18: 2026-1 | B18: 21399531

Sheet Tabla 36
A1: Tabla NO | B1: 36
A2: Nombre | B2: Leads obtenidos año a año por canal en el Poli
A4: Canales | B4: 2019 | C4: 2020 | D4: 2021 | E4: 2022 | F4: 2023 | G4: 2024.1 | H4: 2024-2 | I4: 2025-1 | J4: 2025-2 | K4: 2026-1
A5: ATL | B5: 18.233 | C5: 14.324 | D5: 17.807 | E5: 20.995 | F5: 30.827 | G5: 13291 | H5: 11793 | I5: 14538 | J5: 14259 | K5: 9186
A6: B2B | B6: 9.393 | C6: 2.009 | D6: 3.609 | E6: 9.323 | F6: 21.653 | G6: 20582 | H6: 15974 | I6: 19968 | J6: 26920 | K6: 28597
A7: BTL | B7: 4.622 | C7: 476 | D7: 1.198 | E7: 19.619 | F7: 7.481 | G7: 5461 | H7: 5753 | I7: 5200 | J7: 3539 | K7: 361
A8: CSU | B8: 37.114 | C8: 35.572 | D8: 21.573 | E8: 20.026 | F8: 38.695 | G8: 18245 | H8: 24362 | I8: 17930 | J8: 14519 | K8: 14285
A9: DIGITAL | B9: 136.96 | C9: 169.926 | D9: 175.394 | E9: 157.391 | F9: 184.4 | G9: 120682 | H9: 104251 | I9: 105415 | J9: 87620 | K9: 101831
A10: HIGH SCHOOL | B10: 3.345 | C10: 31 | D10: 232 | E10: 627 | F10: 2.258 | G10: 3868 | H10: 709 | I10: 3465 | J10: =2139+6 -> 2145 | K10: 2695
A11: INBOUND | B11: 30.211 | C11: 10.203 | D11: 4.823 | E11: 4.673 | F11: 2.984 | G11: 934 | H11: 753 | I11: 2099 | J11: 1843 | K11: 1426
A12: REMARKETING | B12: 1.807 | C12: 1.306 | D12: 1.191 | E12: 1.227 | F12: 533 | G12: 117 | H12: 77 | I12: 197 | J12: 318 | K12: 34
A13: WHATSAPP | I13: 1137 | J13: 1280 | K13: 5882
A14: TOTAL | B14: 241.685 | C14: 233.847 | D14: 225.827 | E14: 233.881 | F14: 288.831 | G14: 183180 | H14: 163672 | I14: =+SUM(I5:I13) -> 169949 | J14: =+SUM(J5:J13) -> 152443 | K14: =+SUM(K5:K13) -> 164297

Sheet Tabla 39
A1: Tabla NO | B1: 39
A2: Nombre | B2: Tipología de recursos documentales en la Biblioteca
B5: 2025 | D5: 2026-1
A6: Tipología Documental | B6: Títulos | C6: Volúmenes | D6: Títulos | E6: Volúmenes
A7: Libros Físicos | B7: 24.233 | C7: 46.172 | D7: 24.234 | E7: 46260
A8: Publicaciones seriadas impresas | B8: 284 | C8: 284 | D8: 310 | E8: 310
A9: Material Audiovisual (películas educativas, cine, documentales y contenido en streaming) | B9: 5.298 | C9: 5.298 | D9: 5.298 | E9: 5.298
A10: Libros digitales | B10: 140.278 | C10: 140.278 | D10: 145.665 | E10: 145665
A11: Recursos electrónicos Bibliográficos (revistas, artículos, noticias, legislación y publicaciones académicas, monografías, tesis) | B11: 18,000,000 | C11: 18,000,000 | D11: 18,000,000 | E11: 18,000,000
A12: Repositorio Institucional | B12: 4.831 | C12: 4.831 | D12: 5.506 | E12: 5.506

Sheet Tabla 40
A1: Tabla NO | B1: 40
A2: Nombre | B2: Libros por área de conocimiento
B3: 2025 | D3: 2026
A4: Áreas del conocimiento | B4: Títulos | C4: Volúmenes | D4: Títulos | E4: Volúmenes
A5: ARTES | B5: 1823 | C5: 5342 | D5: 1844 | E5: 5366
A6: CIENCIAS ADMINISTRATIVAS (CIENCIAS APLICADAS) | B6: 5443 | C6: 10846 | D6: 5516 | E6: 10957
A7: CIENCIAS NATURALES Y MATEMATICAS | B7: 4646 | C7: 7176 | D7: 4665 | E7: 7210
A8: CIENCIAS SOCIALES | B8: 5527 | C8: 10139 | D8: 5592 | E8: 10239
A9: FILOSOFIA Y PSICOLOGIA | B9: 1878 | C9: 2316 | D9: 1919 | E9: 2385
A10: GEOGRAFIA E HISTORIA | B10: 806 | C10: 1237 | D10: 811 | E10: 1244
A11: LENGUAS | B11: 615 | C11: 1302 | D11: 616 | E11: 1304
A12: LITERATURA | B12: 1984 | C12: 3427 | D12: 2025 | E12: 3509
A13: METODOLOGIA, SISTEMAS, INFORMACION Y PERIODISMO | B13: 1123 | C13: 3791 | D13: 1164 | E13: 3847
A14: RELIGION | B14: 81 | C14: 111 | D14: 81 | E14: 111
A15: TOTAL | B15: =SUM(B5:B14) -> 23926 | C15: =SUM(C5:C14) -> 45687 | D15: =SUM(D5:D14) -> 24233 | E15: 46172

Sheet Tabla 41
A1: Tabla NO | B1: 41
A2: Nombre | B2: Revistas por área de conocimiento
A4: Revistas por Áreas | B4: 2025 | C4: 2026-1
A5: Revistas de Ciencias Administrativas, Económicas y Contables | B5: 33 | C5: 37
A6: Revistas de Ciencias Sociales | B6: 21 | C6: 25
A7: Revistas de Ingeniería y Ciencias Básicas | B7: 48 | C7: 48
A8: Revistas de Mercadeo, Comunicación y Artes | B8: 11 | C8: 20
A9: Revistas Generales | B9: 164 | C9: 171
A10: Periódicos y códigos Legis | B10: 7 | C10: 9
A11: Total | B11: 284 | C11: =SUM(C5:C10) -> 310

Sheet Tabla 42
A1: Tabla NO | B1: 42
A2: Nombre | B2: Recursos bibliográficos 2019-2 a 2026-1
B4: 2019 | C4: 2020 | D4: 2020-2 | E4: 2021-1 | F4: 2021 | G4: 2022 | H4: 2022 | I4: 2023 | J4: 2023- | K4: 2024-1 | L4: 2024-2 | M4: 2025-1 | N4: 2025-2 | O4: 2026-1
B5: -2 | C5: -1 | F5: -2 | G5: -1 | H5: -2 | I5: -1 | J5: 2
A6: NUMERO BIBLIOTECAS | B6: 3 | C6: 3 | D6: 3 | E6: 3 | F6: 3 | G6: 3 | H6: 3 | I6: 3 | J6: 3 | K6: 3 | L6: 3 | M6: 3 | N6: 3 | O6: 3
A7: NUMERO DE BASES DE DATOS ESPECIALIZADAS | B7: 93 | C7: 190 | D7: 290 | E7: 390 | F7: 491 | G7: 599 | H7: 707 | I7: 814 | J7: 921 | K7: 111 | L7: 111 | M7: 114 | N7: 114 | O7: 114
A8: NUMERO DE LIBROS ELECTRONICOS | B8: 90278 | C8: 91000 | D8: 91000 | E8: 91000 | F8: 115780 | G8: 120845 | H8: 122642 | I8: 136642 | J8: 137103 | K8: 143000 | L8: 143000 | M8: 143000 | N8: 145665 | O8: 145665
A9: TITULOS DE LIBROS PROPIOS | B9: 23775 | C9: 23814 | D9: 23853 | E9: 23853 | F9: 23854 | G9: 23914 | H9: 24368 | I9: 24270 | J9: 24738 | K9: 21688 | L9: 23914 | M9: 23926 | N9: 24233 | O9: 24274
A10: VOLUMENES (LIBROS) DE LA COLECCION TOTAL PROPIOS | B10: 46083 | C10: 46122 | D10: 46161 | E10: 46161 | F10: 46167 | G10: 46259 | H10: 46905 | I10: 46838 | J10: 47539 | K10: 41695 | L10: 45653 | M10: 45687 | N10: 46172 | O10: 46260
A11: NUMERO DE TITULOS DE LIBROS ADQUIRIDOS EN EL PERIODO ACADEMICO | B11: 239 | C11: 39 | D11: 39 | E11: - | F11: 1 | G11: 53 | H11: 454 | I11: 1 | J11: 468 | K11: 36 | L11: 580 | M11: 12 | N11: 307 | O11: 41
A12: NUMERO DE VOLUMENES (LIBROS) DE LA COLECCION TOTAL ADQUIRIDOS EN EL PERIODO ACADEMICO | B12: 324 | C12: 39 | D12: 39 | E12: - | F12: 6 | G12: 70 | H12: 646 | I12: 14 | J12: 701 | K12: 13 | L12: 664 | M12: 34 | N12: 485 | O12: 45
A13: NUMERO DE TITULOS DE PUBLICACIONES PERIODICAS | B13: 171 | C13: 171 | D13: 171 | E13: 171 | F13: 171 | G13: 51 | H13: 51 | I13: 51 | J13: 51 | K13: 289 | L13: 289 | M13: 289 | N13: 310 | O13: 310
A14: CANTIDAD DE MATERIAL AUDIOVISUAL | B14: 2095 | C14: 2095 | D14: 2095 | E14: 2095 | F14: 2095 | G14: 2095 | H14: 2095 | I14: 2095 | J14: 2095 | K14: 2095 | L14: 2095 | M14: 2095 | N14: 5298 | O14: 5298

Sheet Tabla 43
A1: Tabla NO | B1: 43
A2: Nombre | B2: Uso de los Recursos Bibliográficos 2019-2 a 2026-1
A4: Ítem | B4: 2019-2 | C4: 2020-1 | D4: 2020-2 | E4: 2021-1 | F4: 2021-2 | G4: 2022-1 | H4: 2022-2 | I4: 2023-1 | J4: 2023-2 | K4: 2024-1 | L4: 2024-2 | M4: 2025-1 | N4: 2025-2 | O4: 2026-1
A5: CONMUTACIÓN BIBLIOGRÁFICA | B5: 456 | C5: 2178 | D5: 998 | E5: 681 | F5: 772 | G5: 494 | H5: 579 | I5: 458 | J5: 375 | K5: 513 | L5: 612 | M5: 795 | N5: 810 | O5: 831
A6: CONSULTAS BASE DE DATOS | B6: 47264868 | C6: 48320340 | D6: 44620912 | E6: 131513607 | F6: 215504296 | G6: 131903542 | H6: 132015121 | I6: 28986998 | J6: 16708878 | K6: 29997498 | L6: 20068282 | M6: 30271328 | N6: 29581428 | O6: 35096112
A7: CONSULTA REPOSITORIO INSTITUCIONAL ALEJANDRÍA | B7: 1980 | C7: 860 | D7: 52586 | E7: 54363 | F7: 92443 | G7: 101565 | H7: 91246 | I7: 88613 | J7: 329609 | K7: 153846 | L7: 322310 | M7: 639346 | N7: 1264296 | O7: 1021821
A8: CONSULTA DE LIBROS EN SALAS | B8: 6654 | C8: 3901 | D8: - | E8: - | F8: 989 | G8: 4119 | H8: 683 | I8: 560 | J8: 1213 | K8: 3800 | L8: 2170 | M8: 2380 | N8: 5489 | O8: 2398
A9: CONSULTAS DESCUBRIDOR RECURSOS BIBLIOGRÁFICOS | B9: 3861 | C9: 3495 | D9: 4679 | E9: 64195 | F9: 5253211 | G9: 101254 | H9: 101589 | I9: 235900 | J9: 1133876 | K9: 8423312 | L9: 1127727 | M9: 1145123 | N9: 8429749 | O9: 1154000
A10: PRÉSTAMO CUBÍCULOS DE ESTUDIO | B10: 3828 | C10: 1992 | D10: - | E10: - | F10: 580 | G10: 3661 | H10: 3153 | I10: 8236 | J10: 4856 | K10: 6992 | L10: 6308 | M10: 6630 | N10: 6692 | O10: 6721
A11: PRÉSTAMO CUBÍCULOS DE VIDEO | B11: 1630 | C11: 955 | D11: - | E11: - | F11: 8 | G11: 1010 | H11: 1057 | I11: 2159 | J11: 1646 | K11: 1739 | L11: 1442 | M11: 1548 | N11: 2335 | O11: 1610
A12: PRÉSTAMO EXTERNO LIBROS | B12: 4156 | C12: 2179 | D12: - | E12: - | F12: 639 | G12: 3462 | H12: 557 | I12: 5567 | J12: 1880 | K12: 1886 | L12: 4323 | M12: 4380 | N12: 5262 | O12: 5923
A13: INGRESOS A LA BIBLIOTECA | B13: 92424 | C13: 25550 | D13: - | E13: - | F13: 15936 | G13: 46283 | H13: 45769 | I13: 52094 | J13: 176260 | K13: 133155 | L13: 139574 | M13: 133243 | N13: 139602 | O13: 133197
A14: CONSULTA LIBROS ELECTRÓNICOS | B14: 57260 | C14: 41993 | D14: 38209 | E14: 126887 | F14: 329153 | G14: 333954 | H14: 349815 | I14: 1052760 | J14: 579228 | K14: 2146159 | L14: 1550653 | M14: 1938888 | N14: 4095873 | O14: 2462401
A15: PRÉSTAMO MATERIAL AUDIOVISUAL | B15: 1536 | C15: 1017 | D15: - | E15: - | F15: 11 | G15: 784 | H15: 848 | I15: 1712 | J15: 1455 | K15: 1634 | L15: 2399 | M15: 4201 | N15: 2902 | O15: 2526
A16: PRÉSTAMO COMPUTADORES | B16: 11640 | C16: 4122 | D16: - | E16: - | F16: 1672 | G16: 5406 | H16: 4081 | I16: 11302 | J16: 7401 | K16: 8971 | L16: 9235 | M16: 8606 | N16: 9650 | O16: 8764
A17: PRÉSTAMO DE TABLETS | B17: 692 | C17: 475 | D17: - | E17: - | F17: 4 | G17: 1596 | H17: 1392 | I17: 870 | J17: 1927 | K17: 237 | L17: 57 | M17: 88 | N17: 553 | O17: 67
A18: PRÉSTAMO DE PUBLICACIONES PERIÓDICAS | B18: 2866 | C18: 3911 | D18: - | E18: - | F18: 2187 | G18: 1543 | H18: 2236 | I18: 704 | J18: 2110 | K18: 504 | L18: 989 | M18: 1014 | N18: 1243 | O18: 1027

Sheet Tabla 44
A1: Tabla NO | B1: 44
A2: Nombre | B2: Divulgación periódica revistas
D4: Artículos
A5: Nombre de la revista | B5: Área temática | C5: Periodicidad | D5: 2019 | E5: 2020 | F5: 2021 | G5: 2022 | H5: 2023 | I5: 2024-1 | J5: 2024-2 | K5: 2025-1 | L5: 2025-2 | M5: 2026-1
A6: Panorama | B6: Académica en Educación y ELearning | C6: Semestral | D6: 18 | E6: 20 | F6: 32 | G6: 35 | H6: 32 | I6: 8 | J6: 7 | K6: 3
A7: ISSN-L: 1909-7433 / E-ISSN: 2145-308X
A8: Punto de Vista | B8: Divulgativa en Administración, economía y contabilidad | C8: Anual | D8: 19 | E8: 13 | F8: 12 | G8: 16 | H8: 13 | I8: 0 | J8: 9 | K8: 10
A9: ISSN-L: 0123-580X / E-ISSN: 2027-5153
A10: Poliantea | B10: Divulgativa en la Facultad: Sociedad, cultura y creatividad | C10: Semestral | D10: 9 | E10: 41 | F10: 41 | G10: 14 | H10: 5 | I10: 0 | J10: 4 | K10: 5
A11: ISSN-L: 1794-3159 / E-ISSN: 2145-3101
A12: Likan | B12: Divulgativa en diseño de modas | C12: Semestral | D12: 22 | E12: 44 | F12: 45 | G12: 45 | H12: 26 | I12: 9 | J12: 8 | K12: 0
A13: E-ISSN: 2711-3698
A14: Elementos | B14: Divulgativa en ingeniería | C14: Anual | G14: 8 | H14: 0 | I14: 0 | J14: 8 | K14: 0
A15: ISSN-L: 2248-5252 / E-ISSN: 2027-923X
A16: Revista Multicultural La Moviola | B16: Divulgativa en temas audiovisuales | C16: Semestral | D16: 22 | E16: 30 | F16: 48 | G16: 44 | H16: 11 | I16: 7 | J16: 7 | K16: 5
A17: ISSN: 2665-556X
A18: Revista Prototypo | B18: Divulgativa para la Escuela de Diseño | C18: Anual | E18: 10 | F18: 8 | G18: 6 | H18: 9 | I18: 0 | J18: 7 | K18: 0
A19: ISSN: 2590-7743
A21: Encuentros con Semilleros | B21: Divulgación de proyectos de investigación formativa | C21: Anual | D21: 27 | E21: 28 | F21: 0 | G21: 9 | H21: 0 | I21: 0 | J21: 0 | K21: 2
A22: ISSN: 2711-4414 (En línea)
A23: Gestión de la seguridad y la salud en el trabajo | B23: Divulgativa de proyectos asociados a la salud y seguridad en el trabajo | C23: Semestral | D23: 9 | E23: 14 | F23: 9 | G23: 36 | H23: 28 | I23: 12 | J23: 12 | K23: 11
A24: ISSN: 2744-8398 (En línea)
A25: Nuevos desafíos del derecho | B25: Especializada en derecho | C25: Anual | F25: 9 | G25: 8 | H25: 8 | I25: 7 | J25: 6 | K25: 8
A26: ISSN: 2745-1461 (En línea)
A27: Objetivo de desarrollo sostenible | B27: Especializada en los Objetivos de Desarrollo Sostenible - ODS | C27: Anual | F27: 11 | G27: 10 | H27: Fin
A28: ISSN: 2805-6418 (En línea)
A29: Posibilidades | B29: Divulgativa en proyectos de investigación en creación | C29: Anual | E29: 12 | F29: 22 | G29: 12 | H29: 6 | I29: 0 | J29: 7 | K29: 0
A30: ISSN: 2805-5926 (En línea)

Sheet Gráfico 3
A1: Tabla NO | B1: 3
A2: Nombre | B2: Estado de los ambientes inmersivos 2025
C4: Valor
B5: Para programar | C5: 9
B6: En desarrollo | C6: 6
B7: En pruebas | C7: 7
B8: Para implementar | C8: 8
B9: En aula | C9: 23
A20: Tabla NO | B20: 3
A21: Nombre | B21: Estado de los ambientes inmersivos 2026
C23: Valor
B24: Para programar | C24: 3
B25: En desarrollo | C25: 2
B26: En pruebas | C26: 1
B27: Para implementar | C27: 11
B28: En aula | C28: 28

Sheet Tabla 45
A1: Tabla NO | B1: 45
A2: Nombre | B2: Ambientes inmersivos registrados a nombre del Politécnico Grancolombiano 2025
B4: Registrados | C4: En proceso | D4: Por solicitar | E4: Total
B5: 24 | C5: 0 | D5: 11 | E5: 35
A9: Tabla NO | B9: 45
A10: Nombre | B10: Ambientes inmersivos registrados a nombre del Politécnico Grancolombiano 2026-1
B12: Registrados | C12: En proceso | D12: Por solicitar | E12: Total
B13: 24 | C13: 0 | D13: 26 | E13: 50

Sheet Tabla 46
A1: Tabla NO | B1: 46
A2: Nombre | B2: Histórico de la salida a los estudiantes de los diferentes ambientes
B4: ACTIVIDAD | C4: 2019 | D4: 2020 | E4: 2021 | F4: 2022 | G4: 2023 | H4: 2024 | I4: 2025 | J4: 2026-1
B5: Proyectos en aula virtual | C5: 4 | D5: 8 | E5: 9 | F5: 1 | G5: 1 | H5: 3 | I5: 4
B6: Proyectos listos para salir a aula | E6: 1 | F6: 7 | G6: 0 | H6: 0 | I6: 8 | J6: 11

Sheet Tabla 47
A1: Tabla NO | B1: 47
A2: Nombre | B2: Uso de los ambientes inmersivos por los estudiantes Poli
B4: Ambiente inmersivo | C4: Total 2019 | D4: Total 2020 | E4: Total 2021 | F4: Total 2022 | G4: Total 2023 | H4: Total 2024 | I4: Total 2025 | J4: Total 2026-1
H5: 2024
B6: Simulador de Análisis Financiero | C6: 8 | D6: 26 | E6: 2655 | F6: 2464 | G6: 2082 | H6: 1819 | I6: 1901 | J6: 680
B7: Simulador de Control de Calidad | C7: 0 | D7: 60 | E7: 1707 | F7: 1643 | G7: 1709 | H7: 1447 | I7: 1380 | J7: 659
B8: Simulador de Costos por órdenes y por procesos | C8: 0 | D8: 36 | E8: 706 | F8: 420 | G8: 299 | H8: 428 | I8: 48 | J8: 325
B9: Software de Diagnostico Empresarial | C9: 65 | D9: 87 | E9: 2 | F9: 38 | G9: 0 | H9: 0 | I9: 0 | J9: 0
B10: Simulador de Evaluación Financiera de proyectos | C10: 1 | D10: 0 | E10: 5 | F10: 12 | G10: 0 | H10: 0 | I10: 0 | J10: 0
B11: Simulador de Finanzas corporativas | C11: 0 | D11: 1 | E11: 155 | F11: 3765 | G11: 3330 | H11: 3550 | I11: 1989 | J11: 539
B12: Software para el Diagnóstico de las Habilidades Gerenciales | C12: 420 | D12: 3736 | E12: 3087 | F12: 3104 | G12: 2875 | H12: 3350 | I12: 3714 | J12: 1653
B13: Simulador de eventos discretos | C13: 2 | D13: 50 | E13: 1572 | F13: 1549 | G13: 1604 | H13: 1576 | I13: 1578 | J13: 807
B14: Simulador de Producción | C14: 0 | D14: 0 | E14: 127 | F14: 857 | G14: 1561 | H14: 1652 | I14: 1619 | J14: 712
B15: Juego para la gerencia de mercadeo | C15: 0 | D15: 6 | E15: 40 | F15: 1 | G15: 0 | H15: 0 | I15: 0 | J15: 0
B16: Juego de Proceso Estratégico - matrices | C16: 0 | D16: 0 | E16: 85 | F16: 4389 | G16: 4284 | H16: 3593 | I16: 4399 | J16: 2216
B17: Laboratorio Virtual Física 1 | C17: 24 | D17: 1644 | E17: 2542 | F17: 2328 | G17: 2331 | H17: 2826 | I17: 2621 | J17: 1396
... B35: Simlador de Psicología comunitaria | C35: 0 | D35: 0 | E35: 0 | F35: 0 | G35: 0 | H35: 0 | I35: 0 | J35: 0
B36: TOTAL | C36: 1119 | D36: 8970 | E36: 23269 | F36: 28783 | G36: 28639 | H36: 29431 | I36: =SUM(I6:I30) -> 27001 | J36: =SUM(J6:J35) -> 12952

Sheet Tabla 48
A1: Tabla NO | B1: 48
A2: Nombre | B2: Distribución de los MI-Books por facultades
A4: FNGS | B4: FSCC | C4: FIDI | D4: Dirección de Currículo | E4: Aseguramiento de la Calidad
A5: 41 | B5: 60 | C5: 33 | D5: 4 | E5: 1
A6: 0.2949 | B6: 43,16% | C6: 23,74% | D6: 2,87% | E6: 0,71%

Sheet Tabla 49
A1: Tabla NO | B1: 49
A2: Nombre | B2: Visitas MI-Books por país
B3: 2024-1 | D3: 2024-2 | F3: 2025-1 | H3: 2025-2 | J3: 2026-1
A4: País | B4: Porcentaje | C4: Visitas | D4: Porcentaje | E4: Visitas | F4: Porcentaje | G4: Visitas | H4: Porcentaje | I4: Visitas | J4: Porcentaje | K4: Visitas
A5: Colombia | B5: 0.6257 | C5: 325571 | D5: 0.9468 | E5: 523724 | F5: 0.867 | G5: 334786 | H5: 0.8366 | I5: 332398 | J5: 0.599 | K5: 222492
A6: Estados unidos | B6: 0.3563 | C6: 185394 | D6: 0.024 | E6: 13276 | F6: 0.033 | G6: 12671 | H6: 0.0328 | I6: 13032 | J6: 0.1476 | K6: 54767
A7: México | B7: 0.008 | C7: 4163 | D7: 0.0142 | E7: 7855 | F7: 0.041 | G7: 15955 | H7: 0.0413 | I7: 16409 | J7: 0.1658 | K7: 61613
A8: España | B8: 0.001 | C8: 520 | D8: 0.004 | E8: 2213 | F8: 0.005 | G8: 1932 | H8: 0.0005 | I8: 198 | J8: 0.023 | K8: 8577
A9: Ecuador | B9: 0.001 | C9: 520 | D9: 0.003 | E9: 1659 | F9: 0.004 | G9: 1429 | H9: 0.0037 | I9: 1470 | J9: 0.009 | K9: 3422
A10: Perú | B10: 0.001 | C10: 520 | D10: 0.004 | E10: 2213 | F10: 0.009 | G10: 3322 | H10: 0.086 | I10: 3416 | J10: 0.001 | K10: 6845
A11: Costa Rica | B11: 0.001 | C11: 520 | D11: 0.002 | E11: 1106 | F11: 0.007 | G11: 2627 | H11: 0 | I11: 0 | J11: 0.001 | K11: 3422
A12: Indonesia | B12: 0.001 | C12: 520 | D12: 0.0012 | E12: 664 | F12: 0.035 | G12: 13598 | H12: 0.0356 | I12: 13985 | J12: 0 | K12: 0
A13: Alemania | B13: 0.005 | C13: 2602 | D13: 0.0008 | E13: 443 | F13: 0 | G13: 0 | H13: 0 | I13: 0 | J13: 0.027 | K13: 10268
A14: TOTAL | B14: =SUM(B5:B13) -> 1 | C14: 520331 | D14: =SUM(D5:D13) -> 1 | E14: 553152 | F14: 1 | G14: 386321 | H14: 1 | I14: 397499 | J14: 1 | K14: 529889
M16: 397499
M17: 386321
M18: =M16+M17 -> 783820

Sheet Gráfico 4
A1: Tabla NO | B1: 4
A2: Nombre | B2: Medición uso recorridos
C4: 2024 | D4: 2025 | E4: 2026-1
B5: Usuarios activos | C5: 6000 | D5: 4800
B6: Números de eventos | C6: 82000 | D6: 18000
B7: Usuarios nuevos | C7: 5900 | D7: 4600
B9: Recorridos 360° | C9: 2024-2 | D9: 2025-1 | E9: 2025-2 | F9: 2026-1 | G9: TOTAL
B10: Recorrido Sede Colores - Medellín | C10: 0 | D10: 0 | E10: 429 | F10: 2901 | G10: =SUM(D10:F10) -> 3330
B11: Recorrido Calle 85 | C11: 0 | D11: 0 | E11: 383 | F11: 1835 | G11: =SUM(D11:F11) -> 2218
B12: Recorrido Procesos lácteos | C12: 0 | D12: 2 | E12: 279 | F12: 245 | G12: =SUM(D12:F12) -> 526
B13: Recorrido Procesos pecuarios | C13: 0 | D13: 2 | E13: 205 | F13: 123 | G13: =SUM(D13:F13) -> 330
B14: Recorrido Protege tu paramo | C14: 0 | D14: 18 | E14: 11092 | F14: 15140 | G14: =SUM(D14:F14) -> 26250 | L14: 18 | M14: 11092 | N14: =L14+M14 -> 11110 | P14: 15140
B15: Recorrido Citycampus | C15: 0 | D15: 87 | E15: 4270 | F15: 7336 | G15: =SUM(D15:F15) -> 11693 | L15: 2 | M15: 279 | N15: =L15+M15 -> 281 | P15: 123
B16: Recorrido Campus principal | C16: 0 | D16: 238 | E16: 11654 | F16: 19396 | G16: =SUM(D16:F16) -> 31288 | L16: 2 | M16: 205 | N16: =L16+M16 -> 207 | P16: 245
B17: Recorrido Desarrollo sostenible | C17: 0 | D17: 0 | E17: 0 | F17: 23 | G17: =SUM(D17:F17) -> 23 | N17: =N14+N15+N16 -> 11598 | P17: 23
B18: TOTAL | C18: 0 | D18: =SUM(D10:D17) -> 347 | E18: =SUM(E10:E17) -> 28312 | F18: =SUM(F10:F17) -> 46999 | G18: =SUM(G10:G17) -> 75658 | P18: =SUM(P14:P17) -> 15531
B20: Salas Virtuales CREA | C20: 2024-2 | D20: 2025-1 | E20: 2025-2 | F20: 2026-1 | G20: TOTAL
B21: Salas virtuales de audiencias y conciliación - derecho laboral | C21: 27 | D21: 39 | E21: 293 | F21: 526 | G21: =SUM(C21:F21) -> 885
B22: Salas virtuales de asamblea - OEA | C22: 7 | D22: 15 | E22: 12 | F22: 450 | G22: =SUM(C22:F22) -> 484
B23: Salas virtuales de audiencias y conciliación - derecho penal | C23: 16 | D23: 49 | E23: 96 | F23: 131 | G23: =SUM(C23:F23) -> 292
B24: Salas virtuales de audiencias y conciliación - derecho público | C24: 12 | D24: 15 | E24: 11 | F24: 75 | G24: =SUM(C24:F24) -> 113
B25: Salas virtuales de audiencias y conciliación - derecho privado | C25: 111 | D25: 33 | E25: 46 | F25: 39 | G25: =SUM(C25:F25) -> 229
B26: Salas virtuales de asamblea - ONU | C26: 66 | D26: 63 | E26: 365 | F26: 35 | G26: =SUM(C26:F26) -> 529
B27: Salas de negociación | C27: 23 | D27: 32 | E27: 52 | F27: 18 | G27: =SUM(C27:F27) -> 125
B28: Sala de audiencias y concertación virtual | C28: 40 | D28: 38 | E28: 19 | F28: 9 | G28: =SUM(C28:F28) -> 106
B29: TOTAL | C29: =SUM(C21:C28) -> 302 | D29: =SUM(D21:D28) -> 284 | E29: =SUM(E21:E28) -> 894 | F29: =SUM(F21:F28) -> 1283 | G29: =SUM(G21:G28) -> 2763
B31: Aplicativos Didácticos CREA | C31: 2024-2 | D31: 2025-1 | E31: 2025-2 | F31: 2026-1 | G31: TOTAL
B32: Cuadro integral de mando | C32: 0 | D32: 33 | E32: 56 | F32: 167 | G32: =SUM(C32:F32) -> 256
B33: Construcción de objetivos | C33: 0 | D33: 56 | E33: 66 | F33: 136 | G33: =SUM(C33:F33) -> 258
B34: Construyendo conceptos financieros | C34: 0 | D34: 0 | E34: 123 | F34: 102 | G34: =SUM(C34:F34) -> 225
B35: Cuerpo en movimiento | C35: 0 | D35: 43 | E35: 51 | F35: 49 | G35: =SUM(C35:F35) -> 143
B36: Plataforma de inventario de medios | C36: 106 | D36: 24 | E36: 60 | F36: 41 | G36: =SUM(C36:F36) -> 231
B37: Matriz de stakeholders | C37: 139 | D37: 33 | E37: 168 | F37: 18 | G37: =SUM(C37:F37) -> 358
B38: Calculadora de Huella Ecológica | C38: 0 | D38: 0 | E38: 6 | F38: 14 | G38: =SUM(C38:F38) -> 20
B39: Construyendo conceptos: Pensamiento en diseño | C39: 0 | D39: 0 | E39: 0 | F39: 11 | G39: =SUM(C39:F39) -> 11
B40: Descifrando enigma | C40: 1 | D40: 3 | E40: 52948 | F40: 64085 | G40: =SUM(C40:F40) -> 117037
B41: TOTAL | C41: =SUM(C33:C40) -> 246 | D41: =SUM(D33:D40) -> 159 | E41: =SUM(E33:E40) -> 53422 | F41: =SUM(F33:F40) -> 64456 | G41: =SUM(G33:G40) -> 118283
B43: Juegos Digitales Educativos CREA | C43: 2024-2 | D43: 2025-1 | E43: 2025-2 | F43: 2026-1 | G43: TOTAL
B44: Desafio Financiero 360° | C44: 0 | D44: 139 | E44: 1 | F44: 722 | G44: =SUM(C44:F44) -> 862
B45: Operaciones básicas en matemáticas | C45: 0 | D45: 0 | E45: 96 | F45: 56 | G45: =SUM(C45:F45) -> 152
B46: ECPA | C46: 0 | D46: 0 | E46: 0 | F46: 38 | G46: =SUM(C46:F46) -> 38
B47: Gestión de inventarios | C47: 0 | D47: 22 | E47: 132 | F47: 37 | G47: =SUM(C47:F47) -> 191
B48: Juego Memoria Poli | C48: 0 | D48: 0 | E48: 0 | F48: 36 | G48: =SUM(C48:F48) -> 36
B49: Modelo Canva para la cadena de producción | C49: 0 | D49: 3 | E49: 0 | F49: 0 | G49: =SUM(C49:F49) -> 3
B50: TOTAL | C50: =SUM(C44:C49) -> 0 | D50: =SUM(D44:D49) -> 164 | E50: =SUM(E44:E49) -> 229 | F50: =SUM(F44:F49) -> 889 | G50: =SUM(G44:G49) -> 1282

Sheet Tabla 53
A1: Tabla NO | B1: 53
A2: Nombre | B2: Talleres y laboratorios de la Institución 2025 | F2: Talleres y laboratorios de la Institución 2026-1
A4: ESPACIO | B4: LABORATORIOS | C4: TALLER | D4: AULA ESPECIALIZADA | F4: ESPACIO | G4: LABORATORIOS | H4: TALLER | I4: AULA ESPECIALIZADA
A5: BLOQUE J CAMPUS PRINCIPAL | F5: BLOQUE J CAMPUS PRINCIPAL
A6: TALLER DE CERÁMICA | C6: 1 | F6: TALLER DE CERÁMICA | H6: 1
A7: TALLER DE PINTURA | C7: 1 | F7: TALLER DE PINTURA | H7: 1
A8: TALLER DE METALES | C8: 1 | F8: TALLER DE METALES | H8: 1
A9: TALLER DE MADERA | C9: 1 | F9: TALLER DE MADERA | H9: 1
A10: TALLER DE TERMOFROMADO | C10: 1 | F10: TALLER DE TERMOFROMADO | H10: 1
A11: TALLER DE PROTOTIPADO | C11: 1 | F11: TALLER DE PROTOTIPADO | H11: 1
A12: AULA TALLER | C12: 1 | F12: AULA TALLER | H12: 1
A13: BLOQUE L CAMPUS PRINCIPAL | F13: BLOQUE L CAMPUS PRINCIPAL
A14: LABORATORIO DE FÍSICA | B14: 1 | F14: LABORATORIO DE FÍSICA | G14: 1
A15: LABORATORIO DE ELECTRÓNICA | B15: 1 | F15: LABORATORIO DE ELECTRÓNICA | G15: 1
A16: LABORATORIO DE QUÍMICA | B16: 1 | F16: LABORATORIO DE QUÍMICA | G16: 1
A17: LABORATORIO PRIMER PISO | B17: 1 | F17: LABORATORIO PRIMER PISO | G17: 1
A18: BLOQUE K CAMPUS PRINCIPAL | F18: BLOQUE K CAMPUS PRINCIPAL
A19: LABORATORIO DE FOTOGRAFÍA | B19: 1 | F19: LABORATORIO DE FOTOGRAFÍA | G19: 1
A20: LABORATORIO DE REDES | B20: 1 | F20: LABORATORIO DE REDES | G20: 1
A21: ESTUDIOS DE FOTOGRAFÍA 1 | B21: 1 | F21: ESTUDIOS DE FOTOGRAFÍA 1 | G21: 1
A22: ESTUDIOS DE FOTOGRAFÍA 2 | B22: 1 | F22: ESTUDIOS DE FOTOGRAFÍA 2 | G22: 1
A23: SALA DE POSTPRODUCCIÓN DE VIDEO 1 | B23: 1 | F23: SALA DE POSTPRODUCCIÓN DE VIDEO 1 | G23: 1
A24: SALA DE POSTPRODUCCIÓN DE VIDEO 2 | B24: 1 | F24: SALA DE POSTPRODUCCIÓN DE VIDEO 2 | G24: 1
A25: SALA DE POSTPRODUCCIÓN DE VIDEO 3 | B25: 1 | F25: SALA DE POSTPRODUCCIÓN DE VIDEO 3 | G25: 1
A26: SALA DE SONIDO 1 | B26: 1 | F26: SALA DE SONIDO 1 | G26: 1
A27: SALA DE SONIDO 2 | B27: 1 | F27: SALA DE SONIDO 2 | G27: 1
A28: SALA DE SONIDO 3 | B28: 1 | F28: SALA DE SONIDO 3 | G28: 1
A29: ESTUDIOS DE CINE Y TELEVISIÓN 1 | B29: 1 | F29: ESTUDIOS DE CINE Y TELEVISIÓN 1 | G29: 1
A30: ESTUDIOS DE CINE Y TELEVISIÓN 2 | B30: 1 | F30: ESTUDIOS DE CINE Y TELEVISIÓN 2 | G30: 1
A31: TALLER DE MODAS Y CONFECCIÓN | C31: 1 | F31: TALLER DE MODAS Y CONFECCIÓN | H31: 1
A32: MASTER DE VIDEO 1 | B32: 1 | F32: MASTER DE VIDEO 1 | G32: 1
A33: MASTER DE VIDEO 2 | B33: 1 | F33: MASTER DE VIDEO 2 | G33: 1
A34: AULAS ESPECIALIZADAS | F34: AULAS ESPECIALIZADAS
A35: RETOS BLOQUE F 1 CAMPUS PRINCIPAL | D35: 1 | F35: RETOS BLOQUE F 1 CAMPUS PRINCIPAL | I35: 1
A36: RETOS BLOQUE F 2 CAMPUS PRINCIPAL | D36: 1 | F36: RETOS BLOQUE F 2 CAMPUS PRINCIPAL | I36: 1
A37: MAKERLAB BLOQUE H CAMPUS PRINCIPAL | D37: 1 | F37: MAKERLAB BLOQUE H CAMPUS PRINCIPAL | I37: 1
A38: SALON EMPRESAS SIMULADAS BLOQUE E CAMPUS PRINCIPAL | D38: 1 | F38: SALON EMPRESAS SIMULADAS BLOQUE E CAMPUS PRINCIPAL | I38: 1
A39: SALÓN DE BOLSA BLOQUE D CAMPUS PRINCIPAL | D39: 1 | F39: SALÓN DE BOLSA BLOQUE D CAMPUS PRINCIPAL | I39: 1
A40: AULA FLEXIBLE BLOQUE H 1 CAMPUS PRINCIPAL | D40: 1 | F40: AULA FLEXIBLE BLOQUE H 1 CAMPUS PRINCIPAL | I40: 1
A41: AULA FLEXIBLE BLOQUE H 2 CAMPUS PRINCIPAL | D41: 1 | F41: AULA FLEXIBLE BLOQUE H 2 CAMPUS PRINCIPAL | I41: 1
A42: SALA DE AUDIENCIAS BLOQUE B CAMPUS PRINCIPAL | D42: 1 | F42: SALA DE AUDIENCIAS BLOQUE B CAMPUS PRINCIPAL | I42: 1
A43: CAMARA DE GESSEL BLOQUE B CAMPUS PRINCIPAL | D43: 1 | F43: CAMARA DE GESSEL BLOQUE B CAMPUS PRINCIPAL | I43: 1
A44: CONSULTORIOS DE PSICOLOGÍA | B44: 1 | F44: CONSULTORIOS DE PSICOLOGÍA | G44: 1
A45: EMISORA CAMPUS PRINCIPAL | D45: 1 | F45: EMISORA CAMPUS PRINCIPAL | I45: 1
A46: AULA ARTES DE LA ESCENA BLOQUE K CAMPUS PRINCIPAL | D46: 1 | F46: AULA ARTES DE LA ESCENA BLOQUE K CAMPUS PRINCIPAL | I46: 1
A47: AULA CENTRO DE INVESTIGACIÓN BLOQUE B 1 CAMPUS PRINCIPAL | D47: 1 | F47: AULA CENTRO DE INVESTIGACIÓN BLOQUE B 1 CAMPUS PRINCIPAL | I47: 1
A48: AULA CENTRO DE INVESTIGACIÓN BLOQUE B 2 CAMPUS PRINCIPAL | D48: 1 | F48: AULA CENTRO DE INVESTIGACIÓN BLOQUE B 2 CAMPUS PRINCIPAL | I48: 1
A49: AULA CENTRO DE INVESTIGACIÓN BLOQUE H CAMPUS PRINCIPAL | D49: 1 | F49: AULA CENTRO DE INVESTIGACIÓN BLOQUE H CAMPUS PRINCIPAL | I49: 1
A50: AULA CENTRO DE INVESTIGACIÓN CITY CAMPUS | D50: 1 | F50: AULA CENTRO DE INVESTIGACIÓN CITY CAMPUS | I50: 1
A51: AUDITORIO BLOQUE K CAMPUS PRINCIPAL | D51: 1 | F51: AUDITORIO BLOQUE K CAMPUS PRINCIPAL | I51: 1
A52: CONCINA BLOQUE H | D52: 1 | F52: CONCINA BLOQUE H | I52: 1
A53: AUDITORIO JAIME MICHELSEN URIBE CAMPUS PRINCIPAL | D53: 1 | F53: AUDITORIO JAIME MICHELSEN URIBE CAMPUS PRINCIPAL | I53: 1

Sheet Gráfico 5
A1: Tabla NO | B1: 5
A2: Nombre | B2: Sitios de práctica
C4: Valor
B5: 2019-2 | C5: 158
B6: 2020-1 | C6: 210
B7: 2020-2 | C7: 221
B8: 2021-1 | C8: 226
B9: 2021-2 | C9: 252
B10: 2022-1 | C10: 195
B11: 2022-2 | C11: 320
B12: 2023-1 | C12: 306
B13: 2023-2 | C13: 474
B14: 2024-1 | C14: 642
B15: 2024-2 | C15: 1049 | D15: Escenarios en donde nuestros estudiantes han realizado sus prácticas (son vinculaciones individuales, no convenios interinstitucionales)
B16: 2025-1 | C16: 1031
B17: 2025-2 | C17: 1025
B18: 2026-1 | C18: 1105

Sheet Tabla 55
A1: Tabla NO | B1: 55
A2: Nombre | B2: Infraestructura física del Poli 2025 | G2: Infraestructura física del Poli 2026
A4: ESPACIO | B4: METROS CUADRADOS | G4: ESPACIO | H4: METROS CUADRADOS
B5: CAMPUS | C5: CITY CAMPUS | D5: CALLE 84 | E5: TOTALES | H5: CAMPUS | I5: CITY CAMPUS | J5: CALLE 84 | K5: TOTALES
A6: Aulas | B6: 2275 | C6: 3069 | D6: 0 | E6: 5344 | G6: Aulas
A7: Laboratorios | B7: 729 | C7: 0 | D7: 0 | E7: 729 | G7: Laboratorios
A8: Talleres | B8: 0 | C8: 0 | D8: 0 | E8: 0 | G8: Talleres
A9: Auditorios | B9: 566 | C9: 0 | D9: 0 | E9: 566 | G9: Auditorios
A10: Bibliotecas | B10: 714 | C10: 80 | D10: 0 | E10: 794 | G10: Bibliotecas
A11: Prácticas | B11: 0 | C11: 0 | D11: 243 | E11: 243 | G11: Prácticas
A12: Oficinas | B12: 1821 | C12: 1208 | D12: 593 | E12: 3622 | G12: Oficinas
A13: Deportivos | B13: 1447 | C13: 0 | D13: 0 | E13: 1447 | G13: Deportivos
A14: Cafeterías | B14: 939 | C14: 374 | D14: 120 | E14: 1433 | G14: Cafeterías
A15: Recreación | B15: 478 | C15: 739 | D15: 0 | E15: 1217 | G15: Recreación
A16: Sanitarios | B16: 356 | C16: 627 | D16: 65 | E16: 1048 | G16: Sanitarios
A17: Otros | B17: 5190 | C17: 6910 | D17: 720 | E17: 12820 | G17: Otros
A18: Total | B18: 14515 | C18: 13007 | D18: 1709 | E18: 29231 | G18: Total | H18: =SUM(H6:H17) -> 0 | I18: =SUM(I6:I17) -> 0 | J18: =SUM(J6:J17) -> 0 | K18: =SUM(K6:K17) -> 0

Sheet Tabla 57
A1: Tabla NO | B1: 57
A2: Nombre | B2: Infraestructura física 2019-2 a 2025-1
B4: 2019-2 | C4: 2020-1 | D4: 2020-2 | E4: 2021-1 | F4: 2021-2 | G4: 2022-1 | H4: 2022-2 | I4: 2023-1 | J4: 2023-2 | K4: 2024-1 | L4: 2024-2 | M4: 2025-1 | N4: 2025-2 | O4: 2026-1
A5: ÁREA ACTIVIDADES DEPORTIVAS (m²) | B5: 1901 | C5: 3348 | D5: 4795 | E5: 6242 | F5: 7689 | G5: 9136 | H5: 10583 | I5: 12030 | J5: 13477 | K5: 13477 | L5: 13477
A6: NÚMERO AULAS DE CLASE | B6: 90 | C6: 273 | D6: 273 | E6: 275 | F6: 270 | G6: 275 | H6: 270 | I6: 239 | J6: 211 | K6: 239 | L6: 208
A7: ÁREA AULAS (m²) | B7: 7160 | C7: 10358 | D7: 10358 | E7: 10358 | F7: 10208 | G7: 10358 | H7: 10208 | I7: 7791 | J7: 7791 | K7: 7791 | L7: 6918
A8: ÁREA UTIL (m²) | B8: 26529 | C8: 22446 | D8: 22446 | E8: 22446 | F8: 21346 | G8: 20841 | H8: 21346 | I8: 35548 | J8: 35548 | K8: 35548 | L8: 36310
A9: NÚMERO AULAS ESPECIALIZADAS | B9: 19 | C9: 5 | D9: 5 | E9: 5 | F9: 5 | G9: 5 | H9: 5 | I9: 10 | J9: 10 | K9: 10 | L9: 18
A10: NÚMERO AULAS DE CÓMPUTO | B10: 40 | C10: 55 | D10: 55 | E10: 55 | F10: 50 | G10: 55 | H10: 50 | I10: 39 | J10: 35 | K10: 39 | L10: 39
A11: NÚMERO BIBLIOTECAS | B11: 3 | C11: 2 | D11: 2 | E11: 2 | F11: 2 | G11: 2 | H11: 2 | I11: 2 | J11: 2 | K11: 2 | L11: 2
A12: NÚMERO AUDITORIOS | B12: 2 | C12: 2 | D12: 2 | E12: 2 | F12: 2 | G12: 2 | H12: 2 | I12: 2 | J12: 2 | K12: 2 | L12: 2
A13: NÚMERO LABORATORIOS Y TALLERES ESPECIALIZADOS | B13: 12 | C13: 22 | D13: 22 | E13: 22 | F13: 22 | G13: 22 | H13: 22 | I13: 27 | J13: 27 | K13: 27 | L13: 27
A14: NÚMERO ASIENTOS POR AULA | B14: 30 | C14: 25 | D14: 25 | E14: 30 | F14: 30 | G14: 30 | H14: 30 | I14: 30 | J14: 30 | K14: 30 | L14: 30
A15: ÁREA TOTAL CONSTRUIDA (m²) | B15: 27540 | C15: 39619 | D15: 39619 | E15: 39619 | F15: 38519 | G15: 39619 | H15: 38519 | I15: 35548 | J15: 37842 | K15: 35548 | L15: 34574
A16: ÁREA LABORATORIOS (m²) | B16: 1170 | C16: 414 | D16: 414 | E16: 414 | F16: 414 | G16: 414 | H16: 414 | I16: 646 | J16: 789 | K16: 646 | L16: 646

Sheet Tabla 58
A1: Tabla NO | B1: 58
A2: Nombre | B2: Infraestructura Tecnológica 2019-2 a 2025-1
B4: 2019-2 | C4: 2020-1 | D4: 2020-2 | E4: 2021-1 | F4: 2021-2 | G4: 2022-1 | H4: 2022-2 | I4: 2023-1 | J4: 2023-2 | K4: 2024-1 | L4: 2024-2 | M4: 2025-1 | N4: 2025-2 | O4: 2026-1
A5: Número PC´S Para Estudiantes | B5: 1104 | C5: 1268 | D5: 1268 | E5: - | F5: 1264 | G5: - | H5: - | I5: 5626 | J5: 5003 | K5: 4047 | L5: 4047 | M5: 4047 | N5: 3625 | O5: 3625
A6: Número PC´S Para Administrativos | B6: 1111 | C6: 1159 | D6: 1159 | E6: - | F6: 1207 | G6: - | H6: - | I6: 1350 | J6: 1317 | K6: 1167 | L6: 1197 | M6: 1197 | N6: 1027 | O6: 1027
A7: Número PC´S Para Profesores | B7: 256 | C7: 557 | D7: 858 | E7: 858 | F7: 1165 | G7: 1165 | H7: 1165 | I7: 1930 | J7: 2670 | K7: 655 | L7: 655 | M7: 655 | N7: 425 | O7: 425
A8: Correo Estudiantes (Gb) | B8: 1750 | C8: 1800 | D8: 1800 | E8: 1900 | F8: 1750 | G8: 1900 | H8: 1900 | I8: 1000 | J8: 750 | K8: ND | L8: ND | M8: ND | N8: ND | O8: 0.5
A9: % De Cubrimiento Del Campus Con Red Inalámbrica | B9: 98 | C9: 99 | D9: 99 | E9: 99 | F9: 99 | G9: 99 | H9: 99 | I9: 98 | J9: 99 | K9: 99 | L9: 99 | M9: 99 | N9: 99 | O9: 99
A10: Ancho De Banda Para Acceso A Internet (Mgbt) | B10: 1681 | C10: 1897 | D10: 1897 | E10: 1914 | F10: 1889 | G10: 2113 | H10: 2113 | I10: 1966 | J10: 3797 | K10: 3613 | L10: 3613 | M10: 3613 | N10: 3613 | O10: 3663
A11: Número Puntos De Red Funcionando Para Acceso A Internet | B11: 4038 | C11: 4365 | D11: 4365 | E11: 4370 | F11: 4357 | G11: 4370 | H11: 4370 | I11: 3823 | J11: 3757 | K11: 3181 | L11: 3181 | M11: 3181 | N11: 2582 | O11: 2582
A12: Equipos Robustos | B12: 12 | C12: 12 | D12: 12 | E12: - | F12: 12 | G12: - | H12: - | I12: 593 | J12: 580 | K12: 545 | L12: 545 | M12: 545 | N12: 326 | O12: 326
A13: Número PC´S Con Acceso A Intranet | B13: 2289 | C13: 2543 | D13: 2543 | E13: - | F13: 2577 | G13: - | H13: - | I13: 3885 | J13: 3792 | K13: 3181 | L13: 3181 | M13: 3181 | N13: 3625 | O13: 3625

Sheet Tabla 61
A1: Tabla NO | B1: 61
A2: Nombre | B2: Ingresos operacionales de la Institución
A4: * Cifras en millones de pesos | B4: 2019 | C4: 2020 | D4: 2021 | E4: 2022 | F4: 2023 | G4: 2024 | H4: 2025 | I4: 2026
A6: Ingreso matriculas | B6: 213983 | C6: 200660 | D6: 191618 | E6: 207590 | F6: 229365 | G6: 253336
A7: Ingreso de extensión | B7: 16734 | C7: 16124 | D7: 25009 | E7: 18493 | F7: 27348 | G7: 24053
A8: Total ingresos operacionales | B8: 230717 | C8: 216784 | D8: 216627 | E8: 226082 | F8: =+F6+F7 -> 256713 | G8: =+G6+G7 -> 277389

Sheet Tabla 62
A1: Tabla NO | B1: 62
A2: Nombre | B2: Fuentes de financiamiento internas y externas de la Institución
A4: Cifras en millones de pesos | B4: 2019 | C4: 2020 | D4: 2021 | E4: 2022 | F4: 2023 | G4: 2024 | H4: 2025 | I4: 2026
A5: Ingresos Operacionales | B5: 230717 | C5: 216784 | D5: 216627 | E5: 226082 | F5: 256713 | G5: 277389
A6: Ingresos no Operacionales | B6: 4828 | C6: 3965 | D6: 2029 | E6: 2216 | F6: 4407 | G6: 4510
A7: Ingresos totales | B7: 235546 | C7: 220749 | D7: 218656 | E7: 228298 | F7: 261121 | G7: 281900

Sheet Tabla 63
A1: Tabla NO | B1: 63
A2: Nombre | B2: Comportamiento de excedentes operacional y neto
A4: * Cifras en millones de pesos | B4: 2019 | C4: 2020 | D4: 2021 | E4: 2022 | F4: 2023 | G4: 2024 | H4: 2025 | I4: 2026
A5: Ingresos | B5: 230717 | C5: 216784 | D5: 216627 | E5: 226082 | F5: 256713 | G5: 277389
A6: Costos y gastos Oper. | B6: 228527 | C6: 209572 | D6: 211231 | E6: 216653 | F6: 243320 | G6: 262330
A7: Excedente operacional | B7: 2191 | C7: 7213 | D7: 5396 | E7: 9429 | F7: 13393 | G7: 15060
A8: Margen Operacional | B8: 0.01 | C8: 0.033 | D8: 0.025 | E8: 0.042 | F8: 0.052 | G8: 0.054
A9: Ingresos no Oper. | B9: 4828 | C9: 3965 | D9: 2029 | E9: 2216 | F9: 4407 | G9: 4510
A10: Gastos no Oper. | B10: 2019 | C10: 2470 | D10: 3688 | E10: 6490 | F10: 7396 | G10: 12467
A11: Excedente antes de Tx | B11: 5000 | C11: 8708 | D11: 3737 | E11: 5155 | F11: 10404 | G11: 7103
A12: Excedente Neto | B12: 4941 | C12: 3748 | D12: 954 | E12: 2437 | F12: 8166 | G12: 4788
A13: Margen neto | B13: 0.021 | C13: 0.017 | D13: 0.004 | E13: 0.011 | F13: 0.032 | G13: 0.017

Sheet Tabla 64
A1: Tabla NO | B1: 64
A2: Nombre | B2: Evolución y composición del patrimonio
A4: * Cifras en millones de pesos | B4: 2019 | C4: 2020 | D4: 2021 | E4: 2022 | F4: 2023 | G4: 2024 | H4: 2025 | I4: 2026
A5: Fondo Social | B5: 11 | C5: 11 | D5: 11 | E5: 11 | F5: 11 | G5: 11
A6: Adopción NIIF | B6: 210581 | C6: 210581 | D6: 210581 | E6: 210581 | F6: 126385 | G6: 126385
A7: Excedentes | B7: 42948 | C7: 46883 | D7: 47888 | E7: 50493 | F7: 59201 | G7: 64342
A8: Total Patrimonio | B8: =+B5+B6+B7 -> 253540 | C8: =+C5+C6+C7 -> 257475 | D8: =+D5+D6+D7 -> 258480 | E8: =+E5+E6+E7 -> 261085 | F8: =+F5+F6+F7 -> 185597 | G8: =+G5+G6+G7 -> 190738

Sheet Tabla 65
A1: Tabla NO | B1: 65
A2: Nombre | B2: Evolución y composición del activo
A4: * Cifras en millones de pesos | B4: 2019 | C4: 2020 | D4: 2021 | E4: 2022 | F4: 2023 | G4: 2024 | H4: 2025 | I4: 2026
A6: Caja | B6: 85458 | C6: 67889 | D6: 77380 | E6: 55487 | F6: 141017 | G6: 176963
A7: Cuentas por cobrar | B7: 9902 | C7: 20875 | D7: 41513 | E7: 85828 | F7: 13808 | G7: 26014
A8: PPE | B8: 324097 | C8: 323929 | D8: 322372 | E8: 311484 | F8: 218782 | G8: 221587
A9: Otros | B9: 2107 | C9: 14842 | D9: 20657 | E9: 25833 | F9: 108741 | G9: 129044
A10: Total Activo | B10: 421563 | C10: 427534 | D10: 461923 | E10: 478632 | F10: =+F6+F7+F8+F9 -> 482348 | G10: 553607

Sheet Tabla 66
A1: Tabla NO | B1: 66
A2: Nombre | B2: Evolución del estado de la situación financiera
A4: * Cifras en millones de pesos | B4: 2019 | C4: 2020 | D4: 2021 | E4: 2022 | F4: 2023 | G4: 2024 | H4: 2025 | I4: 2026
A5: Activos Corrientes | B5: 96106 | C5: 89510 | D5: 124322 | E5: 141872 | F5: 154825 | G5: 202976
A6: Activos no Corrientes | B6: 325457 | C6: 338024 | D6: 337600 | E6: 336760 | F6: 327523 | G6: 350630
A7: Total Activos | B7: 421563 | C7: 427534 | D7: 461923 | E7: 478632 | F7: =+F5+F6 -> 482348 | G7: =+G5+G6 -> 553606
A9: Pasivos Corrientes | B9: 76937 | C9: 59087 | D9: 96218 | E9: 85422 | F9: 96017 | G9: 120212
A10: Pasivos no Corrientes | B10: 91086 | C10: 110971 | D10: 107224 | E10: 132126 | F10: 200734 | G10: 242657
A11: Total Pasivos | B11: 168023 | C11: 170059 | D11: 203443 | E11: 217547 | F11: =+F9+F10 -> 296751 | G11: =+G9+G10 -> 362869
A13: Patrimonio | B13: 253540 | C13: 257475 | D13: 258480 | E13: 261085 | F13: 185597 | G13: 190738

Sheet Gráfico 6
A1: Tabla NO | B1: 6
A2: Nombre | B2: Liquidez y Capital de Trabajo
C4: Capital de trabajo | D4: Índice de liquidez
B5: 2019 | C5: 19169 | D5: 1.25
B6: 2020 | C6: 30423 | D6: 1.51
B7: 2021 | C7: 28104 | D7: 1.29
B8: 2022 | C8: 56450 | D8: 1.66
B9: 2023 | C9: 58808 | D9: 1.61
B10: 2024 | C10: 82764 | D10: 1.69
B11: 2025
B12: 2026

Sheet Tabla 67
A1: Tabla NO | B1: 67
A2: Nombre | B2: Inversiones realizadas en torno al plan de mejoramiento.
B4: 2019 | C4: 2020 | D4: 2021 | E4: 2022 | F4: 2023 | G4: 2024 | H4: 2025 | I4: 2026
A5: Infraestructura | B5: 35462 | C5: 13118 | D5: 545 | E5: 963 | F5: 1692 | G5: 1898
A6: Tecnología | B6: 8018 | C6: 5012 | D6: 3161 | E6: 1925 | F6: 2304 | G6: 3013
A7: Contenidos Virtuales | B7: 2300 | C7: 2295 | D7: 2456 | E7: 2477 | F7: 2451 | G7: 2741
A8: Biblioteca, CMA | B8: 588 | C8: 148 | D8: 6 | E8: 470 | F8: 239 | G8: 348
A9: Fortalecimiento Docencia | D9: 5485 | E9: 4965 | F9: 4612 | G9: 5944
A10: Otros | G10: =76+767 -> 843
A11: Planes de mejoramiento | B11: 46367 | C11: 20574 | D11: 11653 | E11: 10799 | F11: =+F5+F6+F7+F8+F9+F10 -> 11298 | G11: =+G5+G6+G7+G8+G9+G10 -> 14787
A12: Part% sobre Ingreso | B12: 0.2 | C12: 0.09 | D12: 0.05 | E12: 0.05 | F12: 0.04 | G12: =+G11/277389 -> 0.05330781

Sheet Tabla 68
A1: Tabla NO | B1: 68
A2: Nombre | B2: Inversiones misionales de la Institución
A4: Cifras en millones de pesos | B4: 2019 | C4: 2020 | D4: 2021 | E4: 2022 | F4: 2023 | G4: 2024 | H4: 2025 | I4: 2026
A6: Docencia | B6: 185574 | C6: 155058 | D6: 142723 | E6: 168641 | F6: 176277 | G6: 189120
A7: Investigación | B7: 5515 | C7: 5010 | D7: 5476 | E7: 6858 | F7: 8679 | G7: 9575
A8: Bienestar | B8: 14447 | C8: 14747 | D8: 41031 | E8: 20605 | F8: 28395 | G8: 41281
A9: Proyección Social | B9: 14744 | C9: 34052 | D9: 14971 | E9: 20545 | F9: 22200 | G9: 23820
A10: Internacionalización | B10: 1892 | C10: 1525 | D10: 2334 | E10: 2170 | F10: 2270 | G10: 2476
A11: Extensión | B11: 3604 | C11: 2644 | D11: 9139 | E11: 4826 | F11: 10726 | G11: 6330
A12: TOTAL | B12: =+SUM(B6:B11) -> 225776 | C12: =+SUM(C6:C11) -> 213036 | D12: =+SUM(D6:D11) -> 215674 | E12: =+SUM(E6:E11) -> 223645 | F12: =+SUM(F6:F11) -> 248547 | G12: =+SUM(G6:G11) -> 272602

Sheet Tabla 69
A1: Tabla NO | B1: 69
A2: Nombre | B2: Inversiones en bienestar
A4: Cifras en millones de pesos | B4: 2019 | C4: 2020 | D4: 2021 | E4: 2022 | F4: 2023 | G4: 2024 | H4: 2025 | I4: 2026
A5: Bienestar y regionalización | B5: 3154 | C5: 2345 | D5: 2056 | E5: 2343 | F5: 3066 | G5: 5088
A6: Servicio y permanencia | B6: 1829 | C6: 1092 | D6: 3066 | E6: 2040 | F6: 1967 | G6: 2749
A7: Subtotal Bienestar | B7: =+B5+B6 -> 4983 | C7: =+C5+C6 -> 3437 | D7: =+D5+D6 -> 5122 | E7: =+E5+E6 -> 4383 | F7: =+F5+F6 -> 5033 | G7: =+G5+G6 -> 7837
A8: %Part/Ingreso | B8: 0.02 | C8: 0.02 | D8: 0.02 | E8: 0.02 | F8: 0.02 | G8: 0.03
A9: Auxilios estudiantiles | B9: 9464 | C9: 11310 | D9: 13359 | E9: 16222 | F9: 23362 | G9: 33444
A10: Auxilios Pandemia | D10: 22550
A11: Total Bienestar | B11: 14447 | C11: 14747 | D11: 41031 | E11: 20605 | F11: 28395 | G11: 41281
A12: %Part/Ingreso | B12: 0.06 | C12: 0.07 | D12: 0.19 | E12: 0.09 | F12: 0.11 | G12: 0.15

Sheet Tabla 70
A1: Tabla NO | B1: 70
A2: Nombre | B2: Inversiones en proyección social
A4: Cifras en millones de pesos | B4: 2019 | C4: 2020 | D4: 2021 | E4: 2022 | F4: 2023 | G4: 2024 | H4: 2025 | I4: 2026
A5: Becas | B5: 13461 | C5: 14767 | D5: 13693 | E5: 19277 | F5: 19902 | G5: 21879
A6: Proyección social y graduados | B6: 782 | C6: 356 | D6: 539 | E6: 458 | F6: 1494 | G6: 950
A7: Práctica estudiantil y académica | B7: 500 | C7: 683 | D7: 739 | E7: 809 | F7: 804 | G7: 992
A8: Subtotal Proyección social | B8: 14744 | C8: 15806 | D8: 14971 | E8: 20545 | F8: =+F5+F6+F7 -> 22200 | G8: =+G5+G6+G7 -> 23821
A9: %Part/Ingreso | B9: 0.06 | C9: 0.07 | D9: 0.07 | E9: 0.09 | F9: 0.09 | G9: 0.09
A10: Becas Pandemia | C10: 18246
A11: Total Proyección Social | B11: 14744 | C11: 34052 | D11: 14971 | E11: 20545 | F11: 22200 | G11: =+G8 -> 23821
A12: %Part/Ingreso | B12: 0.06 | C12: 0.16 | D12: 0.07 | E12: 0.09 | F12: 0.09 | G12: 0.09

Sheet Tabla 71
A1: Tabla NO | B1: 71
A2: Nombre | B2: Inversión en investigación
A4: Cifras en millones de pesos | B4: 2019 | C4: 2020 | D4: 2021 | E4: 2022 | F4: 2023 | G4: 2024 | H4: 2025 | I4: 2026
A5: Fomento | B5: 952 | C5: 572 | D5: 742 | E5: 638 | F5: 711 | G5: 683
A6: Docencia | B6: 4205 | C6: 3447 | D6: 3735 | E6: 4994 | F6: 6471 | G6: 8280
A7: Otros | B7: 357 | C7: 991 | D7: 999 | E7: 1226 | F7: 1497 | G7: 612
A8: Total Investigación | B8: 5515 | C8: 5010 | D8: 5476 | E8: 6858 | F8: 8679 | G8: =+G5+G6+G7 -> 9575
A9: %Part/Ingreso | B9: 0.02 | C9: 0.02 | D9: 0.03 | E9: 0.03 | F9: 0.03 | G9: 0.03

Sheet Tabla 72
A1: Tabla NO | B1: 72
A2: Nombre | B2: Inversión en internacionalización
A4: Cifras en millones de pesos | B4: 2019 | C4: 2020 | D4: 2021 | E4: 2019 | F4: 2022 | G4: 2023 | H4: 2024 | I4: 2025 | J4: 2026
A5: Misiones Académicas | B5: 686 | C5: 36 | D5: 83 | E5: 686 | F5: 153 | G5: 164 | H5: 532
A6: Relaciones Internacionales | B6: 763 | C6: 450 | D6: 505 | E6: 763 | F6: 553 | G6: 793 | H6: 890
A7: Idiomas | B7: 444 | C7: 1039 | D7: 1746 | E7: 444 | F7: 1463 | G7: 1314 | H7: 1055
A8: Total Internacionalización | B8: 1892 | C8: 1525 | D8: 2334 | E8: 1892 | F8: 2170 | G8: 2270 | H8: 2476
A9: %Part/Ingreso | B9: 0.01 | C9: 0.01 | D9: 0.01 | E9: 0.01 | F9: 0.01 | G9: 0.01 | H9: 0.01

Sheet Tabla 73
A1: Tabla NO | B1: 73
A2: Nombre | B2: Inversión en Docencia
A4: Cifras en millones de pesos | B4: 2019 | C4: 2020 | D4: 2021 | E4: 2022 | F4: 2023 | G4: 2024 | H4: 2025 | I4: 2026
A5: Docencia | B5: 185574 | C5: 155058 | D5: 142723 | E5: 168641 | F5: 176277 | G5: 189120

Sheet Gráfico 8
A1: Tabla NO | B1: 8
A2: Nombre | B2: Ingresos Por extensión
B4: Año | C4: Ingresos | D4: Costos y gestión
B5: 2019 | C5: 16734 | D5: 3604
B6: 2020 | C6: 16124 | D6: 2644
B7: 2021 | C7: 25009 | D7: 9139
B8: 2022 | C8: 18493 | D8: 4826
B9: 2023 | C9: 27348 | D9: 10726
B10: 2024 | C10: 24053 | D10: 6330
B11: 2025
B12: 2026

Sheet Tabla 74
A1: Tabla NO | B1: 74
A2: Nombre | B2: Inversión en Infraestructura
A4: Cifras en millones de pesos | B4: 2019 | C4: 2020 | D4: 2021 | E4: 2022 | F4: 2023 | G4: 2024 | H4: 2025 | I4: 2026
A5: Operación | B5: 18953 | C5: 19773 | D5: 11186 | E5: 18047 | F5: 16177 | G5: 18457
A6: Inversión Capex | B6: 35460 | C6: 13118 | D6: 545 | E6: 963 | F6: 1692 | G6: 2665
A7: Infraestructura | B7: =+B5+B6 -> 54413 | C7: 32891 | D7: 11732 | E7: 19009 | F7: =+F5+F6 -> 17869 | G7: =+G5+G6 -> 21122

Sheet Tabla 75
A1: Tabla NO | B1: 75
A2: Nombre | B2: Inversión en Infraestructura tecnológica
A4: Cifras en millones de pesos | B4: 2019 | C4: 2020 | D4: 2021 | E4: 2022 | F4: 2023 | G4: 2024 | H4: 2025 | I4: 2026
A5: Operación | B5: 58517 | C5: 56054 | D5: 61735 | E5: 63634 | F5: 63073 | G5: 71793
A6: Inversión Capex | B6: 8019 | C6: 5012 | D6: 3161 | E6: 1925 | F6: 2304 | G6: 3013
A7: Tecnología | B7: =+B5+B6 -> 66536 | C7: =+C5+C6 -> 61066 | D7: =+D5+D6 -> 64896 | E7: =+E5+E6 -> 65559 | F7: =+F5+F6 -> 65377 | G7: =+G5+G6 -> 74806

Sheet Tabla 76
A1: Tabla NO | B1: 76
A2: Nombre | B2: Inversión en contenidos virtuales
A4: Cifras en millones de pesos | B4: 2019 | C4: 2020 | D4: 2021 | E4: 2022 | F4: 2023 | G4: 2024 | H4: 2025 | I4: 2026
A5: Operación | B5: 1062 | C5: 1489 | D5: 1855 | E5: 2879 | F5: 3345 | G5: 3359
A6: Inversión Capex | B6: 2300 | C6: 2295 | D6: 2456 | E6: 2477 | F6: 2451 | G6: 2741
A7: Contenidos Virtuales | B7: =+B5+B6 -> 3362 | C7: =+C5+C6 -> 3784 | D7: =+D5+D6 -> 4311 | E7: =+E5+E6 -> 5356 | F7: =+F5+F6 -> 5796 | G7: =+G5+G6 -> 6100

Sheet Tabla 77
A1: Tabla NO | B1: 77
A2: Nombre | B2: Inversión en Medios Audiovisuales y Biblioteca
A4: Cifras en millones de pesos | B4: 2019 | C4: 2020 | D4: 2021 | E4: 2022 | F4: 2023 | G4: 2024 | H4: 2025 | I4: 2026
A5: Operación | B5: 2751 | C5: 2023 | D5: 1958 | E5: 2119 | F5: 2776 | G5: 3542
A6: Inversión Capex | B6: 588 | C6: 148 | D6: 6 | E6: 470 | F6: 239 | G6: 348
A7: Biblioteca, CMA | B7: 3339 | C7: 2171 | D7: 1964 | E7: 2590 | F7: =+F5+F6 -> 3015 | G7: =+G5+G6 -> 3890

Sheet Tabla 82
A1: Tabla NO | B1: 82
A2: Nombre | B2: Proyectos finalizados
A4: LÍNEA ESTRATÉGICA | B4: PROYECTO | C4: OBJETIVO | D4: UNIDAD | E4: Fecha de finalización
A5: CALIDAD | B5: 1. Acreditación Institucional Sede Bogotá-Fase I | C5: Elaborar y radicar la solicitud de condiciones iniciales ante el CNA para optar por la acreditación institucional en alta calidad de la sede Bogotá | D5: Vicerrectoría Académica
B6: 2. Catálogo de recursos Virtuales | C6: Diseñar, estructurar y poner en funcionamiento, el catálogo online de recursos digitales de los materiales virtuales del Poli, que se encuentran asociados a los módulos, los e-books, los Mooc, las experiencias inmersivas y la producción audiovisual del estudio de grabación de la Gerencia de Educación Virtual. | D6: Vicerrectoría Académica
B7: 3. Innovación Curricular | C7: Desarrollar procesos de gestión y evaluación curricular que garanticen la calidad y excelencia académica y conduzcan a innovaciones curriculares en los niveles marco, meso y micro | D7: Vicerrectoría Académica
B8: 4. SER PRO | C8: Definir e implementar estrategias institucionales para mejorar el desempeño estudiantil en las Pruebas Saber, mediante el diseño de sistemas de monitoreo y medición del valor agregado, la formación docente, la articulación con equipos administrativos y la identificación de necesidades en la relación con el entorno externo | D8: Vicerrectoría Académica
B9: 5. Cultura de buena Docencia | C9: Consolidar la comunidad de profesores del POLI entorno a la cultura de la Buena Docencia, Centrada en el aprendizaje del estudiante, su experiencia en el aula de forma permanente y colaborativa | D9: Vicerrectoría Académica
B10: 6. Habilidades Poderosas | C10: Fortalecer la cultura organizacional del Politécnico Grancolombiano con enfoque en liderazgo transformacional, a partir de la apropiación de los valores Institucionales y el desarrollo de las habilidades poderosas en Directivos, Administrativos, Docente, Estudiantes, Graduados, CSU´s y demás grupos de interés durante tres fases. | D10: Vicerrectoría Académica
B11: 7. Acreditación Institucional Fase II | C11: Realizar el proceso de autoevaluación con fines de acreditación y elaborar y radicar el respectivo informe de autoevaluación con fines de acreditación en alta calidad de la sede Bogotá con sus respectivos anexos y cuadros maestros ante el Consejo Nacional de Acreditación (CNA). | D11: Vicerrectoría Académica
B12: 8. CREA Centro de Recursos y Experiencias para el aprendizaje – Fase de Adecuación | C12: Consolidar un espacio dinámico de servicios académicos y experiencias de aprendizaje, integrado en un ecosistema digital institucional, que promueva la producción e innovación de materiales educativos y desarrollos pedagógicos apoyados en tecnologías de la información y la comunicación. | D12: Vicerrectoría Académica
A13: TRANSFORMACIÓN ORGANIZACIONAL | B13: 9. Monarca – Ecosistema Banner | C13: Actualizar la versión de Banner a la última versión para garantizar una operación estable de la herramienta y permitir la aplicación de parches y actualizaciones que mejoren constantemente la funcionalidad de la línea base del producto en una infraestructura altamente escalable | D13: Vicerrectoría del Estudiante
B14: 10. Nuevo POLISIGS | C14: Diseñar e implementar el POLISIGS INSTITUCIONAL, mediante un modelo de gestión soportado en Políticas, procedimientos, indicadores y riesgos de toda la cadena de valor, el cual es el cual sea un apalancador de la planeación estratégica de la Institución | D14: Rectoría
B15: 11. PRIME | C15: Implementar un sistema integral de gestión académica basado en la plataforma Banner, que abarque todos los procesos clave (Graduación, Gestión Académica, Admisión, Gestión Estudiantes, Cuentas por Cobrar y Gestión Docente). El objetivo es garantizar la calidad y la experiencia del estudiante a lo largo de su ciclo académico, así como asegurar una operación académica y financiera estable para toda la comunidad educativa. | D15: Vicerrectoría del Estudiante
B16: 12. Plan Talento | C16: Implementar herramientas de evaluación para los colaboradores que permitan medir la gestión por competencias y desempeño con el objetivo de crear un plan reactivo de evaluación 360 | D16: Rectoría
B17: 13. Portal Web Universitario | C17: Diseñar, desarrollar, desplegar, implementar y dar soporte post-implementación del portal Web institucional, para mejorar la experiencia de las audiencias a las cuales atiende. Esto a través del uso de tecnologías de punta para el desarrollo de páginas web, basadas en experiencia de usuario | D17: Vicerrectoría del Estudiante
B18: 14. HUBSPOT CRM | C18: Migración del CRM actual, de dynamics 365 a Hubspot, incluye: Migración de los datos de 2023-1 a la fecha de salida en vivo Desarrollo de la integración con FDI y Banner Pruebas Integrales | D18: Vicerrectoría del Estudiante
B19: 15. Datalake | C19: Implementar el modelo Data Lake institucional para integrar y centralizar datos de múltiples fuentes (BANNER, CANVAS, CRM, SAP, FDI, entre otros), facilitando su disponibilidad y uso por los equipos, y habilitando análisis avanzados que generen valor agregado para la toma de decisiones. | D19: Vicerrectoría del Estudiante
A20: EXPANSIÓN | B20: 16. PRICING | C20: Definir una metodología de estrategia de precios, que permita conocer el precio y nivel de rentabilidad adecuado para cada programa, incluyendo la definición de descuentos y de estrategias para maximizar la rentabilidad y el número de estudiantes. | D20: Vicerrectoría de Crecimiento
B21: 17. Proyecto Silver | C21: Promover la incorporación del aprendizaje y la educación continua para personas mayores de 50 años, mediante la conceptualización de 4 espacios de conversación y la estructuración de una propuesta de línea de negocio para programas intergeneracionales enfocados en la nueva longevidad | D21: Vicerrectoría de Crecimiento
A22: EXPERIENCIA | B22: 18. Experiencia Institucional fase I | C22: Diseñar un modelo de experiencia Poli, de acuerdo con los principios, valores, cualidades, indicadores y variables institucionales que permitan crear una cultura de la experiencia y el servicio orientada a la excelencia, institucionalizándola como misión en todos los actores de la comunidad educativa | D22: Vicerrectoría del Estudiante
B23: 19. Experiencia Institucional Fase II | C23: Generar una estrategia de gestión de cambio para la apropiación y aplicación del modelo de experiencia Poli, que permita el fortalecimiento de la cultura basada en la experiencia y el servicio orientado a la excelencia | D23: Vicerrectoría del estudiante
B24: 20. Experiencia Institucional fase III - Hub de Experiencia y agilismo | C24: Implementar el Hub de Experiencia en sus 4 líneas de trabajo: Formación, Aseguramiento de procesos, innovación digital y HUB de saberes y estándares de medición internos y externos | D24: Vicerrectoría del estudiante
B25: 21. Centro Gastronómico | C25: Crear el Centro Gastronómico POLI como espacio práctico para fortalecer la formación de estudiantes del programa AHG, apoyar su inserción laboral, promover el sello institucional y aportar a la renovación del Registro Calificado y la acreditación en alta calidad | D25: Vicerrectoría Académica
A26: SOSTENIBILIDAD | B26: 22. Certificación Sistema de Gestión Ambiental (SGA) sede los Colores | C26: Ampliar el alcance de la certificación del Sistema de Gestión Ambiental ISO 14001:2015 en la sede Los Colores Medellín | D26: Rectoría
B27: 23. Equidad de Género | C27: Diseñar e implementar una estrategia institucional de equidad de género que promueva entornos inclusivos, participación equitativa y prácticas respetuosas de la diversidad | D27: Vicerrectoría del estudiante

Sheet Tabla 83
A1: Tabla NO | B1: 83
A2: Nombre | B2: Proyectos en ejecución
A4: LÍNEA ESTRATÉGICA | B4: PROYECTO | C4: OBJETIVO | D4: UNIDAD
A5: CALIDAD | B5: 1. Acreditación Institucional Fase III | C5: Preparar y llevar a cabo la etapa de evaluación externa o evaluación por pares académicos en el marco del proceso de acreditación institucional en alta calidad de la sede Bogotá. | D5: Vicerrectoría Académica
B6: 3. Fortalecimiento de la investigación, la innovación y la creación | C6: Mejorar la investigación, la innovación y la creación institucional mediante el fortalecimiento de habilidades investigativas, la consolidación de semilleros de investigación y la implementación de estrategias para motivar la participación estudiantil. También se enfoca en aumentar la productividad de nuevo conocimiento, propiciar aliados para proyectos con impacto en el sector externo, fomentar la cultura de innovación y ampliar la divulgación de resultados de investigación.​ | D6: Vicerrectoría Académica
B7: 4. Fortalecimiento de planta docente | C7: Diseñar e implementar el modelo de fortalecimiento de la planta docente, que permita identificar la relación óptima Docente - Estudiante de acuerdo con las políticas y lineamientos institucionales, para las diferentes modalidades y niveles, garantizando la calidad y la sostenibilidad financiera de la institución. | D7: Vicerrectoría Académica
B8: 5. Plataforma de gestión de información curricular Fase 1 | C8: Desarrollo, integración y soporte de una plataforma de gestión curricular para la sistematización y digitalización de la información curricular de cada programa académico del Poli, que comprende: perfiles profesional y ocupacional, competencias de egreso, resultados de aprendizaje, plan de estudios, indicadores de logro de las asignaturas o módulos de dicho plan, syllabus y proyectos educativos de programa. | D8: Vicerrectoría Académica
A9: TRANSFORMACIÓN ORGANIZACIONAL | B9: 6. Reingenieria de aplicaciones | C9: Definir y establecer un marco de arquitectura robusto y escalable, basado en la evaluación del road map de aplicaciones, que sirva como guía para la creación de un proyecto semilla. Este proyecto semilla será fundamental para la construcción de diversas aplicaciones y servicios necesarios para la Institución, culminando con la puesta en marcha de un piloto exitoso. | D9: Vicerrectoría del estudiante
B10: 7. SOPHIA Sistema de Optimización y Programación Horaria Institucional Académica I Fase | C10: Diseñar, desarrollar e implementar un software intuitivo y eficiente que permita a la institución realizar la planificación académica y la programación de grupos de pregrado y posgrado presencial en BOG y MDE; así como la programación de encuentros sincrónicos en Pregrado y Posgrado Virtual; garantizado el uso optimo de la planta física, docente y la proyección de demanda estudiantil. | D10: Vicerrectoría del estudiante
B11: 8. Gobierno de datos | C11: Diseñar e implementar un Modelo de Gobierno de Datos Institucional que garantice la disponibilidad, confiabilidad y oportunidad de la información, facilitando su uso eficiente en la toma de decisiones estratégicas de la Institución. | D11: Vicerrectoría del estudiante
B12: 9. Self Service S&P | C12: Mejorar la eficiencia operativa, aumentando la experiencia y satisfacción del estudiante (NPS) reduciendo costos y los tiempos de maduración para acelerar el paso del funnel. . El proyecto busca crear una experiencia web y de canales escritos que apoye la conversión sin intervención de agentes con capacidades de e-commerce de manera autónoma en toda la cadena. | D12: Vicerrectoría del estudiante
B13: 10. ADN POLI | C13: Diseñar e implementar un modelo de experiencia positiva para todos los colaboradores del Politécnico Grancolombiano, que fortalezca el sentido de pertenencia, fomente la satisfacción laboral y promueva el desarrollo personal y profesional, garantizando que vivan y reflejen los valores institucionales en su día a día y contribuyan al impacto positivo en la comunidad educativa. | D13: Rectoría
B14: 11. Actualización de TRD y creación del Plan de Gestión documental | C14: Actualización de los Instrumentos Archivísticos, que incluye la actualización de las Tablas de Retención Documental (TRD), actualización de los Cuadros de Clasificación Documental (CCD), y elaboración del Programa de Gestión Documental (PGD), de conformidad con la normatividad archivística vigente nacional | D14: Rectoría
B15: 12. Herramientas de Gestión para el mejoramiento continuo | C15: Fortalecer el mejoramiento continuo institucional mediante el rediseño del modelo, la definición de herramientas y la implementación de mecanismos de seguimiento que apoyen a los líderes de proceso en la solución de problemas. | D15: Rectoría
A16: EXPERIENCIA | B16: 13. Migración modelo de transporte rotativo | C16: Optimizar el funcionamiento de la flota de transporte rotativo para estudiantes, profesores, administrativos, externos y la comunidad del barrio El Castillo. Mediante la renovación de los vehículos actuales para cumplir con las medidas reglamentarias en temas ambientales y técnicos | D16: Vicerrectoría Financiera
B17: 14. Permanencia institucional | C17: Fortalecer el proceso de acompañamiento institucional dirigido a los estudiantes con el objetivo de favorecer la permanencia instutucional, a través de estrtaegias de orientación académica y administrativa, mitigando los factores de riesgo de deserción | D17: Vicerrectoría del estudiante
A18: SOSTENIBILIDAD | B18: 15. Ecosistema E3 | C18: Brindar herramientas a la comunidad POLI para fomentar la empleabilidad, el emprendimiento y la innovación, mediante la articulación de unidades internas y alianzas externas que fortalezcan la oferta de servicios, el posicionamiento institucional y el vínculo con graduados. | D18: Vicerrectoría Académica
B19: 16. Modelo de seguimiento al graduado | C19: Fortalecer el modelo de seguimiento y relacionamiento con graduados mediante la recolección de datos representativos, la sistematización de procesos, el desarrollo de herramientas tecnológicas y el análisis estadístico por programa, integrando los resultados en los planes de mejora institucionales. | D19: Vicerrectoría Académica
A20: EDUCACION PARA TODA LA VIDA | B20: 17. Colegio Virtual – Cafam | C20: El objetivo del Proyecto en fase I es ejecutar los procesos legales para conformar la alianza CAFAM – Poli con el objetivo de incursionar en la educación media a través de la modalidad semipresencial y virtual. | D20: Rectoría
B21: 18. Institución de educación para el trabajo y desarrollo humano IETDH – Cafam | C21: El objetivo principal del Proyecto en fase 1 es llevar a cabo los procesos legales, logísticos, financieros y académicos necesarios para conformar la alianza con CET CAFAM (Centro de Educación para el Trabajo CAFAM). Para el inicio de la en operación de los programas del IETDH (Institución de Educación para el Trabajo y el Desarrollo Humano) | D21: Rectoría
B22: 19. Centro de Idiomas Poli | C22: Diseñar y poner en marcha la primera fase del Centro de Idiomas del Poli desde la sensibilización de la comunidad académica frente a sus funciones, así como radicar un programa de formación ante la SED para oferta externa | D22: Vicerrectoría Académica

Sheet Tabla 85
A1: Tabla NO | B1: 85
A2: Nombre | B2: Procesos formación permanente desarrollados desde el SIAC
A4: Año | B4: Evento | C4: Población objetivo | D4: No. Participantes
A5: 2020 | B5: Socialización de resultados del acompañamiento para el Fortalecimiento de los Sistemas Internos de Aseguramiento de la Calidad en 2020 | C5: Directivos | D5: 50
A6: 2021 | B6: Socialización de resultados del acompañamiento para el Fortalecimiento de los Sistemas Internos de Aseguramiento de la Calidad en 2021 | C6: Directivos | D6: 31
A7: 2021 | B7: Sistema de Aseguramiento de la Calidad de la Educación Superior, con la participación de Carmen Amalia Camacho | C7: Profesores y Directivos | D7: 134
A8: 2022 | B8: Seminario: Elaboración de Documentos para el Aseguramiento de la Calidad de la Educación Superior | C8: Profesores y Directivos | D8: 30
A9: 2022 | B9: Conoce nuestro Sistema Interno de Aseguramiento de la Calidad | C9: Colaboradores | D9: 120
A10: 2023 | B10: Seminario: Fundamentos para el Aseguramiento de la Calidad de los Programas Académicos | C10: Profesores y Directivos | D10: 36
A11: 2023 | B11: Conferencia: Explorando los beneficios de la acreditación de Programas en Diseño | C11: Red Académica de Diseño (RAD) | D11: 50
A12: 2023 | B12: Nuestro SIAC y las perspectivas institucionales para el logro de la alta calidad académica | C12: Colaboradores | D12: 150
A13: 2024 | B13: Charla “En camino a nuestra acreditación” | C13: Colaboradores | D13: 200
A14: 2025 | B14: Seminario: Sistema de Información en la Educación Superior (SNIES, SPADIES Y OLE) | C14: Profesores y Directivos | D14: 44
A15: 2025 | B15: Capacitación Anexo Técnicos Programas de Salud | C15: Profesores y Directivos | D15: 23
A16: 2025 | B16: Nuevo Modelo de Acreditación de Programas (Acuerdo 01 de 2025) | C16: Profesores y Directivos | D16: 28
A17: 2026 | B17: Se ejecutan en el 2026-2 | C17: NA | D17: NA

Sheet Gráfico 9
A1: Tabla NO | B1: 9
A2: Nombre | B2: Resultados de la evaluación de profesores
B4: Cátedra | C4: Planta
A5: 2019-2 | B5: 4.3 | C5: 4.4
A6: 2020-1 | B6: 4.4 | C6: 4.4
A7: 2020-2 | B7: 4.7 | C7: 4.7
A8: 2021-1 | B8: 4.7 | C8: 4.5
A9: 2021-2 | B9: 4.5 | C9: 4.6
A10: 2022-1 | B10: 4.4 | C10: 4.6
A11: 2022-2 | B11: 4.4 | C11: 4.4
A12: 2023-1 | B12: 4.4 | C12: 4.7
A13: 2023-2 | B13: 4.4 | C13: 4.7
A14: 2024-1 | B14: 4.5 | C14: 4.7
A15: 2024-2 | B15: 4.6 | C15: 4.7
A16: 2025-1 | B16: 4.5 | C16: 4.7
... A18: 2026-1 | B18: 4.49 | C18: 4.77

Sheet Tabla 87
A1: Tabla NO | B1: 87
A2: Nombre | B2: Resultados de la evaluación de administrativos
B4: Evaluación 360° | C4: Resultado 2022 | D4: Resultado 2023 | E4: Resultado 2024 | F4: Resultado 2025 | G4: Resultado 2026
B5: Resultado global administrativos | C5: 0.86 | D5: 0.884 | E5: 0.8884 | F5: 0.901

Sheet Tabla 98
A1: Tabla NO | B1: 98
A2: Nombre | B2: Formación a equipos curriculares encargados de la declaración y formulación de resultados de aprendizaje
A4: Área formadora | B4: Tipo de formación | C4: Logros
A5: Dirección de Currículo | B5: Articulación y declaración de resultados de aprendizaje con perfiles y competencias profesionales de programa | C5: Año 2021:
C6: · Revisión de las brechas y las cualificaciones declaradas en el Marco Nacional de Cualificaciones para la reforma curricular y la declaración de resultados de aprendizaje e indicadores de logro
C7: · Reflexión curricular en torno a la formulación de los resultados de aprendizaje y posibilidad de medición y verificación en el proceso formativo
C8: Año 2022:
C9: · Articulación de los mapeos curriculares con la estrategia de declaración de los resultados de aprendizaje
C10: · Caracterización de las labores académicas, formativas, científicas, profesores y de extensión y proyección social en los procesos de gestión curricular de los programas académicos en relación con los resultados de aprendizaje declarados por estos
C11: Año 2023:
C12: · 88 sesiones de trabajo en las que participaron 44 programas, con 3 Decanos,12 Directores de Escuela y 12 profesores de planta, integrantes de los comités curriculares de Escuela
C13: Año 2024-I:
C14: · 20 sesiones de trabajo en las que participaron 10 programas, con 6 Directores y 6 profesores de planta, integrantes de los comités curriculares de Escuela
C15: Año 2024-II:
C16: · 52 sesiones de trabajo en las que participaron 27 programas, con 24 personas (entre profesores y delegados).
C17: Año 2025-I:
C18: · 3 sesiones de trabajo en para 2 programas, con 2 personas (profesores y director de Escuela). · 3 sesiones de trabajo para 3 profesores que se integran a la Dirección de Currículo, para acompañar el proceso con los programas y las Escuelas.
A19: Impacto | B19: · Actualización de las taxonomías a las necesidades disciplinares o de los campos profesionales.
B20: · Ejercicio permanente de reflexión en torno a los aspectos meso curriculares de los programas académicos y su gestión en el mediano plazo.
B21: · Compromiso de la comunidad académica con los resultados de aprendizaje, que llevó al ajuste de la totalidad de programas activos entre 2023 y 2024-I.
B22: · Compromiso de la comunidad académica con los resultados de aprendizaje, que llevó al ajuste de 15 propramas en el 2024-II.

Sheet Tabla 99
A1: Tabla NO | B1: 99
A2: Nombre | B2: Formación para declarar indicadores de logro
A4: Área formadora | B4: Tipo de formación | C4: Logros
A5: Dirección de Currículo | B5: · Formulación de Indicadores de Logro asignatura o módulo · Actualización de Syllabus por asignatura o módulo | C5: Año 2021:
C6: · Articulación de los resultados de aprendizaje con los indicadores de logro como producto de las discusiones de los comités curriculares y el cuerpo profesoral que apoya a los programas
C7: Año 2022:
C8: · Revisión cíclica para garantizar la articulación entre contenidos conceptuales, procedimentales y actitudinales, con los indicadores de logro y las actividades evaluativas
C9: · Toma de decisiones informadas a partir de las reflexiones curriculares del cuerpo profesoral que acompaña y apoya los procesos formativos de los programas
C10: Año 2023:
C11: · 37 sesiones de trabajo para la identificación de necesidades, y la caracterización de fortalezas y aspectos de mejora de 37 programas
C12: · 12 sesiones de trabajo para la elaboración de mapeos curriculares de 37 programas
C13: · 36 sesiones de trabajo para la estructuración de los planes de estudio de 37 programas
C14: · 74 sesiones de trabajo para la declaración de perfiles y competencias de 37 programas
C15: · 111 sesiones de trabajo para la declaración de resultados de aprendizaje de 37 programas
C16: · 111 sesiones de trabajo con 37 programas para la declaración de estrategias extracurriculares asociadas a las labores académicas, formativas, culturales, científicas y de extensión y proyección social.
C17: · 111 sesiones de trabajo para la declaración de indicadores de logro, el establecimiento de créditos, actividades de aprendizaje y de evaluación de las asignaturas o módulos que conformarían los planes de estudio de 37 programas
... C40: · 12 sesiones de trabajo para la declaración de indicadores de logro, el establecimiento de créditos, actividades de aprendizaje y de evaluación de las asignaturas o módulos que conformarían los planes de estudio de 4 programas
A41: Impacto | B41: · Transformación de las prácticas curriculares a través de las mesas de trabajo colectivas
B42: · Transformación de las prácticas didácticas con la definición de estrategias y actividades orientadas a favorecer el aprendizaje de acuerdo con los indicadores de logro en el marco de las metodologías activas.
B43: · Incorporación de las estrategias de declaración de resultados de aprendizaje en los procesos de creación, renovación y modificación de registro calificado y de acreditación de programas.
B44: · Ejercicio permanente de reflexión en torno a los aspectos micro curriculares de los programas académicos y su gestión a corto plazo.
B45: · Compromiso de la comunidad académica con los resultados de aprendizaje, que ha promovido el ajuste de 27 programas activos entre 2023 y 2024-I.
B46: · Compromiso de la comunidad académica con los resultados de aprendizaje, que ha promovido el ajuste de 30 programas activos entre 2024-II y 2025-I.
B47: · Cualificación del cuerpo profesoral en declaración de resultados de aprendizaje.

Sheet Tabla 100
A1: Tabla NO | B1: 100
A2: Nombre | B2: Participación de profesores formación del Modelo Institucional de Resultados de Aprendizaje
A4: Facultad | B4: 2021 | C4: 2022 | D4: 2023 | E4: 2024-1 | F4: 2024-2 | G4: 2025-1 | H4: 2025-2 | I4: 2026-1 | J4: Total
A5: Ingeniería, Diseño e Innovación | B5: 70 | C5: 4 | D5: 10 | E5: 1 | F5: 9 | G5: 1 | J5: =+SUM(B5:I5) -> 95
A6: Negocios, Gestión y Sostenible | B6: 66 | C6: 5 | D6: 5 | F6: 13 | G6: 1 | J6: =+SUM(B6:I6) -> 90
A7: Sociedad, Cultura y Creatividad | B7: 94 | C7: 16 | D7: 34 | F7: 10 | G7: 3 | J7: =+SUM(B7:I7) -> 157
A8: Total | B8: 230 | C8: 25 | D8: 50 | E8: 1 | F8: =SUM(F5:F7) -> 32 | G8: =SUM(G5:G7) -> 5 | J8: =+SUM(B8:I8) -> 343

Sheet Tabla 199
A1: Tabla NO | B1: 199
A2: Nombre | B2: Profesores T.C en estrategias Resultados de Aprendizaje 2021 a 2025-1
A5: FACULTAD | B5: 2021-1 | C5: 2021-2 | D5: 2022-1 | E5: 2023-1 | F5: 2023-2 | G5: 2024-1 | H5: 2024-2 | I5: 2025-1 | J5: 2025-2 | K5: 2026-1 | L5: Total
A6: FACULTAD DE INGENIERÍA, DISEÑO E INNOVACIÓN | B6: 61 | C6: 10 | D6: 6 | E6: 4 | G6: 4 | H6: 5 | I6: 3 | L6: =SUM(B6:K6) -> 93
A7: FACULTAD DE NEGOCIOS, GESTIÓN Y SOSTENIBILIDAD | B7: 64 | C7: 4 | D7: 5 | E7: 6 | G7: 6 | H7: 3 | I7: 1 | L7: =SUM(B7:K7) -> 89
A8: FACULTAD DE SOCIEDAD, CULTURA Y CREATIVIDAD | B8: 90 | C8: 21 | D8: 18 | E8: 16 | G8: 8 | H8: 4 | I8: 3 | L8: =SUM(B8:K8) -> 160
A9: Total | B9: 215 | C9: 35 | D9: 29 | E9: 26 | G9: =SUM(G6:G8) -> 18 | H9: =SUM(H6:H8) -> 12 | I9: =SUM(I6:I8) -> 7 | L9: =SUM(B9:K9) -> 342

Sheet Tabla 101
A1: Tabla NO | B1: 101
A2: Nombre | B2: Participación de profesores en el plan de cualificación institucional
A4: Formación | B4: 2019-2 | C4: 2020-1 | D4: 2020-2 | E4: 2021-1 | F4: 2021-2 | G4: 2022-1 | H4: 2022-2 | I4: 2023-1 | J4: 2023-2 | K4: 2024-1 | L4: 2024-2 | M4: 2025-1 | N4: 2025-2 | O4: 2026-1
A5: Pedagógica | B5: 220 | C5: 436 | D5: 119 | E5: 335 | F5: 72 | G5: 85 | H5: 128 | I5: 85 | J5: 62 | K5: 321 | L5: 478 | M5: 946
A6: Investigación, Innovación, Internacionalización | B6: 156 | C6: 293 | D6: 47 | E6: 133 | F6: 25 | G6: 51 | H6: 28 | I6: 18 | J6: 6 | K6: 282 | L6: 229 | M6: 640
A7: Digital | B7: 174 | C7: 444 | D7: 86 | E7: 298 | F7: 69 | G7: 79 | H7: 145 | I7: 65 | J7: 24 | K7: 129 | L7: 107 | M7: 97
A8: Complementaria | B8: 118 | C8: 303 | D8: 78 | E8: 138 | F8: 44 | G8: 102 | H8: 120 | I8: 35 | J8: 24 | K8: 6 | L8: 238 | M8: 13

Sheet Tabla 105
A1: Tabla NO | B1: 105
A2: Nombre | B2: Evolución de la nueva oferta 2019-2026
A4: Nivel de formación | B4: No. Programas creados | J4: Total general
B5: 2019 | C5: 2020 | D5: 2021 | E5: 2022 | F5: 2023 | G5: 2024 | H5: 2025 | I5: 2026 -1
A6: Tecnológico | B6: 1 | C6: 0 | D6: 1 | E6: 0 | F6: 0 | G6: 0 | H6: 0 | I6: 0 | J6: =SUM(B6:H6) -> 2
A7: Universitario | B7: 1 | C7: 2 | D7: 5 | E7: 4 | F7: 0 | G7: 2 | H7: 2 | I7: 4 | J7: =SUM(B7:H7) -> 16
A8: Especialización | B8: 0 | C8: 1 | D8: 2 | E8: 0 | F8: 0 | G8: 0 | H8: 1 | I8: 4 | J8: =SUM(B8:H8) -> 4
A9: Maestría | B9: 2 | C9: 0 | D9: 3 | E9: 1 | F9: 1 | G9: 3 | H9: 5 | I9: 2 | J9: =SUM(B9:H9) -> 15
A10: Total general | B10: 4 | C10: 3 | D10: 11 | E10: 5 | F10: 1 | G10: 5 | H10: =SUM(H6:H9) -> 8 | I10: =SUM(I6:I9) -> 10 | J10: =SUM(J6:J9) -> 37

Sheet Tabla 108
A1: Tabla NO | B1: 108
A2: Nombre | B2: Estudiantes en actividades de investigación 2019 a 2026-1
A4: Estrategias de Iniciación Científica | B4: 2019 | C4: 2020 | D4: 2021 | E4: 2022 | F4: 2023 | G4: 2024 | H4: 2025 | I4: 2026-1
A5: Aulas Abiertas de Investigación (AAI) | E5: 631 | F5: 1961 | G5: 2283 | H5: 657 | I5: 1045
A6: Trabajo de Grado Investigación (TGI) | B6: 679 | C6: 1380 | D6: 612 | E6: 900 | F6: 622 | G6: 485 | H6: 517 | I6: 497
A7: MOOC de Investigación | F7: 1690 | G7: 690 | H7: 773 | I7: 537
A8: Semilleristas | B8: 737 | C8: 1006 | D8: 899 | E8: 792 | F8: 681 | G8: 1013 | H8: 866 | I8: 923
A9: Asistentes de Investigación | B9: 17 | C9: 7 | D9: 17 | E9: 18 | F9: 6 | G9: 18 | H9: 13 | I9: 1
A10: Jóvenes Investigadores | B10: 5 | D10: 23 | E10: 5 | F10: 8 | G10: 20 | H10: 20 | I10: 12
A11: Programa Delfín | C11: 3 | D11: 12 | E11: 8 | F11: 9 | G11: 9 | H11: 14 | I11: 20
A12: Hablemos de Investigación En Región | G12: 675 | H12: 431 | I12: 83
A13: Jueves de Investigación (Actividades Escuelas) | H13: 434 | I13: 63
A14: Actividades de investigación desarrolladas por escuelas | H14: 2023 | I14: 1568
A15: Estrategia de Horas Beca en Investigación | I15: 265
A16: Total de estudiantes en las actividades | B16: 1438 | C16: 2396 | D16: 1563 | E16: 2354 | F16: 4977 | G16: =SUM(G5:G12) -> 5193 | H16: =SUM(H5:H14) -> 5748 | I16: =SUM(I5:I15) -> 5014
A17: Cantidad de semilleros de investigación activos | B17: 106 | C17: 127 | D17: 133 | E17: 124 | F17: 133 | G17: 124 | H17: 115 | I17: 122

Sheet Tabla 110
A1: Tabla NO | B1: 110
A2: Nombre | B2: Resultado de los grupos institucionales en la Convocatoria de Medición de Grupos e Investigadores 957
G3: Convocatoria 957
A4: Grupo | B4: Facultad | C4: 2018 | D4: 2022 | E4: 2023 | F4: 2024 | G4: 2025-1 | H4: 2026
A5: Psicología Educación y Cultura – PEC | B5: FSCC | C5: C | D5: B | E5: B | F5: B | G5: A1 | H5: A1
A6: Comunicación Estratégica y Creativa – CEC | B6: FSCC | C6: C | D6: B | E6: B | F6: B | G6: C | H6: C
A7: MERCADEO I+2 - MI2 | B7: FSCC | C7: A | D7: B | E7: B | F7: B | G7: A | H7: A
A8: Economía, Negocios y Desarrollo Internacional – ENDI | B8: FNGS | C8: C | D8: B | E8: B | F8: B | G8: A | H8: A
A9: CITIC | B9: FIDI | C9: B | D9: A | E9: A | F9: A | G9: A | H9: A
A10: Derecho, Sociedad y Empresa – DSE | B10: FSCC | C10: C | D10: B | E10: B | F10: B | G10: A | H10: A
A11: Equipo de Investigación en Contabilidad, Organizaciones y Sociedad – EICOS | B11: FNGS | C11: - | D11: C | E11: C | F11: C | G11: B | H11: B
A12: Narrativas, Creación y Estéticas – NCE | B12: FSCC | C12: - | D12: C | E12: C | F12: C | G12: C | H12: C
A13: Administración, Competitividad y Sostenibilidad – GACS | B13: FNGS | C13: - | D13: C | E13: C | F13: C | G13: B | H13: B
A14: Diseño, Artefacto y Sociedad – DAS | B14: FIDI | C14: - | D14: C | E14: C | F14: C | G14: C | H14: C
A15: Educación, Innovación y Sociedad – EIS | B15: FSCC | C15: - | D15: C | E15: C | F15: C | G15: B | H15: B
A16: Optimización, Infraestructura y Automatización – OPINA | B16: FIDI | C16: - | D16: REC | E16: REC | F16: REC | G16: B | H16: B
... A18: Grupo de Investigación en Gestión de las Organizaciones Laborales y Seguridad Laboral | B18: FSCC | C18: - | D18: - | E18: - | F18: - | G18: C | H18: C
A19: Comunicación, Interacción y Branding (CIB) | B19: FSCC | G19: C | H19: C
A20: GIAP | B20: FNGS | C20: - | D20: - | E20: - | F20: - | G20: B | H20: B
A21: E-TIC | B21: FIDI | C21: - | D21: - | E21: - | F21: - | G21: REC | H21: REC
A23: Branding

Sheet Tabla 111
A1: Tabla NO | B1: 111
A2: Nombre | B2: Investigadores categorizados por área en la Convocatoria de Medición de Grupos e Investigadores 957
A4: Unidad Académica | B4: Cantidad
A5: Dirección de Currículo, Presencial y Virtual | B5: 0
A6: Junior | B6: 0
A7: Secretaría Académica y de Extensión | B7: 2
A8: Junior | B8: 2
A9: Dirección Investigación, Innovación y Creación | B9: 2
A10: Junior | B10: 2
A11: Facultad Ingeniería Diseño e Innovación | B11: 27
A12: Asociado | B12: 6
A13: Junior | B13: 20
A14: Sénior | B14: 1
A15: Facultad Negocios, Gestión y Sostenibilidad | B15: 30
A16: Asociado | B16: 11
... A23: Total | B23: 122
A24: Resultados concocatoria 957 Minciencas

Sheet Tabla 112
A1: Tabla NO | B1: 112
A2: Nombre | B2: Profesores en capacitaciones de investigación durante el quinquenio
A4: Año | B4: Profesores capacitados
A5: 2019 | B5: 69
A6: 2020 | B6: 251
A7: 2021 | B7: 200
A8: 2022 | B8: 190
A9: 2023 | B9: 204
A10: 2024 | B10: 73
A11: 2025 | B11: 90
A12: 2026-1

Sheet Tabla 113
A1: Tabla NO | B1: 113
A2: Nombre | B2: Estímulos por productividad de alto impacto entregados a profesores
A4: Año | B4: Número de profesores beneficiados
A5: 2019 | B5: 10
A6: 2020 | B6: 13
A7: 2021 | B7: 14
A8: 2022 | B8: 13
A9: 2023 | B9: 23
A10: 2024 | B10: 17
A11: 2025 | B11: 39
A12: 2026 | B12: 29
A13: Total | B13: =SUM(B5:B10) -> 90

Sheet Tabla 114
A1: Tabla NO | B1: 114
A2: Nombre | B2: Número de Proyectos de investigación 2019-2026-1
B4: Año
A5: Grupo | B5: 2019 | C5: 2020 | D5: 2021 | E5: 2022 | F5: 2023 | G5: 2024 - CIERRE | H5: 2025-1 | I5: 2025 -CIERRE | J5: 2026-1
A6: CEC | B6: 12 | C6: 18 | D6: 14 | E6: 7 | F6: 3 | G6: 7 | H6: 11 | I6: 12 | J6: 13
A7: CIADE | D7: 2 | E7: 1 | F7: 1 | G7: 2 | H7: 4 | I7: 3 | J7: 3
A8: CIB | D8: 1 | E8: 2 | F8: 3 | G8: 1 | H8: 1 | I8: 2 | J8: 3
A9: CITIC | B9: 17 | C9: 36 | D9: 47 | E9: 37 | F9: 40 | G9: 21 | H9: 15 | I9: 12 | J9: 30
A10: CVSSL | D10: 3 | E10: 2 | F10: 2 | G10: 6 | H10: 6 | I10: 7 | J10: 8
A11: DAS | C11: 6 | D11: 10 | E11: 11 | F11: 7 | G11: 4 | H11: 2 | I11: 9 | J11: 10
A12: DSE | B12: 6 | C12: 10 | D12: 15 | E12: 10 | F12: 11 | G12: 15 | H12: 20 | I12: 18 | J12: 22
A13: EEAPS | C13: 4 | D13: 2
A14: EICOS | C14: 8 | D14: 10 | E14: 6 | F14: 6 | G14: 8 | H14: 7 | I14: 13 | J14: 9
A15: EIS | C15: 6 | D15: 14 | E15: 16 | F15: 14 | G15: 11 | H15: 10 | I15: 9 | J15: 14
A16: ENDI | B16: 19 | C16: 25 | D16: 21 | E16: 16 | F16: 12 | G16: 15 | H16: 15 | I16: 19 | J16: 28
A17: GACS | C17: 13 | D17: 20 | E17: 21 | F17: 17 | G17: 18 | H17: 14 | I17: 21 | J17: 15
A18: GIAP | D18: 1 | E18: 4 | F18: 3 | G18: 5 | H18: 3 | I18: 8 | J18: 12
A19: MI+2 | B19: 8 | C19: 17 | D19: 22 | E19: 13 | F19: 13 | G19: 15 | H19: 22 | I19: 16 | J19: 18
A20: NCE | C20: 4 | D20: 2 | E20: 5 | F20: 5 | G20: 4 | H20: 4 | I20: 5 | J20: 3
A21: OPINA | B21: 1 | C21: 20 | D21: 15 | E21: 7 | F21: 6 | G21: 14 | H21: 14 | I21: 22 | J21: 20
A22: PEC | B22: 9 | C22: 38 | D22: 24 | E22: 16 | F22: 28 | G22: 14 | H22: 9 | I22: 6 | J22: 7
A23: E-TIC | G23: 1 | H23: 2 | I23: 9
A24: FNGS | J24: 5
A25: TOTAL | B25: 72 | C25: 205 | D25: 223 | E25: 174 | F25: 171 | G25: =SUM(G6:G23) -> 161 | H25: =SUM(H6:H23) -> 159 | I25: =SUM(I6:I24) -> 191 | J25: =SUM(J6:J24) -> 220

Sheet Tabla 115
A1: Tabla NO | B1: 115
A2: Nombre | B2: Número de Proyectos con obtención de recursos externos
A4: Año | B4: Número de proyectos
A5: 2019 | B5: 3
A6: 2020 | B6: 0
A7: 2021 | B7: 1
A8: 2022 | B8: 6
A9: 2023 | B9: 2
A10: 2024 | B10: 4
A11: 2025 | B11: 4
A12: 2026-1
A13: Total | B13: =SUM(B5:B12) -> 20

Sheet Tabla 116
A1: Tabla NO | B1: 116
A2: Nombre | B2: Productividad académica por tipología entre 2019-2026-1
A4: Tipología | B4: 2019 | C4: 2020 | D4: 2021 | E4: 2022 | F4: 2023 | G4: 2024 | H4: 2025 | I4: 2026-1 | J4: Total
A5: Artículo en revista especializada impresa y electrónica | B5: 56 | C5: 75 | D5: 77 | E5: 63 | F5: 30 | G5: 15 | H5: 15 | J5: =+SUM(B5:F5,G5:G5) -> 316
A6: Libro resultado de investigación | B6: 42 | C6: 97 | D6: 65 | E6: 27 | F6: 16 | G6: 4 | H6: 0 | J6: =+SUM(B6:F6,G6:G6) -> 251
A7: Capítulo en libro resultado de investigación | B7: 41 | C7: 151 | D7: 88 | E7: 72 | F7: 20 | G7: 19 | H7: 9 | J7: =+SUM(B7:F7,G7:G7) -> 391
A8: Regulaciones y normas | B8: 31 | C8: 1 | D8: 8 | E8: 0 | F8: 0 | G8: 1 | H8: 0 | J8: =+SUM(B8:F8,G8:G8) -> 41
A9: Semilleros | B9: 106 | C9: 127 | D9: 133 | E9: 124 | F9: 133 | G9: 132 | H9: 115 | J9: =+SUM(B9:F9,G9:G9) -> 755
A10: Generación de contenido virtual y multimedia | B10: 76 | C10: 82 | D10: 24 | E10: 19 | F10: 37 | G10: 186 | H10: 10 | J10: =+SUM(B10:F10,G10:G10) -> 424
A11: Participación en evento científico | B11: 158 | C11: 222 | D11: 225 | E11: 248 | F11: 172 | G11: 274 | H11: 25 | J11: =+SUM(B11:F11,G11:G11) -> 1299
A12: Edición científica | B12: 12 | C12: 23 | D12: 48 | E12: 30 | F12: 4 | G12: 3 | H12: 0 | J12: =+SUM(B12:F12,G12:G12) -> 120
A13: Asesoría tesis de doctorado | D13: 2 | E13: 3 | F13: 0 | G13: 0 | H13: 0 | J13: =+SUM(B13:F13,G13:G13) -> 5
A14: Asesoría tesis de maestría | B14: 59 | C14: 35 | D14: 16 | E14: 4 | F14: 16 | G14: 113 | H14: 14 | J14: =+SUM(B14:F14,G14:G14) -> 243
A15: Asesoría tesis de pregrado | B15: 210 | C15: 357 | D15: 169 | E15: 160 | F15: 109 | G15: 84 | H15: 3 | J15: =+SUM(B15:F15,G15:G15) -> 1089
A16: Creación de programas (Maestría) | B16: 2 | C16: 1 | D16: 0 | E16: 3 | F16: 0 | G16: 1 | H16: 0 | J16: =+SUM(B16:F16,G16:G16) -> 7
A17: Creación de programas (Doctorado) | B17: 1 | C17: 0 | D17: 0 | E17: 1 | G17: 0 | H17: 0 | J17: =+SUM(B17:F17,G17:G17) -> 2
A18: Creación de cursos Maestría | C18: 2 | D18: 0 | E18: 0 | F18: 4 | G18: 0 | H18: 0 | J18: =+SUM(B18:F18,G18:G18) -> 6
A19: Creación de cursos Doctorado | B19: 1 | C19: 0 | D19: 1 | E19: 0 | F19: 0 | G19: 0 | H19: 0 | J19: =+SUM(B19:F19,G19:G19) -> 2
A20: Proyecto de investigación y desarrollo | B20: 72 | C20: 205 | D20: 223 | E20: 174 | F20: 171 | G20: 112 | H20: 159 | J20: =+SUM(B20:F20,G20:G20) -> 957
A21: TOTAL | B21: 878 | C21: 1402 | D21: 1079 | E21: 928 | F21: 712 | G21: =SUM(G5:G20) -> 944 | H21: =SUM(H5:H20) -> 350 | J21: =+SUM(B21:F21,G21) -> 5943
A23: Nota: Dato anual 2024 se actulizó

Sheet Tabla 137
A1: Tabla NO | B1: 137
A2: Nombre | B2: Actividad y población impactada entre 2020-2025-1
A4: Año | B4: Actividad | C4: Población impactada | D4: Lugar
A5: 2020 | B5: Elaboración Retazo | C5: 120 estudiantes | D5: Poli
A6: 2021 | B6: Lanzamiento Poliretazo | C6: 300 personas | D6: Poli
D7: Casa de la paz
A8: 2022 | B8: Arropamiento 9 de abril | C8: 1000 personas | D8: Casa de la Comisión de la verdad
A9: 2023 | B9: Evento Víctimas | C9: 100 personas | D9: CMPR Bogotá
A10: 2024 | B10: 72 horas tejiendo por la memoria | C10: 100 personas | D10: Casa de la paz
A11: 2024 | B11: Semana por la paz | C11: 100 personas | D11: Licenciatura en Ciencias Sociales Politécnico Grancolombiano
A12: 2024 | B12: Jornadas de arropamiento Red de pro-tejedores de memoria | C12: 1000 personas | D12: Palacio de Justicia, Palacio Liévano, Plaza de Bolívar
A13: 2025 | B13: 72 horas tejiendo por la memoria | C13: 100 personas | D13: Casa de la paz
A14: 2026 | B14: 72 horas tejiendo por la memoria y la verdad | C14: 50 personas | D14: Espacio ODEON

Sheet Tabla 121
A1: Tabla NO | B1: 121
A2: Nombre | B2: Histórico de producción del Laboratorio de Experiencias de Aprendizaje Inmersivo (LEAI y MI-Book) 2019-2026-1
A4: Producción | B4: 2019 | C4: 2020 | D4: 2021 | E4: 2022 | F4: 2023 | G4: 2024 | H4: 2025 | I4: 2026-1
A5: Ambientes inmersivos | B5: 4 | C5: 8 | D5: 10 | E5: 8 | F5: 1 | G5: 2 | H5: 5 | I5: 8
A6: Mi-Book | B6: 37 | C6: 20 | D6: 14 | E6: 15 | F6: 17 | G6: 16 | H6: 16 | I6: 8

Sheet Tabla 122
A1: Tabla NO | B1: 122
A2: Nombre | B2: Histórico de uso de los ambientes inmersivos por parte de los estudiantes 2019-2025-1
A4: Uso por los estudiantes | B4: 2019 | C4: 2020 | D4: 2021 | E4: 2022 | F4: 2023 | G4: 2024 | H4: 2025 | I4: 2026-1
A5: Ambientes inmersivos | B5: 1119 | C5: 8970 | D5: 23269 | E5: 28783 | F5: 28639 | G5: 29431 | H5: 27001 | I5: 12952
A6: Recorridos 360° | H6: 11598 | I6: 15531
A7: Mi-Book | E7: 177000 | F7: 343331 | G7: 13000 | H7: 24936 | I7: 28503
A8: Visualizaciones | B8: 2019 | C8: 2020 | D8: 2021 | E8: 2022 | F8: 2023 | G8: 2024 | H8: 2025 | I8: 2026-1
A9: Recorridos 360° | G9: 302849 | H9: 46999 | I9: 75658
A10: Mi-Book | E10: 328516 | F10: 520331 | G10: 541141 | H10: 783820 | I10: 529889

Sheet Tabla 123
A1: Tabla NO | B1: 123
A2: Nombre | B2: Proyectos con aliados regionales
A4: Año | B4: Región | C4: Proyecto | D4: Investigador principal
A5: 2019 | B5: CALDAS | C5: Minorías étnico-raciales en Colombia: análisis de los outcomes laborales en contextos de discriminación y segmentación ocupacional. | D5: José Wilmar Quintero Peña
A6: 2019 | B6: CUNDINAMARCA | C6: Investigar en la Escuela: Paz, territorio y memoria. | D6: Doris Lised García Ortíz
A7: 2019 | B7: CUNDINAMARCA | C7: ANÁLISIS DE LAS NARRATIVAS PERIODÍSTICAS EN LOS MAGAZINES DE EMISORAS COMUNITARIAS EN COLOMBIA EN CLAVE DEL PROCESO DE PAZ | D7: Mireya Barón Pulido
A8: 2019 | B8: CUNDINAMARCA | C8: REPRESENTACIONES DEL RECLUTAMIENTO FORZADO DE MENORES DE EDAD POR GRUPOS ARMADOS ILEGALES EN LA PRENSA COLOMBIANA | D8: Juliana Castellanos Diaz
A9: 2019 | B9: COLOMBIA | C9: EDUCAÇÃO EM DIREITOS HUMANOS DAS MULHERES, GESTÃO E SUSTENTABILIDADE (IV EDIÇÃO) - EDUCACIÓN EN DERECHOS HUMANOS DE LAS MUJERES, GESTIÓN Y SOSTENIBILIDAD (IV EDICIÓN) | D9: Martha Inés Moreno Medel
A10: 2020 | B10: BOLÍVAR | C10: Participación y educación ciudadana: una apuesta para la consolidación de comunidades de práctica en los Montes de María. | D10: Haidy Rodríguez Sánchez
A11: 2020 | B11: COLOMBIA | C11: COLOMBIA UN CASO: POS ACUERDO Y NARRATIVAS FOTOGRÁFICAS EN PERIODISMO DIGITAL DE COLOMBIA Y ESPAÑA (1-2018) | D11: Mireya Barón Pulido
A12: 2020 | B12: COLOMBIA | C12: PRÁCTICAS DE COMUNICACIÓN PÚBLICA Y CIUDADANÍA. ANÁLISIS DE LOS CANALES DIGITALES DE SEIS GOBERNACIONES DE COLOMBIA Y SU INCIDENCIA EN LA CONSOLIDACIÓN DE UNA CULTURA PARTICIPATIVA. | D12: Marcela Fernanda Tellez Pedraza
A13: 2020 | B13: COLOMBIA | C13: POLI-RETAZO PARA LOS TEJEDORES DE MEMORIA, POR UNA APUESTA A LA RECONCILIACIÓN EN COLOMBIA | D13: Mireya Barón Pulido
A14: 2020 | B14: BOGOTÁ D.C. | C14: MODELADO PARA LA EVALUACIÓN DE ALTERNATIVAS DE POLÍTICAS PÚBLICAS EN LA GESTIÓN DEL AGUA EN LA REGIÓN HÍDRICA BOGOTÁ – CUNDINAMARCA | D14: ANDRES CHAVARRO VELANDIA
A15: 2020 | B15: MEDELLÍN, ANTIOQUIA | C15: ESTUDIO DE CARACTERIZACIÓN Y MEDICIÓN DE IMPACTO SOCIOECONOMICO DE LOS SOCIOS DE LOS CÍRCULOS SOLIDARIOS DE LA CORPORACIÓN FOMENTAMOS DE MEDELLÍN | D15: JAIRO TAMAYO BUSTAMANTE
A16: 2020 | B16: MARÍA LA BAJA, BOLIVAR | C16: PARTICIPACIÓN Y EDUCACIÓN CIUDADANA: UNA APUESTA PARA LA CONSOLIDACIÓN DE COMUNIDADES DE PRÁCTICA EN LOS MONTES DE MARÍA” | D16: Haidy Johanna Rodriguez Sanchez
... A69: 2025 | B69: GUASCA, CUNDINAMARCA, COLOMBIA (Principal)_x000D_, GUASCA, CUNDINAMARCA, COLOMBIA (100%)_x000D_ | C69: INNOVACIÓN SOCIAL PARA COMUNIDADES VIVAS | D69: WILINTON JAVIER ORTIZ AMADOR
A70: 2026

Sheet Tabla 126
A1: Tabla NO | B1: 126
A2: Nombre | B2: Capacitación y actualización profesional entre 2019-2 a 2025-1
B4: 2019-2 | C4: 2020-1 | D4: 2020-2 | E4: 2021-1 | F4: 2021-2 | G4: 2022-1 | H4: 2022-2 | I4: 2023-1 | J4: 2023-2 | K4: 2024-1 | L4: 2024-2 | M4: 2025-1 | N4: 2025-2 | O4: 2026-1
A5: Diplomados | B5: 15 | C5: 3 | D5: 5 | E5: 10 | F5: 15 | G5: 5 | H5: 8 | I5: 5 | J5: 7 | K5: 2 | L5: 4 | M5: 4
A6: Cursos y talleres | B6: 12 | C6: 8 | D6: 10 | E6: 6 | F6: 10 | G6: 10 | H6: 16 | I6: 9 | J6: 10 | K6: 25 | L6: 26 | M6: 36
A7: Asesorías y consultorías | B7: 6 | C7: 5 | D7: 4 | E7: 5 | F7: 3 | G7: 5 | H7: 4 | I7: 2 | J7: 10 | K7: 4 | L7: 4 | M7: 8
A8: Recursos educativos digitales | B8: 2 | C8: 0 | D8: 8 | E8: 3 | F8: 5 | G8: 0 | H8: 3 | I8: 0 | J8: 0 | K8: 0 | L8: 0 | M8: 0

Sheet Tabla 127
A1: Tabla NO | B1: 130
A2: Nombre | B2: Estudiantes que realizan práctica profesional de acuerdo con los tipos de vinculación 2019-2 a 2026-1
A4: Tipos de vinculación | B4: Modalidad | C4: 2019-2 | D4: 2020-1 | E4: 2020-2 | F4: 2021-1 | G4: 2021-2 | H4: 2022-1 | I4: 2022-2 | J4: 2023-1 | K4: 2023-2 | L4: 2024-1 | M4: 2024-2 | N4: 2025-1 | O4: 2025-2 | P4: 2026-1 | Q4: Total
A5: Vinculación Laboral | B5: PRESENCIAL | C5: 10 | D5: 13 | E5: 16 | F5: 13 | G5: 27 | H5: 24 | I5: 34 | J5: 32 | K5: 33 | L5: 43 | M5: 19 | N5: 15 | O5: 40 | P5: 25 | Q5: =SUM(C5:P5) -> 344
B6: VIRTUAL | C6: 188 | D6: 262 | E6: 275 | F6: 301 | G6: 325 | H6: 273 | I6: 428 | J6: 471 | K6: 788 | L6: 784 | M6: 945 | N6: 904 | O6: 974 | P6: 970 | Q6: =SUM(C6:P6) -> 7888
B7: Total | C7: =SUM(C5:C6) -> 198 | D7: =SUM(D5:D6) -> 275 | E7: =SUM(E5:E6) -> 291 | F7: =SUM(F5:F6) -> 314 | G7: =SUM(G5:G6) -> 352 | H7: =SUM(H5:H6) -> 297 | I7: =SUM(I5:I6) -> 462 | J7: =SUM(J5:J6) -> 503 | ... P7: =SUM(P5:P6) -> 995 | Q7: =SUM(C7:P7) -> 8232
A8: Contrato De Aprendizaje – Vinculación Formativa | B8: PRESENCIAL | C8: 378 | D8: 309 | E8: 277 | F8: 352 | G8: 388 | H8: 344 | I8: 332 | J8: 262 | K8: 280 | L8: 202 | M8: 285 | N8: 234 | O8: 406 | P8: 381 | Q8: =SUM(C8:P8) -> 4430
B9: VIRTUAL | C9: 124 | D9: 158 | E9: 192 | F9: 231 | G9: 225 | H9: 297 | I9: 362 | J9: 405 | K9: 579 | L9: 676 | M9: 764 | N9: 797 | O9: 784 | P9: 967 | Q9: =SUM(C9:P9) -> 6561
B10: Total | C10: =SUM(C8:C9) -> 502 | D10: =SUM(D8:D9) -> 467 | E10: =SUM(E8:E9) -> 469 | F10: =SUM(F8:F9) -> 583 | G10: =SUM(G8:G9) -> 613 | H10: =SUM(H8:H9) -> 641 | I10: =SUM(I8:I9) -> 694 | J10: =SUM(J8:J9) -> 667 | ... P10: =SUM(P8:P9) -> 1348 | Q10: =SUM(C10:P10) -> 10991

Sheet Gráfico 13
A1: Tabla NO | B1: 13
A2: Nombre | B2: Estudiantes modalidad virtual que han realizado practicas pedagógicas entre 2019-2026-1
B4: 2019 | C4: 2020 | D4: 2021 | E4: 2022 | F4: 2023 | G4: 2024 | H4: 2025-1 | I4: 2025-2 | J4: 2026-1
A5: Vinculación Laboral | B5: 35 | C5: 99 | D5: 112 | E5: 323 | F5: 898 | G5: 1361 | H5: 709 | I5: 766 | J5: 725
A6: Contrato De Aprendizaje - Vinculación Formativa | B6: 17 | C6: 12 | D6: 16 | E6: 166 | F6: 649 | G6: 1218 | H6: 642 | I6: 593 | J6: 684
A8: Nota: aquí solo se registran estudiantes de prácticas de licenciaturas

Sheet Tabla 131
A1: Tabla NO | B1: 131
A2: Nombre | B2: Estudiantes modalidad presencial y virtual que han realizado prácticas educativas del programa de Psicología entre 2019-2026-1
A4: Tipos de vinculación | B4: 2019 | C4: 2020 | D4: 2021 | E4: 2022 | F4: 2023 | G4: 2024-1 | H4: 2024-2 | I4: 2025-1 | J4: 2025-2 | K4: 2026-1 | L4: Total
A5: Contrato De Aprendizaje – Vinculación Formativa | B5: N/A | C5: 50 | D5: 78 | E5: 76 | F5: 31 | G5: 7 | H5: 21 | I5: 33 | J5: 38 | K5: 49 | L5: =SUM(C5:K5) -> 383

Sheet Tabla 132
A1: Tabla NO | B1: 132
A2: Nombre | B2: Estudiantes modalidad presencial y virtual que han realizado prácticas en el consultorio tributario y empresarial entre 2019-2025-1
A4: Tipos de vinculación | B4: 2019-2 | C4: 2020 | D4: 2021 | E4: 2022 | F4: 2023 | G4: 2024-1 | H4: 2024-2 | I4: 2025-1 | J4: 2025-2 | K4: 2026-1 | L4: Total
A5: Contrato De Aprendizaje – Vinculación Formativa | B5: 18 | C5: 10 | D5: 11 | E5: 11 | F5: 8 | G5: 10 | H5: 10 | I5: 17 | L5: =SUM(B5:K5) -> 95

Sheet Tabla 133
A1: Tabla NO | B1: 133
A2: Nombre | B2: Estudiantes en modalidad presencial que han realizado prácticas entre 2019-2025-1
A4: Tipos de vinculación | B4: Modalidad | C4: 2019-2 | D4: 2020 | E4: 2021 | F4: 2022 | G4: 2023 | H4: 2024-1 | I4: 2024-2 | J4: 2025-1 | K4: 2025-2 | L4: 2026-1 | M4: Total
A5: Contrato De Aprendizaje – Vinculación Formativa | B5: Presencial | C5: 8 | D5: 15 | E5: 15 | F5: 14 | G5: 9 | H5: 4 | I5: 285 | J5: 234 | K5: 446 | L5: 406 | M5: =SUM(C5:L5) -> 1436
C6: 378 | D6: 586 | E6: 740 | F6: 676 | G6: 542 | H6: 202 | I6: 285 | J6: 234 | K6: 446 | L6: 406 | M6: =SUM(C6:L6) -> 4495

Sheet Tabla 134
A1: Tabla NO | B1: 134
A2: Nombre | B2: Estudiantes de modalidad presencial que han realizado prácticas en la Agencia Trompo entre 2019-2025-1
A4: Tipos de vinculación | B4: 2019-2 | C4: 2020 | D4: 2021 | E4: 2022 | F4: 2023 | G4: 2024-1 | H4: 2024-2 | I4: 2025-1 | J4: 2025-2 | K4: 2026-1 | L4: Total
A5: Contrato De Aprendizaje – Vinculación Formativa | B5: 5 | C5: 6 | D5: 6 | E5: 5 | F5: 7 | G5: 4 | H5: 7 | I5: 2 | J5: 5 | K5: 5 | L5: =SUM(B5:K5) -> 52

Sheet Tabla 135
A1: Tabla NO | B1: 135
A2: Nombre | B2: Histórico de Becas otorgadas por el Poli entre 2019-2 y 2025-1
A4: BECAS OTORGADAS HG | B4: 2019-02 | C4: 2020-01 | D4: 2020-02 | E4: 2021-01 | F4: 2021-02 | G4: 2022-01 | H4: 2022-02 | I4: 2023-01 | J4: 2023-02 | K4: 2024-01 | L4: 2024-2 | M4: 2025-1 | N4: 2025-2 | O4: 2026-1 | P4: Total general
A5: BOGOTA | B5: 797 | C5: 670 | D5: 608 | E5: 553 | F5: 586 | G5: 620 | H5: 550 | I5: 546 | J5: 359 | K5: 337 | L5: 325 | M5: =+SUM(M6:M13) -> 351 | N5: 303 | O5: 326 | P5: =+SUM(B5:O5) -> 6931
A6: COLABORADORES | B6: 35 | C6: 36 | D6: 27 | E6: 24 | F6: 21 | G6: 15 | H6: 16 | I6: 7 | J6: 13 | K6: 12 | L6: 16 | M6: 15 | N6: 7 | O6: 7 | P6: =+SUM(B6:O6) -> 251
A7: ESPECIAL | B7: 378 | C7: 329 | D7: 322 | E7: 311 | F7: 318 | G7: 258 | H7: 238 | I7: 203 | J7: 167 | K7: 188 | L7: 167 | M7: 173 | N7: 202 | O7: 180 | P7: =+SUM(B7:O7) -> 3434
A8: EXCELENCIA ACADEMICA | B8: 15 | C8: 13 | D8: 20 | E8: 17 | F8: 22 | G8: 26 | H8: 21 | I8: 17 | J8: 23 | K8: 13 | L8: 20 | M8: 22 | N8: 13 | O8: 18 | P8: =+SUM(B8:O8) -> 260
A9: FAMILIARES DE COLABORADORES | B9: 48 | C9: 44 | D9: 41 | E9: 31 | F9: 22 | G9: 17 | H9: 12 | I9: 12 | J9: 8 | K9: 16 | L9: 12 | M9: 21 | N9: 20 | O9: 22 | P9: =+SUM(B9:O9) -> 326
A10: HUELLA GRANCOLOMBIANA | B10: 216 | C10: 171 | D10: 127 | E10: 104 | F10: 139 | G10: 242 | H10: 200 | I10: 236 | J10: 93 | K10: 30 | L10: 27 | M10: 26 | N10: 26 | O10: 31 | P10: =+SUM(B10:O10) -> 1668
A11: LOGROS Y REPRESENTANTES | B11: 7 | C11: 5 | D11: 5 | E11: 3 | F11: 2 | G11: 9 | H11: 6 | I11: 21 | J11: 3 | K11: 13 | L11: 9 | M11: 11 | N11: 23 | O11: 52 | P11: =+SUM(B11:O11) -> 169
A12: MINORIAS | B12: 26 | C12: 27 | D12: 24 | E12: 22 | F12: 18 | G12: 13 | H12: 11 | I12: 9 | J12: 9 | K12: 10 | L12: 8 | M12: 17 | N12: 12 | O12: 16 | P12: =+SUM(B12:O12) -> 222
A13: MONITORIAS | B13: 72 | C13: 45 | D13: 42 | E13: 41 | F13: 44 | G13: 40 | H13: 46 | I13: 41 | J13: 43 | K13: 55 | L13: 66 | M13: 66 | N13: 0 | P13: =+SUM(B13:O13) -> 601
A14: VIRTUAL | B14: 575 | C14: 529 | D14: 644 | E14: 703 | F14: 603 | G14: 968 | H14: 1018 | I14: 1121 | J14: 977 | K14: 705 | L14: 681 | M14: =+SUM(M15:M24) -> 632 | N14: 705 | O14: 792 | P14: =+SUM(B14:O14) -> 10653
A15: AVANZA | B15: 0 | C15: 0 | D15: 0 | E15: 0 | F15: 0 | G15: 0 | H15: 0 | I15: 0 | J15: 0 | K15: 2 | L15: 6 | M15: 16 | N15: 16 | O15: 21 | P15: =+SUM(B15:O15) -> 61
A16: COLABORADORES | B16: 73 | C16: 56 | D16: 39 | E16: 48 | F16: 45 | G16: 42 | H16: 54 | I16: 62 | J16: 42 | K16: 46 | L16: 49 | M16: 43 | N16: 39 | O16: 48 | P16: =+SUM(B16:O16) -> 686
A17: ESPECIAL | B17: 237 | C17: 215 | D17: 360 | E17: 413 | F17: 250 | G17: 340 | H17: 465 | I17: 492 | J17: 625 | K17: 417 | L17: 346 | M17: 289 | N17: 322 | O17: 314 | P17: =+SUM(B17:O17) -> 5085
A18: EXCELENCIA ACADEMICA | B18: 27 | C18: 34 | D18: 33 | E18: 31 | F18: 32 | G18: 40 | H18: 36 | I18: 35 | J18: 37 | K18: 29 | L18: 33 | M18: 34 | N18: 41 | O18: 52 | P18: =+SUM(B18:O18) -> 494
A19: FAMILIARES DE COLABORADORES | B19: 21 | C19: 23 | D19: 20 | E19: 24 | F19: 23 | G19: 21 | H19: 21 | I19: 18 | J19: 17 | K19: 15 | L19: 12 | M19: 17 | N19: 20 | O19: 22 | P19: =+SUM(B19:O19) -> 274
A20: HUELLA GRANCOLOMBIANA | B20: 184 | C20: 157 | D20: 139 | E20: 134 | F20: 218 | G20: 479 | H20: 377 | I20: 426 | J20: 177 | K20: 86 | L20: 128 | M20: 123 | N20: 131 | O20: 162 | P20: =+SUM(B20:O20) -> 2921
A21: LOGROS Y REPRESENTANTES | B21: 4 | C21: 0 | D21: 2 | E21: 5 | F21: 1 | G21: 3 | H21: 3 | I21: 9 | J21: 5 | K21: 10 | L21: 8 | M21: 85 | N21: 11 | O21: 27 | P21: =+SUM(B21:O21) -> 173
A22: MINORIAS | B22: 29 | C22: 44 | D22: 51 | E22: 47 | F22: 33 | G22: 41 | H22: 57 | I22: 75 | J22: 72 | K22: 97 | L22: 87 | M22: 10 | N22: 110 | O22: 132 | P22: =+SUM(B22:O22) -> 885
A23: MONITORIAS | B23: 0 | C23: 0 | D23: 0 | E23: 1 | F23: 1 | G23: 2 | H23: 5 | I23: 4 | J23: 2 | K23: 2 | L23: 4 | M23: 4 | N23: 0 | O23: 0 | P23: =+SUM(B23:O23) -> 25
A24: PODIUM | B24: 0 | C24: 0 | D24: 0 | E24: 0 | F24: 0 | G24: 0 | H24: 0 | I24: 0 | J24: 0 | K24: 1 | L24: 8 | M24: 11 | N24: 15 | O24: 14 | P24: =+SUM(B24:O24) -> 49
A25: TOTAL | B25: 1372 | C25: 1199 | D25: 1252 | E25: 1256 | F25: 1189 | G25: 1588 | H25: 1568 | I25: 1667 | J25: 1336 | K25: 1042 | L25: 1006 | M25: =+M5+M14 -> 983 | N25: 1008 | O25: 1118 | P25: =+SUM(B25:O25) -> 17584
B26: =+SUM(B5+B14) -> 1372 | C26: =+SUM(C5+C14) -> 1199 | D26: =+SUM(D5+D14) -> 1252 | E26: =+SUM(E5+E14) -> 1256 | F26: =+SUM(F5+F14) -> 1189 | G26: =+SUM(G5+G14) -> 1588 | H26: =+SUM(H5+H14) -> 1568 | I26: =+SUM(I5+I14) -> 1667 | ... O26: =+SUM(O5+O14) -> 1118 | P26: =+SUM(B26:O26) -> 17584
B27: =+B26=B25 -> TRUE | C27: =+C26=C25 -> TRUE | D27: =+D26=D25 -> TRUE | E27: =+E26=E25 -> TRUE | F27: =+F26=F25 -> TRUE | G27: =+G26=G25 -> TRUE | H27: =+H26=H25 -> TRUE | I27: =+I26=I25 -> TRUE | ... P27: =+P26=P25 -> TRUE

Sheet Gráfico 15
A1: Tabla NO | B1: 15
A2: Nombre | B2: Usuarios que han tomado el servicio de transporte desde 2019 a 2025-1
B4: 2019 | C4: 2020 | D4: 2021 | E4: 2022 | F4: 2023 | G4: 2024 | H4: 2025-1 | I4: 2025-2 | J4: 2026-1
A5: Usuarios que han tomado el servicio de transporte desde 2019 a 2024-1 | B5: 82579 | C5: 11244 | D5: 4137 | E5: 9852 | F5: 22774 | G5: 29900 | H5: 12000 | I5: 12901 | J5: 11488

Sheet Tabla 136
A1: Tabla NO | B1: 136
A2: Nombre | B2: Investigación asociada a proyección social 2019-1 a 2026-1
A4: Año | B4: Proyectos de Creación | C4: Proyectos de Innovación o DT | D4: Proyectos de Semillero | E4: Proyectos de Investigación Aplicada
A5: 2019 | E5: 23
A6: 2020 | D6: 26 | E6: 44
A7: 2021 | C7: 1 | D7: 21 | E7: 38
A8: 2022 | B8: 10 | C8: 2 | D8: 8 | E8: 36
A9: 2023 | B9: 8 | C9: 3 | D9: 9 | E9: 33
A10: 2024 | B10: 7 | C10: 3 | D10: 8 | E10: 24
A11: 2025 | B11: 2 | C11: 0 | D11: 1 | E11: 7
A12: 2026-1
A13: Total | B13: =SUM(B5:B11) -> 27 | C13: =SUM(C5:C11) -> 9 | D13: =SUM(D5:D11) -> 73 | E13: =SUM(E5:E11) -> 205

Sheet Tabla 138
A1: Tabla NO | B1: 138
A2: Nombre | B2: Semilleros asociados a proyección social 2019-2026-1
A4: Semilleros | B4: 2019 | C4: 2020 | D4: 2021 | E4: 2022 | F4: 2023 | G4: 2024 | H4: 2025 | I4: 2026-1
A5: Relación con sector externo | B5: 36 | C5: 52 | D5: 51 | E5: 44 | F5: 57 | G5: 52 | H5: 41 | I5: 40
A6: Total Semilleros Poli | B6: 106 | C6: 127 | D6: 133 | E6: 124 | F6: 133 | G6: 124 | H6: 115 | I6: 122
A7: % Semilleros relacionados con sector externo | B7: 0.34 | C7: 0.409 | D7: 0.383 | E7: 0.355 | F7: 0.429 | G7: 0.413 | H7: =H5/H6 -> 0.35652174 | I7: =I5/I6 -> 0.32786885

Sheet Tabla 139
A1: Tabla NO | B1: 139
A2: Nombre | B2: Trabajos de grado que han aportado a la solución de problemas en el entorno
A4: Trabajos de grado basados en proyectos sociales | B4: 2019 | C4: 2020 | D4: 2021 | E4: 2022 | F4: 2023 | G4: 2024 | H4: 2025 | I4: 2026-1
B5: 12 | C5: 20 | D5: 14 | E5: 31 | F5: 117 | G5: 30 | H5: 8

Sheet Tabla 144
A1: Tabla NO | B1: 144
A2: Nombre | B2: Convenios por países 2025
A4: PAÍS | B4: TOTAL | C4: ACTIVO | E4: PAÍS | F4: TOTAL | G4: ACTIVO
A5: Argentina | B5: 9 | C5: 7 | E5: Honduras | F5: 1 | G5: 1
A6: Austria | B6: 1 | C6: 1 | E6: India | F6: 1 | G6: 1
A7: Brasil | B7: 6 | C7: 6 | E7: Japón | F7: 1 | G7: 1
A8: Canadá | B8: 2 | C8: 2 | E8: México | F8: 28 | G8: 25
A9: Chile | B9: 5 | C9: 5 | E9: Panamá | F9: 2 | G9: 2
A10: Colombia | B10: 42 | C10: 38 | E10: Paraguay | F10: 2 | G10: 2
A11: Costa Rica | B11: 3 | C11: 3 | E11: Perú | F11: 4 | G11: 4
A12: Croacia | B12: 1 | C12: 1 | E12: Puerto Rico | F12: 1 | G12: 1
A13: Ecuador | B13: 3 | C13: 3 | E13: República Dominicana | F13: 1 | G13: 1
A14: España | B14: 22 | C14: 20 | E14: Rumania | F14: 1 | G14: 1
A15: Estados Unidos | B15: 5 | C15: 5 | E15: Rusia | F15: 1 | G15: 1
A16: Francia | B16: 3 | C16: 3 | E16: Suiza | F16: 1 | G16: 1
... A18: Holanda | B18: 1 | C18: 1 | E18: TOTAL | F18: 149 | G18: 138
A21: Tabla NO | B21: 144
A22: Nombre | B22: Convenios por países 2026-1
A24: PAÍS | B24: TOTAL | C24: ACTIVO | E24: PAÍS | F24: TOTAL | G24: ACTIVO
A25: Argentina | E25: Honduras
A26: Austria | E26: India
A27: Brasil | E27: Japón
A28: Canadá | E28: México
A29: Chile | E29: Panamá
A30: Colombia | E30: Paraguay
A31: Costa Rica | E31: Perú
A32: Croacia | E32: Puerto Rico
A33: Ecuador | E33: República Dominicana
A34: España | E34: Rumania
A35: Estados Unidos | E35: Rusia
A36: Francia | E36: Suiza
... A38: Holanda | E38: TOTAL

Sheet Tabla 145
A1: Tabla NO | B1: 145
A2: Nombre | B2: Número de clases espejo y estudiantes que participaron en estos espacios
A4: Clases Espejo | B4: 2019-2 | C4: 2020-1 | D4: 2020-2 | E4: 2021-1 | F4: 2021-2 | G4: 2022-1 | H4: 2022-2 | I4: 2023-1 | J4: 2023-2 | K4: 2024-1 | L4: 2024-2 | M4: 2025-1 | N4: 2025-2 | O4: 2026-1 | P4: Total
A5: No. Clases Espejo | B5: 13 | C5: 100 | D5: 86 | E5: 112 | F5: 108 | G5: 93 | H5: 106 | I5: 88 | J5: 68 | K5: 97 | L5: 97 | M5: 101 | P5: =+SUM(B5:O5) -> 1069
A6: No. Estudiantes Participantes | B6: 103 | C6: 3620 | D6: 2059 | E6: 4912 | F6: 4269 | G6: 2561 | H6: 2893 | I6: 2638 | J6: 1401 | K6: 3376 | L6: 3747 | M6: 2493 | P6: =+SUM(B6:O6) -> 34072

Sheet Tabla 147
A1: Tabla NO | B1: 147
A2: Nombre | B2: Número de estudiantes con reconocimientos académicos por medio de seminarios internacionales virtuales, doble titulación, intercambio virtual
A4: Actividad | B4: 2019-2 | C4: 2020-1 | D4: 2020-2 | E4: 2021-1 | F4: 2021-2 | G4: 2022-1 | H4: 2022-2 | I4: 2023-1 | J4: 2023-2 | K4: 2024-1 | L4: 2024-2 | M4: 2025-1 | N4: 2025-2 | O4: 2026-1 | P4: TOTAL
A5: Seminarios Internacionales Virtuales | B5: 0 | C5: 29 | D5: 1305 | E5: 217 | F5: 321 | G5: 353 | H5: 176 | I5: 196 | J5: 104 | K5: 231 | L5: 136 | M5: 160 | P5: =+SUM(B5:O5) -> 3228
A6: Doble Titulación | B6: 7 | C6: 1 | D6: 0 | E6: 1 | F6: 38 | G6: 69 | H6: 20 | I6: 36 | J6: 99 | K6: 22 | L6: 61 | M6: 93 | P6: =+SUM(B6:O6) -> 447
A7: Intercambio Virtual | B7: 4 | C7: 0 | D7: 0 | E7: 88 | F7: 126 | G7: 60 | H7: 81 | I7: 173 | J7: 194 | K7: 199 | L7: 305 | M7: 309 | P7: =+SUM(B7:O7) -> 1539
A8: Total | B8: 11 | C8: 30 | D8: 1305 | E8: 306 | F8: 485 | G8: 482 | H8: 277 | I8: 405 | J8: 397 | K8: 452 | L8: 502 | M8: 562 | N8: =SUM(N5:N7) -> 0 | O8: =SUM(O5:O7) -> 0 | P8: =+SUM(B8:O8) -> 5214

Sheet Tabla 148
A1: Tabla NO | B1: 148
A2: Nombre | B2: Número de profesores y expertos invitados
A4: Tipo de movilidad del invitado | B4: 2019-2 | C4: 2020-1 | D4: 2020-2 | E4: 2021-1 | F4: 2021-2 | G4: 2022-1 | H4: 2022-2 | I4: 2023-1 | J4: 2023-2 | K4: 2024-1 | L4: 2024-2 | M4: 2025-1 | N4: 2025-2 | O4: 2026-1 | P4: TOTAL
A5: Presencial | B5: 38 | C5: 12 | D5: 0 | E5: 0 | F5: 0 | G5: 9 | H5: 36 | I5: 13 | J5: 44 | K5: 15 | L5: 41 | M5: 60 | P5: =+SUM(B5:O5) -> 268
A6: Virtual | B6: 0 | C6: 12 | D6: 106 | E6: 213 | F6: 191 | G6: 179 | H6: 313 | I6: 50 | J6: 156 | K6: 37 | L6: 93 | M6: 88 | P6: =+SUM(B6:O6) -> 1438
A7: Total | B7: 38 | C7: 24 | D7: 106 | E7: 213 | F7: 191 | G7: 188 | H7: 349 | I7: 63 | J7: 200 | K7: 52 | L7: 134 | M7: 148 | P7: =+SUM(B7:O7) -> 1706

Sheet Tabla 149
A1: Tabla NO | B1: 149
A2: Nombre | B2: Número de estudiantes en internacionalización en casa
A4: Semestre | B4: Encuentro con extranjeros | C4: Conversatorio con extranjeros | D4: Cátedra internacional | E4: País invitado | F4: Centro de Idiomas | G4: Total
A5: 2019-2 | B5: 44 | C5: 51 | D5: 0 | E5: 0 | G5: 95
A6: 2020-1 | B6: 0 | C6: 915 | D6: 0 | E6: 726 | G6: 1641
A7: 2020-2 | B7: 137 | C7: 0 | D7: 99 | E7: 0 | G7: 236
A8: 2021-1 | B8: 0 | C8: 360 | D8: 0 | E8: 661 | G8: 1021
A9: 2021-2 | B9: 84 | C9: 0 | D9: 113 | E9: 0 | G9: 197
A10: 2022-1 | B10: 0 | C10: 536 | D10: 0 | E10: 486 | G10: 1022
A11: 2022-2 | B11: 29 | C11: 0 | D11: 438 | E11: 0 | G11: 467
A12: 2023-1 | B12: 0 | C12: 115 | D12: 0 | E12: 0 | G12: 115
A13: 2023-2 | B13: 46 | C13: 0 | D13: 77 | E13: 0 | G13: 123
A14: 2024-1 | B14: 0 | C14: 87 | D14: 0 | E14: 0 | G14: 87
A15: 2024-2 | B15: 5 | C15: 0 | D15: 128 | E15: 0 | F15: 1769 | G15: 1902
A16: 2025-1 | B16: 0 | C16: 98 | D16: 0 | E16: 637 | F16: 10780 | G16: 11515
A17: 2025-2
A18: 2026-1
A19: Total | B19: =+SUM(B5:B18) -> 345 | C19: =+SUM(C5:C18) -> 2162 | D19: =+SUM(D5:D18) -> 855 | E19: =+SUM(E5:E18) -> 2510 | F19: =+SUM(F5:F18) -> 12549 | G19: =+SUM(G5:G18) -> 18421

Sheet Tabla 150
A1: Tabla NO | B1: 150
A2: Nombre | B2: Número de estudiantes en cursos de idiomas
A4: CURSOS | B4: 2019-2 | C4: 2020-1 | D4: 2020-2 | E4: 2021-1 | F4: 2021-2 | G4: 2022-1 | H4: 2022-2 | I4: 2023-1 | J4: 2023-2 | K4: 2024-1 | L4: 2024-2 | M4: 2025-1 | N4: 2025-2 | O4: 2026-1 | P4: Total
A5: Inglés como electiva | B5: 602 | C5: 1206 | D5: 1534 | E5: 780 | F5: 1199 | G5: 1008 | H5: 802 | I5: 666 | J5: 559 | K5: 581 | L5: 579 | M5: 771 | P5: =+SUM(B5:O5) -> 10287
A6: Francés | B6: 108 | C6: 83 | D6: 100 | E6: 100 | F6: 120 | G6: 63 | H6: 41 | I6: 44 | J6: 26 | K6: 40 | L6: 278 | M6: 73 | P6: =+SUM(B6:O6) -> 1076
A7: Portugués | B7: 90 | C7: 65 | D7: 63 | E7: 48 | F7: 43 | G7: 25 | H7: 18 | I7: 11 | J7: 25 | K7: 30 | L7: 30 | M7: 104 | P7: =+SUM(B7:O7) -> 552
A8: Mandarín | B8: 16 | C8: 25 | D8: 25 | E8: 0 | F8: 0 | G8: 0 | H8: 31 | I8: 50 | J8: 42 | K8: 36 | L8: 30 | M8: 38 | P8: =+SUM(B8:O8) -> 293
A9: Inglés virtual | B9: 713 | C9: 702 | D9: 678 | E9: 1978 | F9: 1507 | G9: 1357 | H9: 1250 | I9: 1292 | J9: 749 | K9: 851 | L9: 492 | M9: 530 | P9: =+SUM(B9:O9) -> 12099
A10: Italiano | B10: 0 | C10: 0 | D10: 0 | E10: 0 | F10: 0 | G10: 0 | H10: 0 | I10: 0 | J10: 0 | K10: 0 | L10: 0 | M10: 67 | P10: =+SUM(B10:O10) -> 67
A11: Total | B11: 1529 | C11: 2081 | D11: 2400 | E11: 2906 | F11: 2869 | G11: 2453 | H11: 2142 | I11: 2063 | J11: 1401 | K11: 1538 | L11: 1409 | M11: 1583 | N11: =SUM(N5:N10) -> 0 | O11: =SUM(O5:O10) -> 0 | P11: =+SUM(B11:O11) -> 24374

Sheet Tabla 151
A1: Tabla NO | B1: 151
A2: Nombre | B2: Número de convenios con ICETEX para asistentes extranjeros
A4: Período | B4: # Convenios | C4: País de origen | D4: Apoyo idioma
A5: 2019-2020 | B5: 3 | C5: Francia | D5: Francés
C6: India | D6: Inglés
C7: China | D7: Mandarín
A8: 2020-2021 | B8: 3 | C8: Francia | D8: Francés
C9: India | D9: Inglés
C10: China | D10: Mandarín
A11: 2021-2022 | B11: 3 | C11: Reino Unido | D11: Inglés
C12: China | D12: Mandarín
C13: Francia | D13: Francés
A14: 2022-2023 | B14: 3 | C14: Francia | D14: Francés
C15: Reino Unido | D15: Inglés
C16: China | D16: Mandarín
A17: 2023-2024 | B17: 2 | C17: Reino Unido | D17: Inglés
C18: China | D18: Mandarín
A19: 2024-2025 | B19: 2 | C19: Reino Unido | D19: Inglés
C20: China | D20: Mandarín
A21: 2025-2026
A23: Total | B23: 16

Sheet Gráfico 16
A1: Tabla NO | B1: 16
A2: Nombre | B2: Evolución bilingüismo profesores
B4: A1 | C4: A2 | D4: B1 | E4: B2 | F4: C1 | G4: C2
A5: 2019 | B5: 30 | C5: 31 | D5: 19 | E5: 40 | F5: 32 | G5: 8
A6: 2020 | B6: 55 | C6: 56 | D6: 30 | E6: 36 | F6: 53 | G6: 13
A7: 2021 | B7: 70 | C7: 65 | D7: 26 | E7: 34 | F7: 78 | G7: 22
A8: 2022 | B8: 81 | C8: 52 | D8: 23 | E8: 30 | F8: 87 | G8: 20
A9: 2023 | B9: 71 | C9: 63 | D9: 23 | E9: 39 | F9: 78 | G9: 19
A10: 2024 | B10: 52 | C10: 57 | D10: 64 | E10: 91 | F10: 76 | G10: 18
A11: 2025 | B11: 26 | C11: 28 | D11: 37 | E11: 60 | F11: 40 | G11: 14
A12: 2026

Sheet Tabla 152
A1: Tabla NO | B1: 152
A2: Nombre | B2: Número de eventos académicos desde y para la academia
A4: Modalidad del evento | B4: 2019-2 | C4: 2020-1 | D4: 2020-2 | E4: 2021-1 | F4: 2021-2 | G4: 2022-1 | H4: 2022-2 | I4: 2023-1 | J4: 2023-2 | K4: 2024-1 | L4: 2024-2 | M4: 2025-1 | N4: 2025-2 | O4: 2026-1 | P4: TOTAL
A5: Presencial | B5: 10 | C5: 3 | D5: 4 | E5: 2 | F5: 3 | G5: 3 | H5: 21 | I5: 8 | J5: 24 | K5: 16 | L5: 69 | M5: 32 | P5: =+SUM(B5:O5) -> 195
A6: Virtual | B6: 1 | C6: 7 | D6: 19 | E6: 26 | F6: 22 | G6: 8 | H6: 22 | I6: 21 | J6: 58 | K6: 17 | L6: 26 | M6: 13 | P6: =+SUM(B6:O6) -> 240
A7: Total | B7: 11 | C7: 10 | D7: 23 | E7: 28 | F7: 25 | G7: 11 | H7: 43 | I7: 29 | J7: 82 | K7: 33 | L7: 95 | M7: 45 | N7: =SUM(N5:N6) -> 0 | O7: =SUM(O5:O6) -> 0 | P7: =+SUM(B7:O7) -> 435

Sheet Tabla 153
A1: Tabla NO | B1: 153
A2: Nombre | B2: Contenido del Poli para otros
A4: Actividades | B4: 2021-1 | C4: 2021-2 | D4: 2022-1 | E4: 2022-2 | F4: 2023-1 | G4: 2023-2 | H4: 2024-1 | I4: 2024-2 | J4: 2025-1 | K4: 2025-2 | L4: 2026-1 | M4: TOTAL
A5: No. de eventos | B5: 7 | C5: 13 | D5: 6 | E5: 8 | F5: 10 | G5: 10 | H5: 11 | I5: 7 | J5: 13 | M5: =+SUM(B5:L5) -> 85
A6: No. de participantes | B6: 345 | C6: 1097 | D6: 219 | E6: 1017 | F6: 1322 | G6: 494 | H6: 525 | I6: 248 | J6: 707 | M6: =+SUM(B6:L6) -> 5974

Sheet Tabla 154
A1: Tabla NO | B1: 154
A2: Nombre | B2: Actividades en las regiones
A5: AÑO | B5: ACTIVIDAD | C5: CIUDAD | D5: DESCRIPCIÓN ACTIVIDAD
